Workbook
Name AcceptableRisk: '2. Enterprise Parameters'!$E$35
Name AcceptableRisk1: 'Enterprise Parameters -EXAMPLE'!$E$35
Name Asset_Classes: Table10[[#Data],[Asset Classes]]
Name Industry: tblVCDBIndex[Asset Class]
Name Industry: tblVCDBIndex[Asset Class]
Name Industry: tblVCDBIndex[Asset Class]
Name Industry: tblVCDBIndex[Asset Class]
Name Industry: tblVCDBIndex[Asset Class]
Name Maturity_Score: tblMaturityScores[Maturity Scores]
Name Maturity_Score: tblMaturityScores[Maturity Scores]
Name Maturity_Score: tblMaturityScores[Maturity Scores]
Name Maturity_Score: tblMaturityScores[Maturity Scores]
Name Maturity_Score: tblMaturityScores[Maturity Scores]

Sheet Cover

Sheet MIS 595
C6: This workbook has been edited to work with the MIS 595 class. Several columns in the Risk Register were removed to simplify matters.

Sheet 1. Impact Criteria Survey 
D2: Prompt | E2: Response
B3: 1 | C3: Mission | D3: How would you concisely describe the benefit that your enterprise provides your customers, clients, constituents, or the public? This is why they engage in this risk with you. | E3: Fabella Bank exists to provide secure, reliable, and accessible financial services to customers in the Springfield area. Its mission is to protect customer funds, support financial growth, and maintain trust through safe and modern banking technology.
C5: Instructions: Imagine that your enterprise suffers a cybersecurity or information security incident. Describe in the spaces provided below how you would determine that the impacts to your mission were acceptable, or unacceptable.
C7: Impact Magnitude | D7: Prompt | E7: Response
C8: Negligible | D8: What observable evidence would you have that your mission - as you defined it above - would be unaffected? | E8: A small disruption occurs but does not affect customers or the bank’s ability to serve them.
C9: Acceptable | D9: What observable evidence would you have that your mission would be compromised, but it would not require correction? | E9: The bank can still achieve its mission with little or no impact on customer trust
C10: Unacceptable | D10: What observable evidence would you have that your mission would be compromised in a way that would require correction, but the correction could be achieved through the normal course of business? | E10: The bank must reinvest time or money to fix the situation before it can continue serving customers reliably
C11: High | D11: What observable evidence would you have that your mission would be compromised so badly that extraordinary efforts would be required to restore it? | E11: The bank’s ability to provide services is significantly affected for an extended time.
C12: Catastrophic | D12: What observable evidence would you have that your mission would be compromised so badly that it could not be achieved? | E12: The bank cannot achieve its mission, and customer trust is severely damaged.
D15: Prompt | E15: Response
B16: 2 | C16: Operational Objectives | D16: What business or organizational goals does the enterprise attempt to achieve? | E16: • Keep banking systems like MYBANK, ERP, ATMs, and mobile apps running smoothly. • Protect customer and employee information from unauthorized access. • Ensure daily operations such as deposits, withdrawals, loan processing, payroll, and reporting run without disruption. • Maintain compliance with financial and cybersecurity regulations.
C18: Instructions: Imagine that your enterprise suffers a cybersecurity or information security incident. Describe in the spaces provided below how you would determine that the impacts to your operational objectives were acceptable, or unacceptable.
C20: Impact Magnitude | D20: Prompt | E20: Response
C21: Negligible | D21: What observable evidence would you have that your operational objectives - as you defined them above - would be unaffected? | E21: Routine work may slow down briefly but returns to normal without extra effort.
C22: Acceptable | D22: What observable evidence would you have that your operational objectives would be compromised, but it would not require correction? | E22: Minor issues may require small adjustments but no major cost or downtime
C23: Unacceptable | D23: What observable evidence would you have that your operational objectives would be compromised in a way that would require correction, but the correction could be achieved through the normal course of business? | E23: Operations are disrupted enough that extra resources or overtime work are needed to catch up.
C24: High | D24: What observable evidence would you have that your operational objectives would be compromised so badly that extraordinary efforts would be required to restore them? | E24: Key systems become unavailable, causing major downtime, financial loss, or regulatory concerns.
C25: Catastrophic | D25: What observable evidence would you have that your operational objectives would be compromised so badly that they could not be achieved? | E25: Critical systems fail completely, operations stop, and recovery requires full restoration efforts
D28: Prompt | E28: Response
B29: 3 | C29: Financial Objectives | D29: What are the unexpected cost outlays that your enterprise could or could not tolerate? | E29: Not Applicable for MIS 595 Course
C31: Instructions: Imagine that your enterprise suffers a cybersecurity or information security incident. Describe in the spaces provided below how you would determine that the impacts to your financial objectives were acceptable, or unacceptable.
C33: Impact Magnitude | D33: Prompt | E33: Response
C34: Negligible | D34: What observable evidence would you have that your financial objectives - as you defined them above - would be unaffected? | E34: Not Applicable for MIS 595 Course
C35: Acceptable | D35: What observable evidence would you have that your financial objectives would be compromised, but it would not require correction? | E35: Not Applicable for MIS 595 Course
C36: Unacceptable | D36: What observable evidence would you have that your financial objectives would be compromised in a way that would require correction, but the correction could be achieved through the normal course of business? | E36: Not Applicable for MIS 595 Course
C37: High | D37: What observable evidence would you have that your financial objectives would be compromised so badly that extraordinary efforts would be required to restore them? | E37: Not Applicable for MIS 595 Course
C38: Catastrophic | D38: Leave this blank
D41: Prompt | E41: Response
B42: 4 | C42: Obligations | D42: What harm may foreseeably come to others as a result of a cybersecurity incident? | E42: • Protect customer data (PII, account details, transactions). • Ensure fair and uninterrupted access to financial services. • Report breaches or outages to regulators when required. • Prevent harm to customers, employees, and third-party partners
C44: Instructions: Imagine that your enterprise suffers a cybersecurity or information security incident. Describe in the spaces provided below how you would determine that the impacts to your obligations (harm, to others) were acceptable, or unacceptable.
C46: Impact Magnitude | D46: Prompt | E46: Response
C47: Negligible | D47: Describe a condition where others would not be harmed. | E47: No harm to customers or partners; no regulatory action required.
C48: Acceptable | D48: Describe a condition where others would not be harmed to a degree that required correction or compensation. | E48: No harm to customers, and any inconvenience is easily corrected.
C49: Unacceptable | D49: Describe a condition where one or few others would be harmed to a degree that you could correct. | E49: Customers or partners may experience temporary harm or delayed services, but the harm is fixable.
C50: High | D50: Describe a condition where many others would be harmed to a degree that you could correct, or where few others are harmed to a degree that others would always have a small degree of impairment. | E50: Customers may face real impacts such as delayed transactions, financial stress, or other risks.
C51: Catastrophic | D51: Describe a condition where others would be irreparably harmed. | E51: Harm to customers or partners is long-lasting or not fully correctable; regulators may intervene.

Sheet 2. Enterprise Parameters
B2: 1 | C2: Enterprise Risk Assessment Criteria | D2: Enterprise Name | E2: BANK NAME
D3: Scope | E3: ALL BRANCHES
D4: Last Completed (Date) | E4: 45053
B8: 2 | C8: Impact Criteria
C10: Impact Scores | D10: Mission | E10: Operational Objectives | F10: Financial Objectives | G10: Obligations
C11: Definition | D11: Fabella Bank exists to provide secure, reliable, and accessible financial services to customers in the Springfield area. Its mission is to protect customer funds, support financial growth, and maintain trust through safe and modern banking technology | E11: =IF(ISBLANK('1. Impact Criteria Survey '!E16),"",'1. Impact Criteria Survey '!E16) -> • Keep banking systems like MYBANK, ERP, ATMs, and mobile apps running smoothly. • Protect customer and employee information from unauthorized access. • Ensure daily operations such as deposits, withdrawals, loan processing, payroll, and reporting run without disruption. • Maintain compliance with financial and cybersecurity regulations. | F11: =IF(ISBLANK('1. Impact Criteria Survey '!E29),"",'1. Impact Criteria Survey '!E29) -> Not Applicable for MIS 595 Course | G11: =IF(ISBLANK('1. Impact Criteria Survey '!E42),"",'1. Impact Criteria Survey '!E42) -> • Protect customer data (PII, account details, transactions). • Ensure fair and uninterrupted access to financial services. • Report breaches or outages to regulators when required. • Prevent harm to customers, employees, and third-party partners
C12: 1. Negligible | D12: =IF(ISBLANK('1. Impact Criteria Survey '!E8),"",'1. Impact Criteria Survey '!E8) -> A small disruption occurs but does not affect customers or the bank’s ability to serve them. | E12: =IF(ISBLANK('1. Impact Criteria Survey '!E21),"",'1. Impact Criteria Survey '!E21) -> Routine work may slow down briefly but returns to normal without extra effort. | F12: =IF(ISBLANK('1. Impact Criteria Survey '!E34),"",'1. Impact Criteria Survey '!E34) -> Not Applicable for MIS 595 Course | G12: =IF(ISBLANK('1. Impact Criteria Survey '!E47),"",'1. Impact Criteria Survey '!E47) -> No harm to customers or partners; no regulatory action required.
C13: 2. Acceptable | D13: =IF(ISBLANK('1. Impact Criteria Survey '!E9),"",'1. Impact Criteria Survey '!E9) -> The bank can still achieve its mission with little or no impact on customer trust | E13: =IF(ISBLANK('1. Impact Criteria Survey '!E22),"",'1. Impact Criteria Survey '!E22) -> Minor issues may require small adjustments but no major cost or downtime | F13: =IF(ISBLANK('1. Impact Criteria Survey '!E35),"",'1. Impact Criteria Survey '!E35) -> Not Applicable for MIS 595 Course | G13: =IF(ISBLANK('1. Impact Criteria Survey '!E48),"",'1. Impact Criteria Survey '!E48) -> No harm to customers, and any inconvenience is easily corrected.
C14: 3. Unacceptable | D14: =IF(ISBLANK('1. Impact Criteria Survey '!E10),"",'1. Impact Criteria Survey '!E10) -> The bank must reinvest time or money to fix the situation before it can continue serving customers reliably | E14: =IF(ISBLANK('1. Impact Criteria Survey '!E23),"",'1. Impact Criteria Survey '!E23) -> Operations are disrupted enough that extra resources or overtime work are needed to catch up. | F14: =IF(ISBLANK('1. Impact Criteria Survey '!E36),"",'1. Impact Criteria Survey '!E36) -> Not Applicable for MIS 595 Course | G14: =IF(ISBLANK('1. Impact Criteria Survey '!E49),"",'1. Impact Criteria Survey '!E49) -> Customers or partners may experience temporary harm or delayed services, but the harm is fixable.
C15: 4. High | D15: =IF(ISBLANK('1. Impact Criteria Survey '!E11),"",'1. Impact Criteria Survey '!E11) -> The bank’s ability to provide services is significantly affected for an extended time. | E15: =IF(ISBLANK('1. Impact Criteria Survey '!E24),"",'1. Impact Criteria Survey '!E24) -> Key systems become unavailable, causing major downtime, financial loss, or regulatory concerns. | F15: =IF(ISBLANK('1. Impact Criteria Survey '!E37),"",'1. Impact Criteria Survey '!E37) -> Not Applicable for MIS 595 Course | G15: =IF(ISBLANK('1. Impact Criteria Survey '!E50),"",'1. Impact Criteria Survey '!E50) -> Customers may face real impacts such as delayed transactions, financial stress, or other risks.
C16: 5. Catastrophic | D16: =IF(ISBLANK('1. Impact Criteria Survey '!E12),"",'1. Impact Criteria Survey '!E12) -> The bank cannot achieve its mission, and customer trust is severely damaged. | E16: =IF(ISBLANK('1. Impact Criteria Survey '!E25),"",'1. Impact Criteria Survey '!E25) -> Critical systems fail completely, operations stop, and recovery requires full restoration efforts | F16: =IF(ISBLANK('1. Impact Criteria Survey '!E38),"",'1. Impact Criteria Survey '!E38) | G16: =IF(ISBLANK('1. Impact Criteria Survey '!E51),"",'1. Impact Criteria Survey '!E51) -> Harm to customers or partners is long-lasting or not fully correctable; regulators may intervene.
B20: 3 | C20: Expectancy Criteria
C22: Expectancy Score | D22: Expectancy | E22: Criteria
C23: 1 | D23: Remote | E23: Safeguard would reliably prevent the threat.
C24: 2 | D24: Unlikely | E24: Safeguard would reliably prevent most occurrences of the threat.
C25: 3 | D25: As likely as not | E25: Safeguard would prevent as many threat occurrences as it would miss.
C26: 4 | D26: Likely | E26: Safeguard would prevent few threat occurrences.
C27: 5 | D27: Certain | E27: Safeguard would not prevent threat occurrences.
B31: 4 | C31: Risk Acceptance Criteria
C33: We would start to invest against risks to prevent this expectancy and impact, or higher. | D33: Expectancy | E33: Impact
D34: 3 | E34: 3
D35: Acceptable Risk is less than … | E35: =D34*E34 -> 9
B39: 5 | C39: Inherent Risk Criteria | D39: What is the highest impact to the Mission, Operational Objectives, Financial Objectives, and Obligations that each Asset Type could cause? The "Enterprise" Asset Class will automatically use the highest Impact Score you provide for the assets below.
C41: Asset Class | D41: Mission Impact | E41: Operational Objectives Impact | F41: Financial Objectives Impact | G41: Obligations Impact
C42: Enterprise | D42: =IF(MAX(D43:D47)=0,"",MAX(D43:D47)) -> 5 | E42: =IF(MAX(E43:E47)=0,"",MAX(E43:E47)) -> 5 | F42: 1 | G42: =IF(MAX(G43:G47)=0,"",MAX(G43:G47)) -> 5
C43: Devices | D43: 3 | E43: 3 | F43: 1 | G43: 3
C44: Applications | D44: 3 | E44: 4 | F44: 1 | G44: 4
C45: Data | D45: 4 | E45: 4 | F45: 1 | G45: 4
C46: Network | D46: 4 | E46: 5 | F46: 1 | G46: 5
C47: Users | D47: 5 | E47: 5 | F47: 1 | G47: 5

Sheet 3b. Risk Register Controls v8
B2: Enterprise Risk Assessment Criteria | D2: Enterprise Name | E2: FABELLA BANK
D3: Scope | E3: =IF(ISBLANK('2. Enterprise Parameters'!E3),"",'2. Enterprise Parameters'!E3) -> ALL BRANCHES
D4: Last Completed (Date) | E4: Wednesday, December 10, 2025
B8: Risk Register | D8: Risk Analysis | U8: Risk Register | V8: Risk Treatment | AM8: Reasonable Annual Cost
B9: For MIS 595 - we will only focus on a handful of the controls - filtered with column C
B10: Asset Class | C10: MIS 595 Focused Controls | D10: CIS Safeguard #2 | E10: CIS Safeguard Title | F10: Our Implementation | G10: Vulnerabilities | H10: Safeguard Maturity Score | I10: VCDB Index | J10: Expectancy Score | K10: Impact to Mission | L10: Impact to Operational Objectives | M10: Impact to Financial Objectives | N10: Impact to Obligations | O10: Risk Score | P10: Risk Level | Q10: Risk Treatment Option | R10: Risk Treatment Safeguard | S10: Risk Treatment Safeguard Title | T10: Risk Treatment Safeguard Description | U10: Our Planned Implementation | V10: Risk Treatment Safeguard Maturity Score | W10: Risk Treatment Safeguard Expectancy Score | X10: Risk Treatment Safeguard Impact to Mission | Y10: Risk Treatment Safeguard Impact to Operational Objectives | Z10: Risk Treatment Safeguard Impact to Financial Objectives | AA10: Risk Treatment Safeguard Impact to Obligations | AB10: Risk Treatment Safeguard Risk Score | AC10: Reasonable and Acceptable | AD10: Risk Treatment Safeguard Cost | AE10: Implementation Quarter | AF10: Implementation Year | AH10: Impact to Financial Objectives | AI10: Year | AJ10: Reasonable?
B11: Devices | C11: MIS 595 Focus | D11: 1.1 | E11: Establish and Maintain Detailed Enterprise Asset Inventory | F11: We maintain a centralized asset inventory using automated discovery tools to track all devices across Fabella Bank. | G11: No Vulnerability | H11: 5 | I11: =IFERROR(VLOOKUP(tblRiskRegister32[[#This Row],[Asset Class]],tblVCDBIndex[],4,FALSE),"") -> 1 | J11: =IFERROR(VLOOKUP(10*tblRiskRegister32[[#This Row],[Safeguard Maturity Score]]+tblRiskRegister32[[#This Row],[VCDB Index]],tblHITIndexWeightTable[],4,FALSE),"") -> 1 | K11: =VLOOKUP(tblRiskRegister32[[#This Row],[Asset Class]],tblInherentImpacts30[],2,FALSE) -> 3 | L11: =VLOOKUP(tblRiskRegister32[[#This Row],[Asset Class]],tblInherentImpacts30[],3,FALSE) -> 3 | M11: =VLOOKUP(tblRiskRegister32[[#This Row],[Asset Class]],tblInherentImpacts30[],4,FALSE) -> 1 | N11: =VLOOKUP(tblRiskRegister32[[#This Row],[Asset Class]],tblInherentImpacts30[],5,FALSE) -> 3 | O11: =IFERROR(MAX(tblRiskRegister32[[#This Row],[Impact to Mission]:[Impact to Obligations]])*tblRiskRegister32[[#This Row],[Expectancy Score]],"") -> 3 | P11: =tblRiskRegister32[[#This Row],[Risk Score]] -> 3 | Q11: Accept | R11: 1.1 | S11: Establish and Maintain Detailed Enterprise Asset Inventory | T11: Establish and maintain an accurate, detailed, and up-to-date inventory of all enterprise assets with the potential to store or process data, to include: end-user devices (including portable and mobile), network devices, non-computing/IoT devices, and servers. Ensure the inventory records the network address (if static), hardware address, machine name, enterprise asset owner, department for each asset, and whether the asset has been approved to connect to the network. For mobile end-user devices, MDM type tools can support this process, where appropriate. This inventory includes assets connected to the infrastructure physically, virtually, remotely, and those within cloud environments. Additionally, it includes assets that are regularly connected to the enterprise’s network infrastructure, even if they are not under control of the enterprise. Review and update the inventory of all enterprise assets bi-annually, or more frequently. | W11: =IFERROR(VLOOKUP(10*tblRiskRegister32[[#This Row],[Risk Treatment Safeguard Maturity Score]]+tblRiskRegister32[[#This Row],[VCDB Index]],tblHITIndexWeightTable[],4,FALSE),"") | X11: =VLOOKUP(tblRiskRegister32[[#This Row],[Asset Class]],tblInherentImpacts30[],2,FALSE) -> 3 | Y11: =VLOOKUP(tblRiskRegister32[[#This Row],[Asset Class]],tblInherentImpacts30[],3,FALSE) -> 3 | Z11: =VLOOKUP(tblRiskRegister32[[#This Row],[Asset Class]],tblInherentImpacts30[],3,FALSE) -> 3 | AA11: =VLOOKUP(tblRiskRegister32[[#This Row],[Asset Class]],tblInherentImpacts30[],4,FALSE) -> 1 | AB11: =IFERROR(MAX(tblRiskRegister32[[#This Row],[Risk Treatment Safeguard Impact to Mission]:[Risk Treatment Safeguard Impact to Obligations]])*tblRiskRegister32[[#This Row],[Risk Treatment Safeguard Expectancy Score]],"") | AC11: =IF(tblRiskRegister32[[#This Row],[Risk Score]]>AcceptableRisk,IF(tblRiskRegister32[[#This Row],[Risk Treatment Safeguard Risk Score]]<AcceptableRisk, IF(tblRiskRegister32[[#This Row],[Risk Treatment Safeguard Risk Score]]<=tblRiskRegister32[[#This Row],[Risk Score]],"Yes","No"),"No"),"Yes") -> Yes | AH11: =SUMIF(tblRiskRegister32[[#All],[Implementation Year]],"="&tblCostImpacts33[[#This Row],[Year]],tblRiskRegister32[[#All],[Risk Treatment Safeguard Cost]]) -> 0 | AI11: 2021 | AJ11: =IF(tblCostImpacts33[[#This Row],[Impact to Financial Objectives]]<='2. Enterprise Parameters'!$F$13,"Yes","No") -> Yes
B12: Devices | D12: 1.2 | E12: Address Unauthorized Assets | I12: =IFERROR(VLOOKUP(tblRiskRegister32[[#This Row],[Asset Class]],tblVCDBIndex[],4,FALSE),"") -> 1 | J12: =IFERROR(VLOOKUP(10*tblRiskRegister32[[#This Row],[Safeguard Maturity Score]]+tblRiskRegister32[[#This Row],[VCDB Index]],tblHITIndexWeightTable[],4,FALSE),"") | K12: =VLOOKUP(tblRiskRegister32[[#This Row],[Asset Class]],tblInherentImpacts30[],2,FALSE) -> 3 | L12: =VLOOKUP(tblRiskRegister32[[#This Row],[Asset Class]],tblInherentImpacts30[],3,FALSE) -> 3 | M12: =VLOOKUP(tblRiskRegister32[[#This Row],[Asset Class]],tblInherentImpacts30[],4,FALSE) -> 1 | N12: =VLOOKUP(tblRiskRegister32[[#This Row],[Asset Class]],tblInherentImpacts30[],5,FALSE) -> 3 | O12: =IFERROR(MAX(tblRiskRegister32[[#This Row],[Impact to Mission]:[Impact to Obligations]])*tblRiskRegister32[[#This Row],[Expectancy Score]],"") | P12: =tblRiskRegister32[[#This Row],[Risk Score]] | R12: 1.2 | S12: Address Unauthorized Assets | T12: Ensure that a process exists to address unauthorized assets on a weekly basis. The enterprise may choose to remove the asset from the network, deny the asset from connecting remotely to the network, or quarantine the asset. | W12: =IFERROR(VLOOKUP(10*tblRiskRegister32[[#This Row],[Risk Treatment Safeguard Maturity Score]]+tblRiskRegister32[[#This Row],[VCDB Index]],tblHITIndexWeightTable[],4,FALSE),"") | X12: =VLOOKUP(tblRiskRegister32[[#This Row],[Asset Class]],tblInherentImpacts30[],2,FALSE) -> 3 | Y12: =VLOOKUP(tblRiskRegister32[[#This Row],[Asset Class]],tblInherentImpacts30[],3,FALSE) -> 3 | Z12: =VLOOKUP(tblRiskRegister32[[#This Row],[Asset Class]],tblInherentImpacts30[],3,FALSE) -> 3 | AA12: =VLOOKUP(tblRiskRegister32[[#This Row],[Asset Class]],tblInherentImpacts30[],4,FALSE) -> 1 | AB12: =IFERROR(MAX(tblRiskRegister32[[#This Row],[Risk Treatment Safeguard Impact to Mission]:[Risk Treatment Safeguard Impact to Obligations]])*tblRiskRegister32[[#This Row],[Risk Treatment Safeguard Expectancy Score]],"") | AC12: =IF(tblRiskRegister32[[#This Row],[Risk Score]]>AcceptableRisk,IF(tblRiskRegister32[[#This Row],[Risk Treatment Safeguard Risk Score]]<AcceptableRisk, IF(tblRiskRegister32[[#This Row],[Risk Treatment Safeguard Risk Score]]<=tblRiskRegister32[[#This Row],[Risk Score]],"Yes","No"),"No"),"Yes") -> No | AH12: =SUMIF(tblRiskRegister32[[#All],[Implementation Year]],"="&tblCostImpacts33[[#This Row],[Year]],tblRiskRegister32[[#All],[Risk Treatment Safeguard Cost]]) -> 0 | AI12: 2022 | AJ12: =IF(tblCostImpacts33[[#This Row],[Impact to Financial Objectives]]<='2. Enterprise Parameters'!$F$13,"Yes","No") -> Yes
B13: Devices | D13: 1.3 | E13: Utilize an Active Discovery Tool | I13: =IFERROR(VLOOKUP(tblRiskRegister32[[#This Row],[Asset Class]],tblVCDBIndex[],4,FALSE),"") -> 1 | J13: =IFERROR(VLOOKUP(10*tblRiskRegister32[[#This Row],[Safeguard Maturity Score]]+tblRiskRegister32[[#This Row],[VCDB Index]],tblHITIndexWeightTable[],4,FALSE),"") | K13: =VLOOKUP(tblRiskRegister32[[#This Row],[Asset Class]],tblInherentImpacts30[],2,FALSE) -> 3 | L13: =VLOOKUP(tblRiskRegister32[[#This Row],[Asset Class]],tblInherentImpacts30[],3,FALSE) -> 3 | M13: =VLOOKUP(tblRiskRegister32[[#This Row],[Asset Class]],tblInherentImpacts30[],4,FALSE) -> 1 | N13: =VLOOKUP(tblRiskRegister32[[#This Row],[Asset Class]],tblInherentImpacts30[],5,FALSE) -> 3 | O13: =IFERROR(MAX(tblRiskRegister32[[#This Row],[Impact to Mission]:[Impact to Obligations]])*tblRiskRegister32[[#This Row],[Expectancy Score]],"") | P13: =tblRiskRegister32[[#This Row],[Risk Score]] | R13: 1.3 | S13: Utilize an Active Discovery Tool | T13: Utilize an active discovery tool to identify assets connected to the enterprise’s network. Configure the active discovery tool to execute daily, or more frequently. | W13: =IFERROR(VLOOKUP(10*tblRiskRegister32[[#This Row],[Risk Treatment Safeguard Maturity Score]]+tblRiskRegister32[[#This Row],[VCDB Index]],tblHITIndexWeightTable[],4,FALSE),"") | X13: =VLOOKUP(tblRiskRegister32[[#This Row],[Asset Class]],tblInherentImpacts30[],2,FALSE) -> 3 | Y13: =VLOOKUP(tblRiskRegister32[[#This Row],[Asset Class]],tblInherentImpacts30[],3,FALSE) -> 3 | Z13: =VLOOKUP(tblRiskRegister32[[#This Row],[Asset Class]],tblInherentImpacts30[],3,FALSE) -> 3 | AA13: =VLOOKUP(tblRiskRegister32[[#This Row],[Asset Class]],tblInherentImpacts30[],4,FALSE) -> 1 | AB13: =IFERROR(MAX(tblRiskRegister32[[#This Row],[Risk Treatment Safeguard Impact to Mission]:[Risk Treatment Safeguard Impact to Obligations]])*tblRiskRegister32[[#This Row],[Risk Treatment Safeguard Expectancy Score]],"") | AC13: =IF(tblRiskRegister32[[#This Row],[Risk Score]]>AcceptableRisk,IF(tblRiskRegister32[[#This Row],[Risk Treatment Safeguard Risk Score]]<AcceptableRisk, IF(tblRiskRegister32[[#This Row],[Risk Treatment Safeguard Risk Score]]<=tblRiskRegister32[[#This Row],[Risk Score]],"Yes","No"),"No"),"Yes") -> No | AH13: =SUMIF(tblRiskRegister32[[#All],[Implementation Year]],"="&tblCostImpacts33[[#This Row],[Year]],tblRiskRegister32[[#All],[Risk Treatment Safeguard Cost]]) -> 0 | AI13: 2023 | AJ13: =IF(tblCostImpacts33[[#This Row],[Impact to Financial Objectives]]<='2. Enterprise Parameters'!$F$13,"Yes","No") -> Yes
B14: Devices | D14: 1.4 | E14: Use Dynamic Host Configuration Protocol (DHCP) Logging to Update Enterprise Asset Inventory | I14: =IFERROR(VLOOKUP(tblRiskRegister32[[#This Row],[Asset Class]],tblVCDBIndex[],4,FALSE),"") -> 1 | J14: =IFERROR(VLOOKUP(10*tblRiskRegister32[[#This Row],[Safeguard Maturity Score]]+tblRiskRegister32[[#This Row],[VCDB Index]],tblHITIndexWeightTable[],4,FALSE),"") | K14: =VLOOKUP(tblRiskRegister32[[#This Row],[Asset Class]],tblInherentImpacts30[],2,FALSE) -> 3 | L14: =VLOOKUP(tblRiskRegister32[[#This Row],[Asset Class]],tblInherentImpacts30[],3,FALSE) -> 3 | M14: =VLOOKUP(tblRiskRegister32[[#This Row],[Asset Class]],tblInherentImpacts30[],4,FALSE) -> 1 | N14: =VLOOKUP(tblRiskRegister32[[#This Row],[Asset Class]],tblInherentImpacts30[],5,FALSE) -> 3 | O14: =IFERROR(MAX(tblRiskRegister32[[#This Row],[Impact to Mission]:[Impact to Obligations]])*tblRiskRegister32[[#This Row],[Expectancy Score]],"") | P14: =tblRiskRegister32[[#This Row],[Risk Score]] | R14: 1.4 | S14: Use Dynamic Host Configuration Protocol (DHCP) Logging to Update Enterprise Asset Inventory | T14: Use DHCP logging on all DHCP servers or Internet Protocol (IP) address management tools to update the enterprise’s asset inventory. Review and use logs to update the enterprise’s asset inventory weekly, or more frequently. | W14: =IFERROR(VLOOKUP(10*tblRiskRegister32[[#This Row],[Risk Treatment Safeguard Maturity Score]]+tblRiskRegister32[[#This Row],[VCDB Index]],tblHITIndexWeightTable[],4,FALSE),"") | X14: =VLOOKUP(tblRiskRegister32[[#This Row],[Asset Class]],tblInherentImpacts30[],2,FALSE) -> 3 | Y14: =VLOOKUP(tblRiskRegister32[[#This Row],[Asset Class]],tblInherentImpacts30[],3,FALSE) -> 3 | Z14: =VLOOKUP(tblRiskRegister32[[#This Row],[Asset Class]],tblInherentImpacts30[],3,FALSE) -> 3 | AA14: =VLOOKUP(tblRiskRegister32[[#This Row],[Asset Class]],tblInherentImpacts30[],4,FALSE) -> 1 | AB14: =IFERROR(MAX(tblRiskRegister32[[#This Row],[Risk Treatment Safeguard Impact to Mission]:[Risk Treatment Safeguard Impact to Obligations]])*tblRiskRegister32[[#This Row],[Risk Treatment Safeguard Expectancy Score]],"") | AC14: =IF(tblRiskRegister32[[#This Row],[Risk Score]]>AcceptableRisk,IF(tblRiskRegister32[[#This Row],[Risk Treatment Safeguard Risk Score]]<AcceptableRisk, IF(tblRiskRegister32[[#This Row],[Risk Treatment Safeguard Risk Score]]<=tblRiskRegister32[[#This Row],[Risk Score]],"Yes","No"),"No"),"Yes") -> No | AH14: =SUMIF(tblRiskRegister32[[#All],[Implementation Year]],"="&tblCostImpacts33[[#This Row],[Year]],tblRiskRegister32[[#All],[Risk Treatment Safeguard Cost]]) -> 0 | AI14: 2024 | AJ14: =IF(tblCostImpacts33[[#This Row],[Impact to Financial Objectives]]<='2. Enterprise Parameters'!$F$13,"Yes","No") -> Yes
B15: Applications | D15: 2.1 | E15: Establish and Maintain a Software Inventory | I15: =IFERROR(VLOOKUP(tblRiskRegister32[[#This Row],[Asset Class]],tblVCDBIndex[],4,FALSE),"") -> 2 | J15: =IFERROR(VLOOKUP(10*tblRiskRegister32[[#This Row],[Safeguard Maturity Score]]+tblRiskRegister32[[#This Row],[VCDB Index]],tblHITIndexWeightTable[],4,FALSE),"") | K15: =VLOOKUP(tblRiskRegister32[[#This Row],[Asset Class]],tblInherentImpacts30[],2,FALSE) -> 3 | L15: =VLOOKUP(tblRiskRegister32[[#This Row],[Asset Class]],tblInherentImpacts30[],3,FALSE) -> 4 | M15: =VLOOKUP(tblRiskRegister32[[#This Row],[Asset Class]],tblInherentImpacts30[],4,FALSE) -> 1 | N15: =VLOOKUP(tblRiskRegister32[[#This Row],[Asset Class]],tblInherentImpacts30[],5,FALSE) -> 4 | O15: =IFERROR(MAX(tblRiskRegister32[[#This Row],[Impact to Mission]:[Impact to Obligations]])*tblRiskRegister32[[#This Row],[Expectancy Score]],"") | P15: =tblRiskRegister32[[#This Row],[Risk Score]] | R15: 2.1 | S15: Establish and Maintain a Software Inventory | T15: Establish and maintain a detailed inventory of all licensed software installed on enterprise assets. The software inventory must document the title, publisher, initial install/use date, and business purpose for each entry; where appropriate, include the Uniform Resource Locator (URL), app store(s), version(s), deployment mechanism, and decommission date. Review and update the software inventory bi-annually, or more frequently. | W15: =IFERROR(VLOOKUP(10*tblRiskRegister32[[#This Row],[Risk Treatment Safeguard Maturity Score]]+tblRiskRegister32[[#This Row],[VCDB Index]],tblHITIndexWeightTable[],4,FALSE),"") | X15: =VLOOKUP(tblRiskRegister32[[#This Row],[Asset Class]],tblInherentImpacts30[],2,FALSE) -> 3 | Y15: =VLOOKUP(tblRiskRegister32[[#This Row],[Asset Class]],tblInherentImpacts30[],3,FALSE) -> 4 | Z15: =VLOOKUP(tblRiskRegister32[[#This Row],[Asset Class]],tblInherentImpacts30[],3,FALSE) -> 4 | AA15: =VLOOKUP(tblRiskRegister32[[#This Row],[Asset Class]],tblInherentImpacts30[],4,FALSE) -> 1 | AB15: =IFERROR(MAX(tblRiskRegister32[[#This Row],[Risk Treatment Safeguard Impact to Mission]:[Risk Treatment Safeguard Impact to Obligations]])*tblRiskRegister32[[#This Row],[Risk Treatment Safeguard Expectancy Score]],"") | AC15: =IF(tblRiskRegister32[[#This Row],[Risk Score]]>AcceptableRisk,IF(tblRiskRegister32[[#This Row],[Risk Treatment Safeguard Risk Score]]<AcceptableRisk, IF(tblRiskRegister32[[#This Row],[Risk Treatment Safeguard Risk Score]]<=tblRiskRegister32[[#This Row],[Risk Score]],"Yes","No"),"No"),"Yes") -> No | AH15: =SUMIF(tblRiskRegister32[[#All],[Implementation Year]],"="&tblCostImpacts33[[#This Row],[Year]],tblRiskRegister32[[#All],[Risk Treatment Safeguard Cost]]) -> 0 | AI15: 2025 | AJ15: =IF(tblCostImpacts33[[#This Row],[Impact to Financial Objectives]]<='2. Enterprise Parameters'!$F$13,"Yes","No") -> Yes
B16: Applications | D16: 2.2 | E16: Ensure Authorized Software is Currently Supported | I16: =IFERROR(VLOOKUP(tblRiskRegister32[[#This Row],[Asset Class]],tblVCDBIndex[],4,FALSE),"") -> 2 | J16: =IFERROR(VLOOKUP(10*tblRiskRegister32[[#This Row],[Safeguard Maturity Score]]+tblRiskRegister32[[#This Row],[VCDB Index]],tblHITIndexWeightTable[],4,FALSE),"") | K16: =VLOOKUP(tblRiskRegister32[[#This Row],[Asset Class]],tblInherentImpacts30[],2,FALSE) -> 3 | L16: =VLOOKUP(tblRiskRegister32[[#This Row],[Asset Class]],tblInherentImpacts30[],3,FALSE) -> 4 | M16: =VLOOKUP(tblRiskRegister32[[#This Row],[Asset Class]],tblInherentImpacts30[],4,FALSE) -> 1 | N16: =VLOOKUP(tblRiskRegister32[[#This Row],[Asset Class]],tblInherentImpacts30[],5,FALSE) -> 4 | O16: =IFERROR(MAX(tblRiskRegister32[[#This Row],[Impact to Mission]:[Impact to Obligations]])*tblRiskRegister32[[#This Row],[Expectancy Score]],"") | P16: =tblRiskRegister32[[#This Row],[Risk Score]] | R16: 2.2 | S16: Ensure Authorized Software is Currently Supported | T16: Ensure that only currently supported software is designated as authorized in the software inventory for enterprise assets. If software is unsupported, yet necessary for the fulfillment of the enterprise’s mission, document an exception detailing mitigating controls and residual risk acceptance. For any unsupported software without an exception documentation, designate as unauthorized. Review the software list to verify software support at least monthly, or more frequently. | W16: =IFERROR(VLOOKUP(10*tblRiskRegister32[[#This Row],[Risk Treatment Safeguard Maturity Score]]+tblRiskRegister32[[#This Row],[VCDB Index]],tblHITIndexWeightTable[],4,FALSE),"") | X16: =VLOOKUP(tblRiskRegister32[[#This Row],[Asset Class]],tblInherentImpacts30[],2,FALSE) -> 3 | Y16: =VLOOKUP(tblRiskRegister32[[#This Row],[Asset Class]],tblInherentImpacts30[],3,FALSE) -> 4 | Z16: =VLOOKUP(tblRiskRegister32[[#This Row],[Asset Class]],tblInherentImpacts30[],3,FALSE) -> 4 | AA16: =VLOOKUP(tblRiskRegister32[[#This Row],[Asset Class]],tblInherentImpacts30[],4,FALSE) -> 1 | AB16: =IFERROR(MAX(tblRiskRegister32[[#This Row],[Risk Treatment Safeguard Impact to Mission]:[Risk Treatment Safeguard Impact to Obligations]])*tblRiskRegister32[[#This Row],[Risk Treatment Safeguard Expectancy Score]],"") | AC16: =IF(tblRiskRegister32[[#This Row],[Risk Score]]>AcceptableRisk,IF(tblRiskRegister32[[#This Row],[Risk Treatment Safeguard Risk Score]]<AcceptableRisk, IF(tblRiskRegister32[[#This Row],[Risk Treatment Safeguard Risk Score]]<=tblRiskRegister32[[#This Row],[Risk Score]],"Yes","No"),"No"),"Yes") -> No | AH16: =SUMIF(tblRiskRegister32[[#All],[Implementation Year]],"="&tblCostImpacts33[[#This Row],[Year]],tblRiskRegister32[[#All],[Risk Treatment Safeguard Cost]]) -> 0 | AI16: 2026 | AJ16: =IF(tblCostImpacts33[[#This Row],[Impact to Financial Objectives]]<='2. Enterprise Parameters'!$F$13,"Yes","No") -> Yes
B17: Applications | D17: 2.3 | E17: Address Unauthorized Software | I17: =IFERROR(VLOOKUP(tblRiskRegister32[[#This Row],[Asset Class]],tblVCDBIndex[],4,FALSE),"") -> 2 | J17: =IFERROR(VLOOKUP(10*tblRiskRegister32[[#This Row],[Safeguard Maturity Score]]+tblRiskRegister32[[#This Row],[VCDB Index]],tblHITIndexWeightTable[],4,FALSE),"") | K17: =VLOOKUP(tblRiskRegister32[[#This Row],[Asset Class]],tblInherentImpacts30[],2,FALSE) -> 3 | L17: =VLOOKUP(tblRiskRegister32[[#This Row],[Asset Class]],tblInherentImpacts30[],3,FALSE) -> 4 | M17: =VLOOKUP(tblRiskRegister32[[#This Row],[Asset Class]],tblInherentImpacts30[],4,FALSE) -> 1 | N17: =VLOOKUP(tblRiskRegister32[[#This Row],[Asset Class]],tblInherentImpacts30[],5,FALSE) -> 4 | O17: =IFERROR(MAX(tblRiskRegister32[[#This Row],[Impact to Mission]:[Impact to Obligations]])*tblRiskRegister32[[#This Row],[Expectancy Score]],"") | P17: =tblRiskRegister32[[#This Row],[Risk Score]] | R17: 2.3 | S17: Address Unauthorized Software | T17: Ensure that unauthorized software is either removed from use on enterprise assets or receives a documented exception. Review monthly, or more frequently. | W17: =IFERROR(VLOOKUP(10*tblRiskRegister32[[#This Row],[Risk Treatment Safeguard Maturity Score]]+tblRiskRegister32[[#This Row],[VCDB Index]],tblHITIndexWeightTable[],4,FALSE),"") | X17: =VLOOKUP(tblRiskRegister32[[#This Row],[Asset Class]],tblInherentImpacts30[],2,FALSE) -> 3 | Y17: =VLOOKUP(tblRiskRegister32[[#This Row],[Asset Class]],tblInherentImpacts30[],3,FALSE) -> 4 | Z17: =VLOOKUP(tblRiskRegister32[[#This Row],[Asset Class]],tblInherentImpacts30[],3,FALSE) -> 4 | AA17: =VLOOKUP(tblRiskRegister32[[#This Row],[Asset Class]],tblInherentImpacts30[],4,FALSE) -> 1 | AB17: =IFERROR(MAX(tblRiskRegister32[[#This Row],[Risk Treatment Safeguard Impact to Mission]:[Risk Treatment Safeguard Impact to Obligations]])*tblRiskRegister32[[#This Row],[Risk Treatment Safeguard Expectancy Score]],"") | AC17: =IF(tblRiskRegister32[[#This Row],[Risk Score]]>AcceptableRisk,IF(tblRiskRegister32[[#This Row],[Risk Treatment Safeguard Risk Score]]<AcceptableRisk, IF(tblRiskRegister32[[#This Row],[Risk Treatment Safeguard Risk Score]]<=tblRiskRegister32[[#This Row],[Risk Score]],"Yes","No"),"No"),"Yes") -> No | AH17: =SUMIF(tblRiskRegister32[[#All],[Implementation Year]],"="&tblCostImpacts33[[#This Row],[Year]],tblRiskRegister32[[#All],[Risk Treatment Safeguard Cost]]) -> 0 | AI17: 2027 | AJ17: =IF(tblCostImpacts33[[#This Row],[Impact to Financial Objectives]]<='2. Enterprise Parameters'!$F$13,"Yes","No") -> Yes
B18: Applications | D18: 2.4 | E18: Utilize Automated Software Inventory Tools | I18: =IFERROR(VLOOKUP(tblRiskRegister32[[#This Row],[Asset Class]],tblVCDBIndex[],4,FALSE),"") -> 2 | J18: =IFERROR(VLOOKUP(10*tblRiskRegister32[[#This Row],[Safeguard Maturity Score]]+tblRiskRegister32[[#This Row],[VCDB Index]],tblHITIndexWeightTable[],4,FALSE),"") | K18: =VLOOKUP(tblRiskRegister32[[#This Row],[Asset Class]],tblInherentImpacts30[],2,FALSE) -> 3 | L18: =VLOOKUP(tblRiskRegister32[[#This Row],[Asset Class]],tblInherentImpacts30[],3,FALSE) -> 4 | M18: =VLOOKUP(tblRiskRegister32[[#This Row],[Asset Class]],tblInherentImpacts30[],4,FALSE) -> 1 | N18: =VLOOKUP(tblRiskRegister32[[#This Row],[Asset Class]],tblInherentImpacts30[],5,FALSE) -> 4 | O18: =IFERROR(MAX(tblRiskRegister32[[#This Row],[Impact to Mission]:[Impact to Obligations]])*tblRiskRegister32[[#This Row],[Expectancy Score]],"") | P18: =tblRiskRegister32[[#This Row],[Risk Score]] | R18: 2.4 | S18: Utilize Automated Software Inventory Tools | T18: Utilize software inventory tools, when possible, throughout the enterprise to automate the discovery and documentation of installed software. | W18: =IFERROR(VLOOKUP(10*tblRiskRegister32[[#This Row],[Risk Treatment Safeguard Maturity Score]]+tblRiskRegister32[[#This Row],[VCDB Index]],tblHITIndexWeightTable[],4,FALSE),"") | X18: =VLOOKUP(tblRiskRegister32[[#This Row],[Asset Class]],tblInherentImpacts30[],2,FALSE) -> 3 | Y18: =VLOOKUP(tblRiskRegister32[[#This Row],[Asset Class]],tblInherentImpacts30[],3,FALSE) -> 4 | Z18: =VLOOKUP(tblRiskRegister32[[#This Row],[Asset Class]],tblInherentImpacts30[],3,FALSE) -> 4 | AA18: =VLOOKUP(tblRiskRegister32[[#This Row],[Asset Class]],tblInherentImpacts30[],4,FALSE) -> 1 | AB18: =IFERROR(MAX(tblRiskRegister32[[#This Row],[Risk Treatment Safeguard Impact to Mission]:[Risk Treatment Safeguard Impact to Obligations]])*tblRiskRegister32[[#This Row],[Risk Treatment Safeguard Expectancy Score]],"") | AC18: =IF(tblRiskRegister32[[#This Row],[Risk Score]]>AcceptableRisk,IF(tblRiskRegister32[[#This Row],[Risk Treatment Safeguard Risk Score]]<AcceptableRisk, IF(tblRiskRegister32[[#This Row],[Risk Treatment Safeguard Risk Score]]<=tblRiskRegister32[[#This Row],[Risk Score]],"Yes","No"),"No"),"Yes") -> No | AH18: =SUMIF(tblRiskRegister32[[#All],[Implementation Year]],"="&tblCostImpacts33[[#This Row],[Year]],tblRiskRegister32[[#All],[Risk Treatment Safeguard Cost]]) -> 0 | AI18: 2028 | AJ18: =IF(tblCostImpacts33[[#This Row],[Impact to Financial Objectives]]<='2. Enterprise Parameters'!$F$13,"Yes","No") -> Yes
B19: Applications | D19: 2.5 | E19: Allowlist Authorized Software | I19: =IFERROR(VLOOKUP(tblRiskRegister32[[#This Row],[Asset Class]],tblVCDBIndex[],4,FALSE),"") -> 2 | J19: =IFERROR(VLOOKUP(10*tblRiskRegister32[[#This Row],[Safeguard Maturity Score]]+tblRiskRegister32[[#This Row],[VCDB Index]],tblHITIndexWeightTable[],4,FALSE),"") | K19: =VLOOKUP(tblRiskRegister32[[#This Row],[Asset Class]],tblInherentImpacts30[],2,FALSE) -> 3 | L19: =VLOOKUP(tblRiskRegister32[[#This Row],[Asset Class]],tblInherentImpacts30[],3,FALSE) -> 4 | M19: =VLOOKUP(tblRiskRegister32[[#This Row],[Asset Class]],tblInherentImpacts30[],4,FALSE) -> 1 | N19: =VLOOKUP(tblRiskRegister32[[#This Row],[Asset Class]],tblInherentImpacts30[],5,FALSE) -> 4 | O19: =IFERROR(MAX(tblRiskRegister32[[#This Row],[Impact to Mission]:[Impact to Obligations]])*tblRiskRegister32[[#This Row],[Expectancy Score]],"") | P19: =tblRiskRegister32[[#This Row],[Risk Score]] | R19: 2.5 | S19: Allowlist Authorized Software | T19: Use technical controls, such as application allowlisting, to ensure that only authorized software can execute or be accessed. Reassess bi-annually, or more frequently. | W19: =IFERROR(VLOOKUP(10*tblRiskRegister32[[#This Row],[Risk Treatment Safeguard Maturity Score]]+tblRiskRegister32[[#This Row],[VCDB Index]],tblHITIndexWeightTable[],4,FALSE),"") | X19: =VLOOKUP(tblRiskRegister32[[#This Row],[Asset Class]],tblInherentImpacts30[],2,FALSE) -> 3 | Y19: =VLOOKUP(tblRiskRegister32[[#This Row],[Asset Class]],tblInherentImpacts30[],3,FALSE) -> 4 | Z19: =VLOOKUP(tblRiskRegister32[[#This Row],[Asset Class]],tblInherentImpacts30[],3,FALSE) -> 4 | AA19: =VLOOKUP(tblRiskRegister32[[#This Row],[Asset Class]],tblInherentImpacts30[],4,FALSE) -> 1 | AB19: =IFERROR(MAX(tblRiskRegister32[[#This Row],[Risk Treatment Safeguard Impact to Mission]:[Risk Treatment Safeguard Impact to Obligations]])*tblRiskRegister32[[#This Row],[Risk Treatment Safeguard Expectancy Score]],"") | AC19: =IF(tblRiskRegister32[[#This Row],[Risk Score]]>AcceptableRisk,IF(tblRiskRegister32[[#This Row],[Risk Treatment Safeguard Risk Score]]<AcceptableRisk, IF(tblRiskRegister32[[#This Row],[Risk Treatment Safeguard Risk Score]]<=tblRiskRegister32[[#This Row],[Risk Score]],"Yes","No"),"No"),"Yes") -> No | AH19: =SUMIF(tblRiskRegister32[[#All],[Implementation Year]],"="&tblCostImpacts33[[#This Row],[Year]],tblRiskRegister32[[#All],[Risk Treatment Safeguard Cost]]) -> 0 | AI19: 2029 | AJ19: =IF(tblCostImpacts33[[#This Row],[Impact to Financial Objectives]]<='2. Enterprise Parameters'!$F$13,"Yes","No") -> Yes
B20: Applications | D20: 2.6 | E20: Allowlist Authorized Libraries | I20: =IFERROR(VLOOKUP(tblRiskRegister32[[#This Row],[Asset Class]],tblVCDBIndex[],4,FALSE),"") -> 2 | J20: =IFERROR(VLOOKUP(10*tblRiskRegister32[[#This Row],[Safeguard Maturity Score]]+tblRiskRegister32[[#This Row],[VCDB Index]],tblHITIndexWeightTable[],4,FALSE),"") | K20: =VLOOKUP(tblRiskRegister32[[#This Row],[Asset Class]],tblInherentImpacts30[],2,FALSE) -> 3 | L20: =VLOOKUP(tblRiskRegister32[[#This Row],[Asset Class]],tblInherentImpacts30[],3,FALSE) -> 4 | M20: =VLOOKUP(tblRiskRegister32[[#This Row],[Asset Class]],tblInherentImpacts30[],4,FALSE) -> 1 | N20: =VLOOKUP(tblRiskRegister32[[#This Row],[Asset Class]],tblInherentImpacts30[],5,FALSE) -> 4 | O20: =IFERROR(MAX(tblRiskRegister32[[#This Row],[Impact to Mission]:[Impact to Obligations]])*tblRiskRegister32[[#This Row],[Expectancy Score]],"") | P20: =tblRiskRegister32[[#This Row],[Risk Score]] | R20: 2.6 | S20: Allowlist Authorized Libraries | T20: Use technical controls to ensure that only authorized software libraries, such as specific .dll, .ocx, .so, etc., files, are allowed to load into a system process. Block unauthorized libraries from loading into a system process. Reassess bi-annually, or more frequently. | W20: =IFERROR(VLOOKUP(10*tblRiskRegister32[[#This Row],[Risk Treatment Safeguard Maturity Score]]+tblRiskRegister32[[#This Row],[VCDB Index]],tblHITIndexWeightTable[],4,FALSE),"") | X20: =VLOOKUP(tblRiskRegister32[[#This Row],[Asset Class]],tblInherentImpacts30[],2,FALSE) -> 3 | Y20: =VLOOKUP(tblRiskRegister32[[#This Row],[Asset Class]],tblInherentImpacts30[],3,FALSE) -> 4 | Z20: =VLOOKUP(tblRiskRegister32[[#This Row],[Asset Class]],tblInherentImpacts30[],3,FALSE) -> 4 | AA20: =VLOOKUP(tblRiskRegister32[[#This Row],[Asset Class]],tblInherentImpacts30[],4,FALSE) -> 1 | AB20: =IFERROR(MAX(tblRiskRegister32[[#This Row],[Risk Treatment Safeguard Impact to Mission]:[Risk Treatment Safeguard Impact to Obligations]])*tblRiskRegister32[[#This Row],[Risk Treatment Safeguard Expectancy Score]],"") | AC20: =IF(tblRiskRegister32[[#This Row],[Risk Score]]>AcceptableRisk,IF(tblRiskRegister32[[#This Row],[Risk Treatment Safeguard Risk Score]]<AcceptableRisk, IF(tblRiskRegister32[[#This Row],[Risk Treatment Safeguard Risk Score]]<=tblRiskRegister32[[#This Row],[Risk Score]],"Yes","No"),"No"),"Yes") -> No | AH20: =SUMIF(tblRiskRegister32[[#All],[Implementation Year]],"="&tblCostImpacts33[[#This Row],[Year]],tblRiskRegister32[[#All],[Risk Treatment Safeguard Cost]]) -> 0 | AI20: 2030 | AJ20: =IF(tblCostImpacts33[[#This Row],[Impact to Financial Objectives]]<='2. Enterprise Parameters'!$F$13,"Yes","No") -> Yes
B21: Data | D21: 3.1 | E21: Establish and Maintain a Data Management Process | I21: =IFERROR(VLOOKUP(tblRiskRegister32[[#This Row],[Asset Class]],tblVCDBIndex[],4,FALSE),"") -> 3 | J21: =IFERROR(VLOOKUP(10*tblRiskRegister32[[#This Row],[Safeguard Maturity Score]]+tblRiskRegister32[[#This Row],[VCDB Index]],tblHITIndexWeightTable[],4,FALSE),"") | K21: =VLOOKUP(tblRiskRegister32[[#This Row],[Asset Class]],tblInherentImpacts30[],2,FALSE) -> 4 | L21: =VLOOKUP(tblRiskRegister32[[#This Row],[Asset Class]],tblInherentImpacts30[],3,FALSE) -> 4 | M21: =VLOOKUP(tblRiskRegister32[[#This Row],[Asset Class]],tblInherentImpacts30[],4,FALSE) -> 1 | N21: =VLOOKUP(tblRiskRegister32[[#This Row],[Asset Class]],tblInherentImpacts30[],5,FALSE) -> 4 | O21: =IFERROR(MAX(tblRiskRegister32[[#This Row],[Impact to Mission]:[Impact to Obligations]])*tblRiskRegister32[[#This Row],[Expectancy Score]],"") | P21: =tblRiskRegister32[[#This Row],[Risk Score]] | R21: 3.1 | S21: Establish and Maintain a Data Management Process | T21: Establish and maintain a data management process. In the process, address data sensitivity, data owner, handling of data, data retention limits, and disposal requirements, based on sensitivity and retention standards for the enterprise. Review and update documentation annually, or when significant enterprise changes occur that could impact this Safeguard. | W21: =IFERROR(VLOOKUP(10*tblRiskRegister32[[#This Row],[Risk Treatment Safeguard Maturity Score]]+tblRiskRegister32[[#This Row],[VCDB Index]],tblHITIndexWeightTable[],4,FALSE),"") | X21: =VLOOKUP(tblRiskRegister32[[#This Row],[Asset Class]],tblInherentImpacts30[],2,FALSE) -> 4 | Y21: =VLOOKUP(tblRiskRegister32[[#This Row],[Asset Class]],tblInherentImpacts30[],3,FALSE) -> 4 | Z21: =VLOOKUP(tblRiskRegister32[[#This Row],[Asset Class]],tblInherentImpacts30[],3,FALSE) -> 4 | AA21: =VLOOKUP(tblRiskRegister32[[#This Row],[Asset Class]],tblInherentImpacts30[],4,FALSE) -> 1 | AB21: =IFERROR(MAX(tblRiskRegister32[[#This Row],[Risk Treatment Safeguard Impact to Mission]:[Risk Treatment Safeguard Impact to Obligations]])*tblRiskRegister32[[#This Row],[Risk Treatment Safeguard Expectancy Score]],"") | AC21: =IF(tblRiskRegister32[[#This Row],[Risk Score]]>AcceptableRisk,IF(tblRiskRegister32[[#This Row],[Risk Treatment Safeguard Risk Score]]<AcceptableRisk, IF(tblRiskRegister32[[#This Row],[Risk Treatment Safeguard Risk Score]]<=tblRiskRegister32[[#This Row],[Risk Score]],"Yes","No"),"No"),"Yes") -> No
B22: Data | D22: 3.1 | E22: Encrypt Sensitive Data in Transit | I22: =IFERROR(VLOOKUP(tblRiskRegister32[[#This Row],[Asset Class]],tblVCDBIndex[],4,FALSE),"") -> 3 | J22: =IFERROR(VLOOKUP(10*tblRiskRegister32[[#This Row],[Safeguard Maturity Score]]+tblRiskRegister32[[#This Row],[VCDB Index]],tblHITIndexWeightTable[],4,FALSE),"") | K22: =VLOOKUP(tblRiskRegister32[[#This Row],[Asset Class]],tblInherentImpacts30[],2,FALSE) -> 4 | L22: =VLOOKUP(tblRiskRegister32[[#This Row],[Asset Class]],tblInherentImpacts30[],3,FALSE) -> 4 | M22: =VLOOKUP(tblRiskRegister32[[#This Row],[Asset Class]],tblInherentImpacts30[],4,FALSE) -> 1 | N22: =VLOOKUP(tblRiskRegister32[[#This Row],[Asset Class]],tblInherentImpacts30[],5,FALSE) -> 4 | O22: =IFERROR(MAX(tblRiskRegister32[[#This Row],[Impact to Mission]:[Impact to Obligations]])*tblRiskRegister32[[#This Row],[Expectancy Score]],"") | P22: =tblRiskRegister32[[#This Row],[Risk Score]] | R22: 3.1 | S22: Encrypt Sensitive Data in Transit | T22: Encrypt sensitive data in transit. Example implementations can include: Transport Layer Security (TLS) and Open Secure Shell (OpenSSH). | W22: =IFERROR(VLOOKUP(10*tblRiskRegister32[[#This Row],[Risk Treatment Safeguard Maturity Score]]+tblRiskRegister32[[#This Row],[VCDB Index]],tblHITIndexWeightTable[],4,FALSE),"") | X22: =VLOOKUP(tblRiskRegister32[[#This Row],[Asset Class]],tblInherentImpacts30[],2,FALSE) -> 4 | Y22: =VLOOKUP(tblRiskRegister32[[#This Row],[Asset Class]],tblInherentImpacts30[],3,FALSE) -> 4 | Z22: =VLOOKUP(tblRiskRegister32[[#This Row],[Asset Class]],tblInherentImpacts30[],3,FALSE) -> 4 | AA22: =VLOOKUP(tblRiskRegister32[[#This Row],[Asset Class]],tblInherentImpacts30[],4,FALSE) -> 1 | AB22: =IFERROR(MAX(tblRiskRegister32[[#This Row],[Risk Treatment Safeguard Impact to Mission]:[Risk Treatment Safeguard Impact to Obligations]])*tblRiskRegister32[[#This Row],[Risk Treatment Safeguard Expectancy Score]],"") | AC22: =IF(tblRiskRegister32[[#This Row],[Risk Score]]>AcceptableRisk,IF(tblRiskRegister32[[#This Row],[Risk Treatment Safeguard Risk Score]]<AcceptableRisk, IF(tblRiskRegister32[[#This Row],[Risk Treatment Safeguard Risk Score]]<=tblRiskRegister32[[#This Row],[Risk Score]],"Yes","No"),"No"),"Yes") -> No
B23: Data | C23: MIS 595 Focus | D23: 3.11 | E23: Encrypt Sensitive Data at Rest | F23: Sensitive data stored on bank systems is encrypted using industry-standard AES protocols based on Fabella’s Data Protection Policy. | G23: No Vulnerability | H23: 4 | I23: =IFERROR(VLOOKUP(tblRiskRegister32[[#This Row],[Asset Class]],tblVCDBIndex[],4,FALSE),"") -> 3 | J23: =IFERROR(VLOOKUP(10*tblRiskRegister32[[#This Row],[Safeguard Maturity Score]]+tblRiskRegister32[[#This Row],[VCDB Index]],tblHITIndexWeightTable[],4,FALSE),"") -> 2 | K23: =VLOOKUP(tblRiskRegister32[[#This Row],[Asset Class]],tblInherentImpacts30[],2,FALSE) -> 4 | L23: =VLOOKUP(tblRiskRegister32[[#This Row],[Asset Class]],tblInherentImpacts30[],3,FALSE) -> 4 | M23: =VLOOKUP(tblRiskRegister32[[#This Row],[Asset Class]],tblInherentImpacts30[],4,FALSE) -> 1 | N23: =VLOOKUP(tblRiskRegister32[[#This Row],[Asset Class]],tblInherentImpacts30[],5,FALSE) -> 4 | O23: =IFERROR(MAX(tblRiskRegister32[[#This Row],[Impact to Mission]:[Impact to Obligations]])*tblRiskRegister32[[#This Row],[Expectancy Score]],"") -> 8 | P23: =tblRiskRegister32[[#This Row],[Risk Score]] -> 8 | Q23: Accept | R23: 3.11 | S23: Encrypt Sensitive Data at Rest | T23: Encrypt sensitive data at rest on servers, applications, and databases containing sensitive data. Storage-layer encryption, also known as server-side encryption, meets the minimum requirement of this Safeguard. Additional encryption methods may include application-layer encryption, also known as client-side encryption, where access to the data storage device(s) does not permit access to the plain-text data. | W23: =IFERROR(VLOOKUP(10*tblRiskRegister32[[#This Row],[Risk Treatment Safeguard Maturity Score]]+tblRiskRegister32[[#This Row],[VCDB Index]],tblHITIndexWeightTable[],4,FALSE),"") | X23: =VLOOKUP(tblRiskRegister32[[#This Row],[Asset Class]],tblInherentImpacts30[],2,FALSE) -> 4 | Y23: =VLOOKUP(tblRiskRegister32[[#This Row],[Asset Class]],tblInherentImpacts30[],3,FALSE) -> 4 | Z23: =VLOOKUP(tblRiskRegister32[[#This Row],[Asset Class]],tblInherentImpacts30[],3,FALSE) -> 4 | AA23: =VLOOKUP(tblRiskRegister32[[#This Row],[Asset Class]],tblInherentImpacts30[],4,FALSE) -> 1 | AB23: =IFERROR(MAX(tblRiskRegister32[[#This Row],[Risk Treatment Safeguard Impact to Mission]:[Risk Treatment Safeguard Impact to Obligations]])*tblRiskRegister32[[#This Row],[Risk Treatment Safeguard Expectancy Score]],"") | AC23: =IF(tblRiskRegister32[[#This Row],[Risk Score]]>AcceptableRisk,IF(tblRiskRegister32[[#This Row],[Risk Treatment Safeguard Risk Score]]<AcceptableRisk, IF(tblRiskRegister32[[#This Row],[Risk Treatment Safeguard Risk Score]]<=tblRiskRegister32[[#This Row],[Risk Score]],"Yes","No"),"No"),"Yes") -> Yes
B24: Network | D24: 3.12 | E24: Segment Data Processing and Storage Based on Sensitivity | I24: =IFERROR(VLOOKUP(tblRiskRegister32[[#This Row],[Asset Class]],tblVCDBIndex[],4,FALSE),"") -> 1 | J24: =IFERROR(VLOOKUP(10*tblRiskRegister32[[#This Row],[Safeguard Maturity Score]]+tblRiskRegister32[[#This Row],[VCDB Index]],tblHITIndexWeightTable[],4,FALSE),"") | K24: =VLOOKUP(tblRiskRegister32[[#This Row],[Asset Class]],tblInherentImpacts30[],2,FALSE) -> 4 | L24: =VLOOKUP(tblRiskRegister32[[#This Row],[Asset Class]],tblInherentImpacts30[],3,FALSE) -> 5 | M24: =VLOOKUP(tblRiskRegister32[[#This Row],[Asset Class]],tblInherentImpacts30[],4,FALSE) -> 1 | N24: =VLOOKUP(tblRiskRegister32[[#This Row],[Asset Class]],tblInherentImpacts30[],5,FALSE) -> 5 | O24: =IFERROR(MAX(tblRiskRegister32[[#This Row],[Impact to Mission]:[Impact to Obligations]])*tblRiskRegister32[[#This Row],[Expectancy Score]],"") | P24: =tblRiskRegister32[[#This Row],[Risk Score]] | R24: 3.12 | S24: Segment Data Processing and Storage Based on Sensitivity | T24: Segment data processing and storage based on the sensitivity of the data. Do not process sensitive data on enterprise assets intended for lower sensitivity data. | W24: =IFERROR(VLOOKUP(10*tblRiskRegister32[[#This Row],[Risk Treatment Safeguard Maturity Score]]+tblRiskRegister32[[#This Row],[VCDB Index]],tblHITIndexWeightTable[],4,FALSE),"") | X24: =VLOOKUP(tblRiskRegister32[[#This Row],[Asset Class]],tblInherentImpacts30[],2,FALSE) -> 4 | Y24: =VLOOKUP(tblRiskRegister32[[#This Row],[Asset Class]],tblInherentImpacts30[],3,FALSE) -> 5 | Z24: =VLOOKUP(tblRiskRegister32[[#This Row],[Asset Class]],tblInherentImpacts30[],3,FALSE) -> 5 | AA24: =VLOOKUP(tblRiskRegister32[[#This Row],[Asset Class]],tblInherentImpacts30[],4,FALSE) -> 1 | AB24: =IFERROR(MAX(tblRiskRegister32[[#This Row],[Risk Treatment Safeguard Impact to Mission]:[Risk Treatment Safeguard Impact to Obligations]])*tblRiskRegister32[[#This Row],[Risk Treatment Safeguard Expectancy Score]],"") | AC24: =IF(tblRiskRegister32[[#This Row],[Risk Score]]>AcceptableRisk,IF(tblRiskRegister32[[#This Row],[Risk Treatment Safeguard Risk Score]]<AcceptableRisk, IF(tblRiskRegister32[[#This Row],[Risk Treatment Safeguard Risk Score]]<=tblRiskRegister32[[#This Row],[Risk Score]],"Yes","No"),"No"),"Yes") -> No
B25: Data | D25: 3.2 | E25: Establish and Maintain a Data Inventory | I25: =IFERROR(VLOOKUP(tblRiskRegister32[[#This Row],[Asset Class]],tblVCDBIndex[],4,FALSE),"") -> 3 | J25: =IFERROR(VLOOKUP(10*tblRiskRegister32[[#This Row],[Safeguard Maturity Score]]+tblRiskRegister32[[#This Row],[VCDB Index]],tblHITIndexWeightTable[],4,FALSE),"") | K25: =VLOOKUP(tblRiskRegister32[[#This Row],[Asset Class]],tblInherentImpacts30[],2,FALSE) -> 4 | L25: =VLOOKUP(tblRiskRegister32[[#This Row],[Asset Class]],tblInherentImpacts30[],3,FALSE) -> 4 | M25: =VLOOKUP(tblRiskRegister32[[#This Row],[Asset Class]],tblInherentImpacts30[],4,FALSE) -> 1 | N25: =VLOOKUP(tblRiskRegister32[[#This Row],[Asset Class]],tblInherentImpacts30[],5,FALSE) -> 4 | O25: =IFERROR(MAX(tblRiskRegister32[[#This Row],[Impact to Mission]:[Impact to Obligations]])*tblRiskRegister32[[#This Row],[Expectancy Score]],"") | P25: =tblRiskRegister32[[#This Row],[Risk Score]] | R25: 3.2 | S25: Establish and Maintain a Data Inventory | T25: Establish and maintain a data inventory, based on the enterprise’s data management process. Inventory sensitive data, at a minimum. Review and update inventory annually, at a minimum, with a priority on sensitive data. | W25: =IFERROR(VLOOKUP(10*tblRiskRegister32[[#This Row],[Risk Treatment Safeguard Maturity Score]]+tblRiskRegister32[[#This Row],[VCDB Index]],tblHITIndexWeightTable[],4,FALSE),"") | X25: =VLOOKUP(tblRiskRegister32[[#This Row],[Asset Class]],tblInherentImpacts30[],2,FALSE) -> 4 | Y25: =VLOOKUP(tblRiskRegister32[[#This Row],[Asset Class]],tblInherentImpacts30[],3,FALSE) -> 4 | Z25: =VLOOKUP(tblRiskRegister32[[#This Row],[Asset Class]],tblInherentImpacts30[],3,FALSE) -> 4 | AA25: =VLOOKUP(tblRiskRegister32[[#This Row],[Asset Class]],tblInherentImpacts30[],4,FALSE) -> 1 | AB25: =IFERROR(MAX(tblRiskRegister32[[#This Row],[Risk Treatment Safeguard Impact to Mission]:[Risk Treatment Safeguard Impact to Obligations]])*tblRiskRegister32[[#This Row],[Risk Treatment Safeguard Expectancy Score]],"") | AC25: =IF(tblRiskRegister32[[#This Row],[Risk Score]]>AcceptableRisk,IF(tblRiskRegister32[[#This Row],[Risk Treatment Safeguard Risk Score]]<AcceptableRisk, IF(tblRiskRegister32[[#This Row],[Risk Treatment Safeguard Risk Score]]<=tblRiskRegister32[[#This Row],[Risk Score]],"Yes","No"),"No"),"Yes") -> No
B26: Data | D26: 3.3 | E26: Configure Data Access Control Lists | I26: =IFERROR(VLOOKUP(tblRiskRegister32[[#This Row],[Asset Class]],tblVCDBIndex[],4,FALSE),"") -> 3 | J26: =IFERROR(VLOOKUP(10*tblRiskRegister32[[#This Row],[Safeguard Maturity Score]]+tblRiskRegister32[[#This Row],[VCDB Index]],tblHITIndexWeightTable[],4,FALSE),"") | K26: =VLOOKUP(tblRiskRegister32[[#This Row],[Asset Class]],tblInherentImpacts30[],2,FALSE) -> 4 | L26: =VLOOKUP(tblRiskRegister32[[#This Row],[Asset Class]],tblInherentImpacts30[],3,FALSE) -> 4 | M26: =VLOOKUP(tblRiskRegister32[[#This Row],[Asset Class]],tblInherentImpacts30[],4,FALSE) -> 1 | N26: =VLOOKUP(tblRiskRegister32[[#This Row],[Asset Class]],tblInherentImpacts30[],5,FALSE) -> 4 | O26: =IFERROR(MAX(tblRiskRegister32[[#This Row],[Impact to Mission]:[Impact to Obligations]])*tblRiskRegister32[[#This Row],[Expectancy Score]],"") | P26: =tblRiskRegister32[[#This Row],[Risk Score]] | R26: 3.3 | S26: Configure Data Access Control Lists | T26: Configure data access control lists based on a user’s need to know. Apply data access control lists, also known as access permissions, to local and remote file systems, databases, and applications. | W26: =IFERROR(VLOOKUP(10*tblRiskRegister32[[#This Row],[Risk Treatment Safeguard Maturity Score]]+tblRiskRegister32[[#This Row],[VCDB Index]],tblHITIndexWeightTable[],4,FALSE),"") | X26: =VLOOKUP(tblRiskRegister32[[#This Row],[Asset Class]],tblInherentImpacts30[],2,FALSE) -> 4 | Y26: =VLOOKUP(tblRiskRegister32[[#This Row],[Asset Class]],tblInherentImpacts30[],3,FALSE) -> 4 | Z26: =VLOOKUP(tblRiskRegister32[[#This Row],[Asset Class]],tblInherentImpacts30[],3,FALSE) -> 4 | AA26: =VLOOKUP(tblRiskRegister32[[#This Row],[Asset Class]],tblInherentImpacts30[],4,FALSE) -> 1 | AB26: =IFERROR(MAX(tblRiskRegister32[[#This Row],[Risk Treatment Safeguard Impact to Mission]:[Risk Treatment Safeguard Impact to Obligations]])*tblRiskRegister32[[#This Row],[Risk Treatment Safeguard Expectancy Score]],"") | AC26: =IF(tblRiskRegister32[[#This Row],[Risk Score]]>AcceptableRisk,IF(tblRiskRegister32[[#This Row],[Risk Treatment Safeguard Risk Score]]<AcceptableRisk, IF(tblRiskRegister32[[#This Row],[Risk Treatment Safeguard Risk Score]]<=tblRiskRegister32[[#This Row],[Risk Score]],"Yes","No"),"No"),"Yes") -> No
B27: Data | D27: 3.4 | E27: Enforce Data Retention | I27: =IFERROR(VLOOKUP(tblRiskRegister32[[#This Row],[Asset Class]],tblVCDBIndex[],4,FALSE),"") -> 3 | J27: =IFERROR(VLOOKUP(10*tblRiskRegister32[[#This Row],[Safeguard Maturity Score]]+tblRiskRegister32[[#This Row],[VCDB Index]],tblHITIndexWeightTable[],4,FALSE),"") | K27: =VLOOKUP(tblRiskRegister32[[#This Row],[Asset Class]],tblInherentImpacts30[],2,FALSE) -> 4 | L27: =VLOOKUP(tblRiskRegister32[[#This Row],[Asset Class]],tblInherentImpacts30[],3,FALSE) -> 4 | M27: =VLOOKUP(tblRiskRegister32[[#This Row],[Asset Class]],tblInherentImpacts30[],4,FALSE) -> 1 | N27: =VLOOKUP(tblRiskRegister32[[#This Row],[Asset Class]],tblInherentImpacts30[],5,FALSE) -> 4 | O27: =IFERROR(MAX(tblRiskRegister32[[#This Row],[Impact to Mission]:[Impact to Obligations]])*tblRiskRegister32[[#This Row],[Expectancy Score]],"") | P27: =tblRiskRegister32[[#This Row],[Risk Score]] | R27: 3.4 | S27: Enforce Data Retention | T27: Retain data according to the enterprise’s data management process. Data retention must include both minimum and maximum timelines. | W27: =IFERROR(VLOOKUP(10*tblRiskRegister32[[#This Row],[Risk Treatment Safeguard Maturity Score]]+tblRiskRegister32[[#This Row],[VCDB Index]],tblHITIndexWeightTable[],4,FALSE),"") | X27: =VLOOKUP(tblRiskRegister32[[#This Row],[Asset Class]],tblInherentImpacts30[],2,FALSE) -> 4 | Y27: =VLOOKUP(tblRiskRegister32[[#This Row],[Asset Class]],tblInherentImpacts30[],3,FALSE) -> 4 | Z27: =VLOOKUP(tblRiskRegister32[[#This Row],[Asset Class]],tblInherentImpacts30[],3,FALSE) -> 4 | AA27: =VLOOKUP(tblRiskRegister32[[#This Row],[Asset Class]],tblInherentImpacts30[],4,FALSE) -> 1 | AB27: =IFERROR(MAX(tblRiskRegister32[[#This Row],[Risk Treatment Safeguard Impact to Mission]:[Risk Treatment Safeguard Impact to Obligations]])*tblRiskRegister32[[#This Row],[Risk Treatment Safeguard Expectancy Score]],"") | AC27: =IF(tblRiskRegister32[[#This Row],[Risk Score]]>AcceptableRisk,IF(tblRiskRegister32[[#This Row],[Risk Treatment Safeguard Risk Score]]<AcceptableRisk, IF(tblRiskRegister32[[#This Row],[Risk Treatment Safeguard Risk Score]]<=tblRiskRegister32[[#This Row],[Risk Score]],"Yes","No"),"No"),"Yes") -> No
B28: Data | D28: 3.5 | E28: Securely Dispose of Data | I28: =IFERROR(VLOOKUP(tblRiskRegister32[[#This Row],[Asset Class]],tblVCDBIndex[],4,FALSE),"") -> 3 | J28: =IFERROR(VLOOKUP(10*tblRiskRegister32[[#This Row],[Safeguard Maturity Score]]+tblRiskRegister32[[#This Row],[VCDB Index]],tblHITIndexWeightTable[],4,FALSE),"") | K28: =VLOOKUP(tblRiskRegister32[[#This Row],[Asset Class]],tblInherentImpacts30[],2,FALSE) -> 4 | L28: =VLOOKUP(tblRiskRegister32[[#This Row],[Asset Class]],tblInherentImpacts30[],3,FALSE) -> 4 | M28: =VLOOKUP(tblRiskRegister32[[#This Row],[Asset Class]],tblInherentImpacts30[],4,FALSE) -> 1 | N28: =VLOOKUP(tblRiskRegister32[[#This Row],[Asset Class]],tblInherentImpacts30[],5,FALSE) -> 4 | O28: =IFERROR(MAX(tblRiskRegister32[[#This Row],[Impact to Mission]:[Impact to Obligations]])*tblRiskRegister32[[#This Row],[Expectancy Score]],"") | P28: =tblRiskRegister32[[#This Row],[Risk Score]] | R28: 3.5 | S28: Securely Dispose of Data | T28: Securely dispose of data as outlined in the enterprise’s data management process. Ensure the disposal process and method are commensurate with the data sensitivity. | W28: =IFERROR(VLOOKUP(10*tblRiskRegister32[[#This Row],[Risk Treatment Safeguard Maturity Score]]+tblRiskRegister32[[#This Row],[VCDB Index]],tblHITIndexWeightTable[],4,FALSE),"") | X28: =VLOOKUP(tblRiskRegister32[[#This Row],[Asset Class]],tblInherentImpacts30[],2,FALSE) -> 4 | Y28: =VLOOKUP(tblRiskRegister32[[#This Row],[Asset Class]],tblInherentImpacts30[],3,FALSE) -> 4 | Z28: =VLOOKUP(tblRiskRegister32[[#This Row],[Asset Class]],tblInherentImpacts30[],3,FALSE) -> 4 | AA28: =VLOOKUP(tblRiskRegister32[[#This Row],[Asset Class]],tblInherentImpacts30[],4,FALSE) -> 1 | AB28: =IFERROR(MAX(tblRiskRegister32[[#This Row],[Risk Treatment Safeguard Impact to Mission]:[Risk Treatment Safeguard Impact to Obligations]])*tblRiskRegister32[[#This Row],[Risk Treatment Safeguard Expectancy Score]],"") | AC28: =IF(tblRiskRegister32[[#This Row],[Risk Score]]>AcceptableRisk,IF(tblRiskRegister32[[#This Row],[Risk Treatment Safeguard Risk Score]]<AcceptableRisk, IF(tblRiskRegister32[[#This Row],[Risk Treatment Safeguard Risk Score]]<=tblRiskRegister32[[#This Row],[Risk Score]],"Yes","No"),"No"),"Yes") -> No
B29: Devices | C29: MIS 595 Focus | D29: 3.6 | E29: Encrypt Data on End-User Devices | F29: Laptops and portable devices use full-disk encryption enforced through endpoint security tools. | G29: No Vulnerability | H29: 3 | I29: =IFERROR(VLOOKUP(tblRiskRegister32[[#This Row],[Asset Class]],tblVCDBIndex[],4,FALSE),"") -> 1 | J29: =IFERROR(VLOOKUP(10*tblRiskRegister32[[#This Row],[Safeguard Maturity Score]]+tblRiskRegister32[[#This Row],[VCDB Index]],tblHITIndexWeightTable[],4,FALSE),"") -> 1 | K29: =VLOOKUP(tblRiskRegister32[[#This Row],[Asset Class]],tblInherentImpacts30[],2,FALSE) -> 3 | L29: =VLOOKUP(tblRiskRegister32[[#This Row],[Asset Class]],tblInherentImpacts30[],3,FALSE) -> 3 | M29: =VLOOKUP(tblRiskRegister32[[#This Row],[Asset Class]],tblInherentImpacts30[],4,FALSE) -> 1 | N29: =VLOOKUP(tblRiskRegister32[[#This Row],[Asset Class]],tblInherentImpacts30[],5,FALSE) -> 3 | O29: =IFERROR(MAX(tblRiskRegister32[[#This Row],[Impact to Mission]:[Impact to Obligations]])*tblRiskRegister32[[#This Row],[Expectancy Score]],"") -> 3 | P29: =tblRiskRegister32[[#This Row],[Risk Score]] -> 3 | Q29: Accept | R29: 3.6 | S29: Encrypt Data on End-User Devices | T29: Encrypt data on end-user devices containing sensitive data. Example implementations can include: Windows BitLocker®, Apple FileVault®, Linux® dm-crypt. | W29: =IFERROR(VLOOKUP(10*tblRiskRegister32[[#This Row],[Risk Treatment Safeguard Maturity Score]]+tblRiskRegister32[[#This Row],[VCDB Index]],tblHITIndexWeightTable[],4,FALSE),"") | X29: =VLOOKUP(tblRiskRegister32[[#This Row],[Asset Class]],tblInherentImpacts30[],2,FALSE) -> 3 | Y29: =VLOOKUP(tblRiskRegister32[[#This Row],[Asset Class]],tblInherentImpacts30[],3,FALSE) -> 3 | Z29: =VLOOKUP(tblRiskRegister32[[#This Row],[Asset Class]],tblInherentImpacts30[],3,FALSE) -> 3 | AA29: =VLOOKUP(tblRiskRegister32[[#This Row],[Asset Class]],tblInherentImpacts30[],4,FALSE) -> 1 | AB29: =IFERROR(MAX(tblRiskRegister32[[#This Row],[Risk Treatment Safeguard Impact to Mission]:[Risk Treatment Safeguard Impact to Obligations]])*tblRiskRegister32[[#This Row],[Risk Treatment Safeguard Expectancy Score]],"") | AC29: =IF(tblRiskRegister32[[#This Row],[Risk Score]]>AcceptableRisk,IF(tblRiskRegister32[[#This Row],[Risk Treatment Safeguard Risk Score]]<AcceptableRisk, IF(tblRiskRegister32[[#This Row],[Risk Treatment Safeguard Risk Score]]<=tblRiskRegister32[[#This Row],[Risk Score]],"Yes","No"),"No"),"Yes") -> Yes
B30: Data | D30: 3.7 | E30: Establish and Maintain a Data Classification Scheme | I30: =IFERROR(VLOOKUP(tblRiskRegister32[[#This Row],[Asset Class]],tblVCDBIndex[],4,FALSE),"") -> 3 | J30: =IFERROR(VLOOKUP(10*tblRiskRegister32[[#This Row],[Safeguard Maturity Score]]+tblRiskRegister32[[#This Row],[VCDB Index]],tblHITIndexWeightTable[],4,FALSE),"") | K30: =VLOOKUP(tblRiskRegister32[[#This Row],[Asset Class]],tblInherentImpacts30[],2,FALSE) -> 4 | L30: =VLOOKUP(tblRiskRegister32[[#This Row],[Asset Class]],tblInherentImpacts30[],3,FALSE) -> 4 | M30: =VLOOKUP(tblRiskRegister32[[#This Row],[Asset Class]],tblInherentImpacts30[],4,FALSE) -> 1 | N30: =VLOOKUP(tblRiskRegister32[[#This Row],[Asset Class]],tblInherentImpacts30[],5,FALSE) -> 4 | O30: =IFERROR(MAX(tblRiskRegister32[[#This Row],[Impact to Mission]:[Impact to Obligations]])*tblRiskRegister32[[#This Row],[Expectancy Score]],"") | P30: =tblRiskRegister32[[#This Row],[Risk Score]] | R30: 3.7 | S30: Establish and Maintain a Data Classification Scheme | T30: Establish and maintain an overall data classification scheme for the enterprise. Enterprises may use labels, such as “Sensitive,” “Confidential,” and “Public,” and classify their data according to those labels. Review and update the classification scheme annually, or when significant enterprise changes occur that could impact this Safeguard. | W30: =IFERROR(VLOOKUP(10*tblRiskRegister32[[#This Row],[Risk Treatment Safeguard Maturity Score]]+tblRiskRegister32[[#This Row],[VCDB Index]],tblHITIndexWeightTable[],4,FALSE),"") | X30: =VLOOKUP(tblRiskRegister32[[#This Row],[Asset Class]],tblInherentImpacts30[],2,FALSE) -> 4 | Y30: =VLOOKUP(tblRiskRegister32[[#This Row],[Asset Class]],tblInherentImpacts30[],3,FALSE) -> 4 | Z30: =VLOOKUP(tblRiskRegister32[[#This Row],[Asset Class]],tblInherentImpacts30[],3,FALSE) -> 4 | AA30: =VLOOKUP(tblRiskRegister32[[#This Row],[Asset Class]],tblInherentImpacts30[],4,FALSE) -> 1 | AB30: =IFERROR(MAX(tblRiskRegister32[[#This Row],[Risk Treatment Safeguard Impact to Mission]:[Risk Treatment Safeguard Impact to Obligations]])*tblRiskRegister32[[#This Row],[Risk Treatment Safeguard Expectancy Score]],"") | AC30: =IF(tblRiskRegister32[[#This Row],[Risk Score]]>AcceptableRisk,IF(tblRiskRegister32[[#This Row],[Risk Treatment Safeguard Risk Score]]<AcceptableRisk, IF(tblRiskRegister32[[#This Row],[Risk Treatment Safeguard Risk Score]]<=tblRiskRegister32[[#This Row],[Risk Score]],"Yes","No"),"No"),"Yes") -> No
B31: Data | D31: 3.8 | E31: Document Data Flows | I31: =IFERROR(VLOOKUP(tblRiskRegister32[[#This Row],[Asset Class]],tblVCDBIndex[],4,FALSE),"") -> 3 | J31: =IFERROR(VLOOKUP(10*tblRiskRegister32[[#This Row],[Safeguard Maturity Score]]+tblRiskRegister32[[#This Row],[VCDB Index]],tblHITIndexWeightTable[],4,FALSE),"") | K31: =VLOOKUP(tblRiskRegister32[[#This Row],[Asset Class]],tblInherentImpacts30[],2,FALSE) -> 4 | L31: =VLOOKUP(tblRiskRegister32[[#This Row],[Asset Class]],tblInherentImpacts30[],3,FALSE) -> 4 | M31: =VLOOKUP(tblRiskRegister32[[#This Row],[Asset Class]],tblInherentImpacts30[],4,FALSE) -> 1 | N31: =VLOOKUP(tblRiskRegister32[[#This Row],[Asset Class]],tblInherentImpacts30[],5,FALSE) -> 4 | O31: =IFERROR(MAX(tblRiskRegister32[[#This Row],[Impact to Mission]:[Impact to Obligations]])*tblRiskRegister32[[#This Row],[Expectancy Score]],"") | P31: =tblRiskRegister32[[#This Row],[Risk Score]] | R31: 3.8 | S31: Document Data Flows | T31: Document data flows. Data flow documentation includes service provider data flows and should be based on the enterprise’s data management process. Review and update documentation annually, or when significant enterprise changes occur that could impact this Safeguard. | W31: =IFERROR(VLOOKUP(10*tblRiskRegister32[[#This Row],[Risk Treatment Safeguard Maturity Score]]+tblRiskRegister32[[#This Row],[VCDB Index]],tblHITIndexWeightTable[],4,FALSE),"") | X31: =VLOOKUP(tblRiskRegister32[[#This Row],[Asset Class]],tblInherentImpacts30[],2,FALSE) -> 4 | Y31: =VLOOKUP(tblRiskRegister32[[#This Row],[Asset Class]],tblInherentImpacts30[],3,FALSE) -> 4 | Z31: =VLOOKUP(tblRiskRegister32[[#This Row],[Asset Class]],tblInherentImpacts30[],3,FALSE) -> 4 | AA31: =VLOOKUP(tblRiskRegister32[[#This Row],[Asset Class]],tblInherentImpacts30[],4,FALSE) -> 1 | AB31: =IFERROR(MAX(tblRiskRegister32[[#This Row],[Risk Treatment Safeguard Impact to Mission]:[Risk Treatment Safeguard Impact to Obligations]])*tblRiskRegister32[[#This Row],[Risk Treatment Safeguard Expectancy Score]],"") | AC31: =IF(tblRiskRegister32[[#This Row],[Risk Score]]>AcceptableRisk,IF(tblRiskRegister32[[#This Row],[Risk Treatment Safeguard Risk Score]]<AcceptableRisk, IF(tblRiskRegister32[[#This Row],[Risk Treatment Safeguard Risk Score]]<=tblRiskRegister32[[#This Row],[Risk Score]],"Yes","No"),"No"),"Yes") -> No
B32: Data | D32: 3.9 | E32: Encrypt Data on Removable Media | I32: =IFERROR(VLOOKUP(tblRiskRegister32[[#This Row],[Asset Class]],tblVCDBIndex[],4,FALSE),"") -> 3 | J32: =IFERROR(VLOOKUP(10*tblRiskRegister32[[#This Row],[Safeguard Maturity Score]]+tblRiskRegister32[[#This Row],[VCDB Index]],tblHITIndexWeightTable[],4,FALSE),"") | K32: =VLOOKUP(tblRiskRegister32[[#This Row],[Asset Class]],tblInherentImpacts30[],2,FALSE) -> 4 | L32: =VLOOKUP(tblRiskRegister32[[#This Row],[Asset Class]],tblInherentImpacts30[],3,FALSE) -> 4 | M32: =VLOOKUP(tblRiskRegister32[[#This Row],[Asset Class]],tblInherentImpacts30[],4,FALSE) -> 1 | N32: =VLOOKUP(tblRiskRegister32[[#This Row],[Asset Class]],tblInherentImpacts30[],5,FALSE) -> 4 | O32: =IFERROR(MAX(tblRiskRegister32[[#This Row],[Impact to Mission]:[Impact to Obligations]])*tblRiskRegister32[[#This Row],[Expectancy Score]],"") | P32: =tblRiskRegister32[[#This Row],[Risk Score]] | R32: 3.9 | S32: Encrypt Data on Removable Media | T32: Encrypt data on removable media. | W32: =IFERROR(VLOOKUP(10*tblRiskRegister32[[#This Row],[Risk Treatment Safeguard Maturity Score]]+tblRiskRegister32[[#This Row],[VCDB Index]],tblHITIndexWeightTable[],4,FALSE),"") | X32: =VLOOKUP(tblRiskRegister32[[#This Row],[Asset Class]],tblInherentImpacts30[],2,FALSE) -> 4 | Y32: =VLOOKUP(tblRiskRegister32[[#This Row],[Asset Class]],tblInherentImpacts30[],3,FALSE) -> 4 | Z32: =VLOOKUP(tblRiskRegister32[[#This Row],[Asset Class]],tblInherentImpacts30[],3,FALSE) -> 4 | AA32: =VLOOKUP(tblRiskRegister32[[#This Row],[Asset Class]],tblInherentImpacts30[],4,FALSE) -> 1 | AB32: =IFERROR(MAX(tblRiskRegister32[[#This Row],[Risk Treatment Safeguard Impact to Mission]:[Risk Treatment Safeguard Impact to Obligations]])*tblRiskRegister32[[#This Row],[Risk Treatment Safeguard Expectancy Score]],"") | AC32: =IF(tblRiskRegister32[[#This Row],[Risk Score]]>AcceptableRisk,IF(tblRiskRegister32[[#This Row],[Risk Treatment Safeguard Risk Score]]<AcceptableRisk, IF(tblRiskRegister32[[#This Row],[Risk Treatment Safeguard Risk Score]]<=tblRiskRegister32[[#This Row],[Risk Score]],"Yes","No"),"No"),"Yes") -> No
B33: Applications | D33: 4.1 | E33: Establish and Maintain a Secure Configuration Process | I33: =IFERROR(VLOOKUP(tblRiskRegister32[[#This Row],[Asset Class]],tblVCDBIndex[],4,FALSE),"") -> 2 | J33: =IFERROR(VLOOKUP(10*tblRiskRegister32[[#This Row],[Safeguard Maturity Score]]+tblRiskRegister32[[#This Row],[VCDB Index]],tblHITIndexWeightTable[],4,FALSE),"") | K33: =VLOOKUP(tblRiskRegister32[[#This Row],[Asset Class]],tblInherentImpacts30[],2,FALSE) -> 3 | L33: =VLOOKUP(tblRiskRegister32[[#This Row],[Asset Class]],tblInherentImpacts30[],3,FALSE) -> 4 | M33: =VLOOKUP(tblRiskRegister32[[#This Row],[Asset Class]],tblInherentImpacts30[],4,FALSE) -> 1 | N33: =VLOOKUP(tblRiskRegister32[[#This Row],[Asset Class]],tblInherentImpacts30[],5,FALSE) -> 4 | O33: =IFERROR(MAX(tblRiskRegister32[[#This Row],[Impact to Mission]:[Impact to Obligations]])*tblRiskRegister32[[#This Row],[Expectancy Score]],"") | P33: =tblRiskRegister32[[#This Row],[Risk Score]] | R33: 4.1 | S33: Establish and Maintain a Secure Configuration Process | T33: Establish and maintain a secure configuration process for enterprise assets (end-user devices, including portable and mobile, non-computing/IoT devices, and servers) and software (operating systems and applications). Review and update documentation annually, or when significant enterprise changes occur that could impact this Safeguard. | W33: =IFERROR(VLOOKUP(10*tblRiskRegister32[[#This Row],[Risk Treatment Safeguard Maturity Score]]+tblRiskRegister32[[#This Row],[VCDB Index]],tblHITIndexWeightTable[],4,FALSE),"") | X33: =VLOOKUP(tblRiskRegister32[[#This Row],[Asset Class]],tblInherentImpacts30[],2,FALSE) -> 3 | Y33: =VLOOKUP(tblRiskRegister32[[#This Row],[Asset Class]],tblInherentImpacts30[],3,FALSE) -> 4 | Z33: =VLOOKUP(tblRiskRegister32[[#This Row],[Asset Class]],tblInherentImpacts30[],3,FALSE) -> 4 | AA33: =VLOOKUP(tblRiskRegister32[[#This Row],[Asset Class]],tblInherentImpacts30[],4,FALSE) -> 1 | AB33: =IFERROR(MAX(tblRiskRegister32[[#This Row],[Risk Treatment Safeguard Impact to Mission]:[Risk Treatment Safeguard Impact to Obligations]])*tblRiskRegister32[[#This Row],[Risk Treatment Safeguard Expectancy Score]],"") | AC33: =IF(tblRiskRegister32[[#This Row],[Risk Score]]>AcceptableRisk,IF(tblRiskRegister32[[#This Row],[Risk Treatment Safeguard Risk Score]]<AcceptableRisk, IF(tblRiskRegister32[[#This Row],[Risk Treatment Safeguard Risk Score]]<=tblRiskRegister32[[#This Row],[Risk Score]],"Yes","No"),"No"),"Yes") -> No
B34: Devices | C34: MIS 595 Focus | D34: 4.1 | E34: Enforce Automatic Device Lockout on Portable End-User Devices | F34: No control in place | G34: No automated screen-lock settings exist on portable devices, leaving endpoints exposed when unattended. | H34: 1 | I34: =IFERROR(VLOOKUP(tblRiskRegister32[[#This Row],[Asset Class]],tblVCDBIndex[],4,FALSE),"") -> 1 | J34: =IFERROR(VLOOKUP(10*tblRiskRegister32[[#This Row],[Safeguard Maturity Score]]+tblRiskRegister32[[#This Row],[VCDB Index]],tblHITIndexWeightTable[],4,FALSE),"") -> 4 | K34: =VLOOKUP(tblRiskRegister32[[#This Row],[Asset Class]],tblInherentImpacts30[],2,FALSE) -> 3 | L34: =VLOOKUP(tblRiskRegister32[[#This Row],[Asset Class]],tblInherentImpacts30[],3,FALSE) -> 3 | M34: =VLOOKUP(tblRiskRegister32[[#This Row],[Asset Class]],tblInherentImpacts30[],4,FALSE) -> 1 | N34: =VLOOKUP(tblRiskRegister32[[#This Row],[Asset Class]],tblInherentImpacts30[],5,FALSE) -> 3 | O34: =IFERROR(MAX(tblRiskRegister32[[#This Row],[Impact to Mission]:[Impact to Obligations]])*tblRiskRegister32[[#This Row],[Expectancy Score]],"") -> 12 | P34: =tblRiskRegister32[[#This Row],[Risk Score]] -> 12 | Q34: Reduce | R34: 4.1 | S34: Enforce Automatic Device Lockout on Portable End-User Devices | T34: Enforce automatic device lockout following a predetermined threshold of local failed authentication attempts on portable end-user devices, where supported. For laptops, do not allow more than 20 failed authentication attempts; for tablets and smartphones, no more than 10 failed authentication attempts. Example implementations include Microsoft® InTune Device Lock and Apple® Configuration Profile maxFailedAttempts. | W34: =IFERROR(VLOOKUP(10*tblRiskRegister32[[#This Row],[Risk Treatment Safeguard Maturity Score]]+tblRiskRegister32[[#This Row],[VCDB Index]],tblHITIndexWeightTable[],4,FALSE),"") | X34: =VLOOKUP(tblRiskRegister32[[#This Row],[Asset Class]],tblInherentImpacts30[],2,FALSE) -> 3 | Y34: =VLOOKUP(tblRiskRegister32[[#This Row],[Asset Class]],tblInherentImpacts30[],3,FALSE) -> 3 | Z34: =VLOOKUP(tblRiskRegister32[[#This Row],[Asset Class]],tblInherentImpacts30[],3,FALSE) -> 3 | AA34: =VLOOKUP(tblRiskRegister32[[#This Row],[Asset Class]],tblInherentImpacts30[],4,FALSE) -> 1 | AB34: =IFERROR(MAX(tblRiskRegister32[[#This Row],[Risk Treatment Safeguard Impact to Mission]:[Risk Treatment Safeguard Impact to Obligations]])*tblRiskRegister32[[#This Row],[Risk Treatment Safeguard Expectancy Score]],"") | AC34: =IF(tblRiskRegister32[[#This Row],[Risk Score]]>AcceptableRisk,IF(tblRiskRegister32[[#This Row],[Risk Treatment Safeguard Risk Score]]<AcceptableRisk, IF(tblRiskRegister32[[#This Row],[Risk Treatment Safeguard Risk Score]]<=tblRiskRegister32[[#This Row],[Risk Score]],"Yes","No"),"No"),"Yes") -> No
B35: Devices | C35: MIS 595 Focus | D35: 4.11 | E35: Enforce Remote Wipe Capability on Portable End-User Devices | F35: No control in place | G35: Devices cannot be remotely wiped if lost or stolen because no mobile device management (MDM) solution is deployed. | H35: 1 | I35: =IFERROR(VLOOKUP(tblRiskRegister32[[#This Row],[Asset Class]],tblVCDBIndex[],4,FALSE),"") -> 1 | J35: =IFERROR(VLOOKUP(10*tblRiskRegister32[[#This Row],[Safeguard Maturity Score]]+tblRiskRegister32[[#This Row],[VCDB Index]],tblHITIndexWeightTable[],4,FALSE),"") -> 4 | K35: =VLOOKUP(tblRiskRegister32[[#This Row],[Asset Class]],tblInherentImpacts30[],2,FALSE) -> 3 | L35: =VLOOKUP(tblRiskRegister32[[#This Row],[Asset Class]],tblInherentImpacts30[],3,FALSE) -> 3 | M35: =VLOOKUP(tblRiskRegister32[[#This Row],[Asset Class]],tblInherentImpacts30[],4,FALSE) -> 1 | N35: =VLOOKUP(tblRiskRegister32[[#This Row],[Asset Class]],tblInherentImpacts30[],5,FALSE) -> 3 | O35: =IFERROR(MAX(tblRiskRegister32[[#This Row],[Impact to Mission]:[Impact to Obligations]])*tblRiskRegister32[[#This Row],[Expectancy Score]],"") -> 12 | P35: =tblRiskRegister32[[#This Row],[Risk Score]] -> 12 | Q35: Reduce | R35: 4.11 | S35: Enforce Remote Wipe Capability on Portable End-User Devices | T35: Remotely wipe enterprise data from enterprise-owned portable end-user devices when deemed appropriate such as lost or stolen devices, or when an individual no longer supports the enterprise. | W35: =IFERROR(VLOOKUP(10*tblRiskRegister32[[#This Row],[Risk Treatment Safeguard Maturity Score]]+tblRiskRegister32[[#This Row],[VCDB Index]],tblHITIndexWeightTable[],4,FALSE),"") | X35: =VLOOKUP(tblRiskRegister32[[#This Row],[Asset Class]],tblInherentImpacts30[],2,FALSE) -> 3 | Y35: =VLOOKUP(tblRiskRegister32[[#This Row],[Asset Class]],tblInherentImpacts30[],3,FALSE) -> 3 | Z35: =VLOOKUP(tblRiskRegister32[[#This Row],[Asset Class]],tblInherentImpacts30[],3,FALSE) -> 3 | AA35: =VLOOKUP(tblRiskRegister32[[#This Row],[Asset Class]],tblInherentImpacts30[],4,FALSE) -> 1 | AB35: =IFERROR(MAX(tblRiskRegister32[[#This Row],[Risk Treatment Safeguard Impact to Mission]:[Risk Treatment Safeguard Impact to Obligations]])*tblRiskRegister32[[#This Row],[Risk Treatment Safeguard Expectancy Score]],"") | AC35: =IF(tblRiskRegister32[[#This Row],[Risk Score]]>AcceptableRisk,IF(tblRiskRegister32[[#This Row],[Risk Treatment Safeguard Risk Score]]<AcceptableRisk, IF(tblRiskRegister32[[#This Row],[Risk Treatment Safeguard Risk Score]]<=tblRiskRegister32[[#This Row],[Risk Score]],"Yes","No"),"No"),"Yes") -> No
B36: Network | D36: 4.2 | E36: Establish and Maintain a Secure Configuration Process for Network Infrastructure | I36: =IFERROR(VLOOKUP(tblRiskRegister32[[#This Row],[Asset Class]],tblVCDBIndex[],4,FALSE),"") -> 1 | J36: =IFERROR(VLOOKUP(10*tblRiskRegister32[[#This Row],[Safeguard Maturity Score]]+tblRiskRegister32[[#This Row],[VCDB Index]],tblHITIndexWeightTable[],4,FALSE),"") | K36: =VLOOKUP(tblRiskRegister32[[#This Row],[Asset Class]],tblInherentImpacts30[],2,FALSE) -> 4 | L36: =VLOOKUP(tblRiskRegister32[[#This Row],[Asset Class]],tblInherentImpacts30[],3,FALSE) -> 5 | M36: =VLOOKUP(tblRiskRegister32[[#This Row],[Asset Class]],tblInherentImpacts30[],4,FALSE) -> 1 | N36: =VLOOKUP(tblRiskRegister32[[#This Row],[Asset Class]],tblInherentImpacts30[],5,FALSE) -> 5 | O36: =IFERROR(MAX(tblRiskRegister32[[#This Row],[Impact to Mission]:[Impact to Obligations]])*tblRiskRegister32[[#This Row],[Expectancy Score]],"") | P36: =tblRiskRegister32[[#This Row],[Risk Score]] | R36: 4.2 | S36: Establish and Maintain a Secure Configuration Process for Network Infrastructure | T36: Establish and maintain a secure configuration process for network devices. Review and update documentation annually, or when significant enterprise changes occur that could impact this Safeguard. | W36: =IFERROR(VLOOKUP(10*tblRiskRegister32[[#This Row],[Risk Treatment Safeguard Maturity Score]]+tblRiskRegister32[[#This Row],[VCDB Index]],tblHITIndexWeightTable[],4,FALSE),"") | X36: =VLOOKUP(tblRiskRegister32[[#This Row],[Asset Class]],tblInherentImpacts30[],2,FALSE) -> 4 | Y36: =VLOOKUP(tblRiskRegister32[[#This Row],[Asset Class]],tblInherentImpacts30[],3,FALSE) -> 5 | Z36: =VLOOKUP(tblRiskRegister32[[#This Row],[Asset Class]],tblInherentImpacts30[],3,FALSE) -> 5 | AA36: =VLOOKUP(tblRiskRegister32[[#This Row],[Asset Class]],tblInherentImpacts30[],4,FALSE) -> 1 | AB36: =IFERROR(MAX(tblRiskRegister32[[#This Row],[Risk Treatment Safeguard Impact to Mission]:[Risk Treatment Safeguard Impact to Obligations]])*tblRiskRegister32[[#This Row],[Risk Treatment Safeguard Expectancy Score]],"") | AC36: =IF(tblRiskRegister32[[#This Row],[Risk Score]]>AcceptableRisk,IF(tblRiskRegister32[[#This Row],[Risk Treatment Safeguard Risk Score]]<AcceptableRisk, IF(tblRiskRegister32[[#This Row],[Risk Treatment Safeguard Risk Score]]<=tblRiskRegister32[[#This Row],[Risk Score]],"Yes","No"),"No"),"Yes") -> No
B37: Users | C37: MIS 595 Focus | D37: 4.3 | E37: Configure Automatic Session Locking on Enterprise Assets | F37: Session timeout and automatic lock policies are implemented for all enterprise devices based on our Access Control Policy. | G37: No Vulnerability | H37: 5 | I37: =IFERROR(VLOOKUP(tblRiskRegister32[[#This Row],[Asset Class]],tblVCDBIndex[],4,FALSE),"") -> 3 | J37: =IFERROR(VLOOKUP(10*tblRiskRegister32[[#This Row],[Safeguard Maturity Score]]+tblRiskRegister32[[#This Row],[VCDB Index]],tblHITIndexWeightTable[],4,FALSE),"") -> 1 | K37: =VLOOKUP(tblRiskRegister32[[#This Row],[Asset Class]],tblInherentImpacts30[],2,FALSE) -> 5 | L37: =VLOOKUP(tblRiskRegister32[[#This Row],[Asset Class]],tblInherentImpacts30[],3,FALSE) -> 5 | M37: =VLOOKUP(tblRiskRegister32[[#This Row],[Asset Class]],tblInherentImpacts30[],4,FALSE) -> 1 | N37: =VLOOKUP(tblRiskRegister32[[#This Row],[Asset Class]],tblInherentImpacts30[],5,FALSE) -> 5 | O37: =IFERROR(MAX(tblRiskRegister32[[#This Row],[Impact to Mission]:[Impact to Obligations]])*tblRiskRegister32[[#This Row],[Expectancy Score]],"") -> 5 | P37: =tblRiskRegister32[[#This Row],[Risk Score]] -> 5 | Q37: Accept | R37: 4.3 | S37: Configure Automatic Session Locking on Enterprise Assets | T37: Configure automatic session locking on enterprise assets after a defined period of inactivity. For general purpose operating systems, the period must not exceed 15 minutes. For mobile end-user devices, the period must not exceed 2 minutes. | W37: =IFERROR(VLOOKUP(10*tblRiskRegister32[[#This Row],[Risk Treatment Safeguard Maturity Score]]+tblRiskRegister32[[#This Row],[VCDB Index]],tblHITIndexWeightTable[],4,FALSE),"") | X37: =VLOOKUP(tblRiskRegister32[[#This Row],[Asset Class]],tblInherentImpacts30[],2,FALSE) -> 5 | Y37: =VLOOKUP(tblRiskRegister32[[#This Row],[Asset Class]],tblInherentImpacts30[],3,FALSE) -> 5 | Z37: =VLOOKUP(tblRiskRegister32[[#This Row],[Asset Class]],tblInherentImpacts30[],3,FALSE) -> 5 | AA37: =VLOOKUP(tblRiskRegister32[[#This Row],[Asset Class]],tblInherentImpacts30[],4,FALSE) -> 1 | AB37: =IFERROR(MAX(tblRiskRegister32[[#This Row],[Risk Treatment Safeguard Impact to Mission]:[Risk Treatment Safeguard Impact to Obligations]])*tblRiskRegister32[[#This Row],[Risk Treatment Safeguard Expectancy Score]],"") | AC37: =IF(tblRiskRegister32[[#This Row],[Risk Score]]>AcceptableRisk,IF(tblRiskRegister32[[#This Row],[Risk Treatment Safeguard Risk Score]]<AcceptableRisk, IF(tblRiskRegister32[[#This Row],[Risk Treatment Safeguard Risk Score]]<=tblRiskRegister32[[#This Row],[Risk Score]],"Yes","No"),"No"),"Yes") -> Yes
B38: Devices | D38: 4.4 | E38: Implement and Manage a Firewall on Servers | I38: =IFERROR(VLOOKUP(tblRiskRegister32[[#This Row],[Asset Class]],tblVCDBIndex[],4,FALSE),"") -> 1 | J38: =IFERROR(VLOOKUP(10*tblRiskRegister32[[#This Row],[Safeguard Maturity Score]]+tblRiskRegister32[[#This Row],[VCDB Index]],tblHITIndexWeightTable[],4,FALSE),"") | K38: =VLOOKUP(tblRiskRegister32[[#This Row],[Asset Class]],tblInherentImpacts30[],2,FALSE) -> 3 | L38: =VLOOKUP(tblRiskRegister32[[#This Row],[Asset Class]],tblInherentImpacts30[],3,FALSE) -> 3 | M38: =VLOOKUP(tblRiskRegister32[[#This Row],[Asset Class]],tblInherentImpacts30[],4,FALSE) -> 1 | N38: =VLOOKUP(tblRiskRegister32[[#This Row],[Asset Class]],tblInherentImpacts30[],5,FALSE) -> 3 | O38: =IFERROR(MAX(tblRiskRegister32[[#This Row],[Impact to Mission]:[Impact to Obligations]])*tblRiskRegister32[[#This Row],[Expectancy Score]],"") | P38: =tblRiskRegister32[[#This Row],[Risk Score]] | R38: 4.4 | S38: Implement and Manage a Firewall on Servers | T38: Implement and manage a firewall on servers, where supported. Example implementations include a virtual firewall, operating system firewall, or a third-party firewall agent. | W38: =IFERROR(VLOOKUP(10*tblRiskRegister32[[#This Row],[Risk Treatment Safeguard Maturity Score]]+tblRiskRegister32[[#This Row],[VCDB Index]],tblHITIndexWeightTable[],4,FALSE),"") | X38: =VLOOKUP(tblRiskRegister32[[#This Row],[Asset Class]],tblInherentImpacts30[],2,FALSE) -> 3 | Y38: =VLOOKUP(tblRiskRegister32[[#This Row],[Asset Class]],tblInherentImpacts30[],3,FALSE) -> 3 | Z38: =VLOOKUP(tblRiskRegister32[[#This Row],[Asset Class]],tblInherentImpacts30[],3,FALSE) -> 3 | AA38: =VLOOKUP(tblRiskRegister32[[#This Row],[Asset Class]],tblInherentImpacts30[],4,FALSE) -> 1 | AB38: =IFERROR(MAX(tblRiskRegister32[[#This Row],[Risk Treatment Safeguard Impact to Mission]:[Risk Treatment Safeguard Impact to Obligations]])*tblRiskRegister32[[#This Row],[Risk Treatment Safeguard Expectancy Score]],"") | AC38: =IF(tblRiskRegister32[[#This Row],[Risk Score]]>AcceptableRisk,IF(tblRiskRegister32[[#This Row],[Risk Treatment Safeguard Risk Score]]<AcceptableRisk, IF(tblRiskRegister32[[#This Row],[Risk Treatment Safeguard Risk Score]]<=tblRiskRegister32[[#This Row],[Risk Score]],"Yes","No"),"No"),"Yes") -> No
B39: Devices | C39: MIS 595 Focus | D39: 4.5 | E39: Implement and Manage a Firewall on End-User Devices | F39: Endpoint firewalls are deployed and managed using centralized security software to restrict unauthorized traffic. | G39: No Vulnerability | H39: 5 | I39: =IFERROR(VLOOKUP(tblRiskRegister32[[#This Row],[Asset Class]],tblVCDBIndex[],4,FALSE),"") -> 1 | J39: =IFERROR(VLOOKUP(10*tblRiskRegister32[[#This Row],[Safeguard Maturity Score]]+tblRiskRegister32[[#This Row],[VCDB Index]],tblHITIndexWeightTable[],4,FALSE),"") -> 1 | K39: =VLOOKUP(tblRiskRegister32[[#This Row],[Asset Class]],tblInherentImpacts30[],2,FALSE) -> 3 | L39: =VLOOKUP(tblRiskRegister32[[#This Row],[Asset Class]],tblInherentImpacts30[],3,FALSE) -> 3 | M39: =VLOOKUP(tblRiskRegister32[[#This Row],[Asset Class]],tblInherentImpacts30[],4,FALSE) -> 1 | N39: =VLOOKUP(tblRiskRegister32[[#This Row],[Asset Class]],tblInherentImpacts30[],5,FALSE) -> 3 | O39: =IFERROR(MAX(tblRiskRegister32[[#This Row],[Impact to Mission]:[Impact to Obligations]])*tblRiskRegister32[[#This Row],[Expectancy Score]],"") -> 3 | P39: =tblRiskRegister32[[#This Row],[Risk Score]] -> 3 | Q39: Accept | R39: 4.5 | S39: Implement and Manage a Firewall on End-User Devices | T39: Implement and manage a host-based firewall or port-filtering tool on end-user devices, with a default-deny rule that drops all traffic except those services and ports that are explicitly allowed. | W39: =IFERROR(VLOOKUP(10*tblRiskRegister32[[#This Row],[Risk Treatment Safeguard Maturity Score]]+tblRiskRegister32[[#This Row],[VCDB Index]],tblHITIndexWeightTable[],4,FALSE),"") | X39: =VLOOKUP(tblRiskRegister32[[#This Row],[Asset Class]],tblInherentImpacts30[],2,FALSE) -> 3 | Y39: =VLOOKUP(tblRiskRegister32[[#This Row],[Asset Class]],tblInherentImpacts30[],3,FALSE) -> 3 | Z39: =VLOOKUP(tblRiskRegister32[[#This Row],[Asset Class]],tblInherentImpacts30[],3,FALSE) -> 3 | AA39: =VLOOKUP(tblRiskRegister32[[#This Row],[Asset Class]],tblInherentImpacts30[],4,FALSE) -> 1 | AB39: =IFERROR(MAX(tblRiskRegister32[[#This Row],[Risk Treatment Safeguard Impact to Mission]:[Risk Treatment Safeguard Impact to Obligations]])*tblRiskRegister32[[#This Row],[Risk Treatment Safeguard Expectancy Score]],"") | AC39: =IF(tblRiskRegister32[[#This Row],[Risk Score]]>AcceptableRisk,IF(tblRiskRegister32[[#This Row],[Risk Treatment Safeguard Risk Score]]<AcceptableRisk, IF(tblRiskRegister32[[#This Row],[Risk Treatment Safeguard Risk Score]]<=tblRiskRegister32[[#This Row],[Risk Score]],"Yes","No"),"No"),"Yes") -> Yes
B40: Network | C40: MIS 595 Focus | D40: 4.6 | E40: Securely Manage Enterprise Assets and Software | F40: All enterprise devices and applications are configured to follow hardening standards defined in Fabella’s Secure Configuration Policy. | G40: No Vulnerability | H40: 3 | I40: =IFERROR(VLOOKUP(tblRiskRegister32[[#This Row],[Asset Class]],tblVCDBIndex[],4,FALSE),"") -> 1 | J40: =IFERROR(VLOOKUP(10*tblRiskRegister32[[#This Row],[Safeguard Maturity Score]]+tblRiskRegister32[[#This Row],[VCDB Index]],tblHITIndexWeightTable[],4,FALSE),"") -> 1 | K40: =VLOOKUP(tblRiskRegister32[[#This Row],[Asset Class]],tblInherentImpacts30[],2,FALSE) -> 4 | L40: =VLOOKUP(tblRiskRegister32[[#This Row],[Asset Class]],tblInherentImpacts30[],3,FALSE) -> 5 | M40: =VLOOKUP(tblRiskRegister32[[#This Row],[Asset Class]],tblInherentImpacts30[],4,FALSE) -> 1 | N40: =VLOOKUP(tblRiskRegister32[[#This Row],[Asset Class]],tblInherentImpacts30[],5,FALSE) -> 5 | O40: =IFERROR(MAX(tblRiskRegister32[[#This Row],[Impact to Mission]:[Impact to Obligations]])*tblRiskRegister32[[#This Row],[Expectancy Score]],"") -> 5 | P40: =tblRiskRegister32[[#This Row],[Risk Score]] -> 5 | Q40: Accept | R40: 4.6 | S40: Securely Manage Enterprise Assets and Software | T40: Securely manage enterprise assets and software. Example implementations include managing configuration through version-controlled-infrastructure-as-code and accessing administrative interfaces over secure network protocols, such as Secure Shell (SSH) and Hypertext Transfer Protocol Secure (HTTPS). Do not use insecure management protocols, such as Telnet (Teletype Network) and HTTP, unless operationally essential. | W40: =IFERROR(VLOOKUP(10*tblRiskRegister32[[#This Row],[Risk Treatment Safeguard Maturity Score]]+tblRiskRegister32[[#This Row],[VCDB Index]],tblHITIndexWeightTable[],4,FALSE),"") | X40: =VLOOKUP(tblRiskRegister32[[#This Row],[Asset Class]],tblInherentImpacts30[],2,FALSE) -> 4 | Y40: =VLOOKUP(tblRiskRegister32[[#This Row],[Asset Class]],tblInherentImpacts30[],3,FALSE) -> 5 | Z40: =VLOOKUP(tblRiskRegister32[[#This Row],[Asset Class]],tblInherentImpacts30[],3,FALSE) -> 5 | AA40: =VLOOKUP(tblRiskRegister32[[#This Row],[Asset Class]],tblInherentImpacts30[],4,FALSE) -> 1 | AB40: =IFERROR(MAX(tblRiskRegister32[[#This Row],[Risk Treatment Safeguard Impact to Mission]:[Risk Treatment Safeguard Impact to Obligations]])*tblRiskRegister32[[#This Row],[Risk Treatment Safeguard Expectancy Score]],"") | AC40: =IF(tblRiskRegister32[[#This Row],[Risk Score]]>AcceptableRisk,IF(tblRiskRegister32[[#This Row],[Risk Treatment Safeguard Risk Score]]<AcceptableRisk, IF(tblRiskRegister32[[#This Row],[Risk Treatment Safeguard Risk Score]]<=tblRiskRegister32[[#This Row],[Risk Score]],"Yes","No"),"No"),"Yes") -> Yes
B41: Users | C41: MIS 595 Focus | D41: 4.7 | E41: Manage Default Accounts on Enterprise Assets and Software | F41: Default accounts are disabled or secured during device provisioning processes. | G41: No Vulnerability | H41: 5 | I41: =IFERROR(VLOOKUP(tblRiskRegister32[[#This Row],[Asset Class]],tblVCDBIndex[],4,FALSE),"") -> 3 | J41: =IFERROR(VLOOKUP(10*tblRiskRegister32[[#This Row],[Safeguard Maturity Score]]+tblRiskRegister32[[#This Row],[VCDB Index]],tblHITIndexWeightTable[],4,FALSE),"") -> 1 | K41: =VLOOKUP(tblRiskRegister32[[#This Row],[Asset Class]],tblInherentImpacts30[],2,FALSE) -> 5 | L41: =VLOOKUP(tblRiskRegister32[[#This Row],[Asset Class]],tblInherentImpacts30[],3,FALSE) -> 5 | M41: =VLOOKUP(tblRiskRegister32[[#This Row],[Asset Class]],tblInherentImpacts30[],4,FALSE) -> 1 | N41: =VLOOKUP(tblRiskRegister32[[#This Row],[Asset Class]],tblInherentImpacts30[],5,FALSE) -> 5 | O41: =IFERROR(MAX(tblRiskRegister32[[#This Row],[Impact to Mission]:[Impact to Obligations]])*tblRiskRegister32[[#This Row],[Expectancy Score]],"") -> 5 | P41: =tblRiskRegister32[[#This Row],[Risk Score]] -> 5 | Q41: Accept | R41: 4.7 | S41: Manage Default Accounts on Enterprise Assets and Software | T41: Manage default accounts on enterprise assets and software, such as root, administrator, and other pre-configured vendor accounts. Example implementations can include: disabling default accounts or making them unusable. | W41: =IFERROR(VLOOKUP(10*tblRiskRegister32[[#This Row],[Risk Treatment Safeguard Maturity Score]]+tblRiskRegister32[[#This Row],[VCDB Index]],tblHITIndexWeightTable[],4,FALSE),"") | X41: =VLOOKUP(tblRiskRegister32[[#This Row],[Asset Class]],tblInherentImpacts30[],2,FALSE) -> 5 | Y41: =VLOOKUP(tblRiskRegister32[[#This Row],[Asset Class]],tblInherentImpacts30[],3,FALSE) -> 5 | Z41: =VLOOKUP(tblRiskRegister32[[#This Row],[Asset Class]],tblInherentImpacts30[],3,FALSE) -> 5 | AA41: =VLOOKUP(tblRiskRegister32[[#This Row],[Asset Class]],tblInherentImpacts30[],4,FALSE) -> 1 | AB41: =IFERROR(MAX(tblRiskRegister32[[#This Row],[Risk Treatment Safeguard Impact to Mission]:[Risk Treatment Safeguard Impact to Obligations]])*tblRiskRegister32[[#This Row],[Risk Treatment Safeguard Expectancy Score]],"") | AC41: =IF(tblRiskRegister32[[#This Row],[Risk Score]]>AcceptableRisk,IF(tblRiskRegister32[[#This Row],[Risk Treatment Safeguard Risk Score]]<AcceptableRisk, IF(tblRiskRegister32[[#This Row],[Risk Treatment Safeguard Risk Score]]<=tblRiskRegister32[[#This Row],[Risk Score]],"Yes","No"),"No"),"Yes") -> Yes
B42: Devices | C42: MIS 595 Focus | D42: 4.8 | E42: Uninstall or Disable Unnecessary Services on Enterprise Assets and Software | F42: Systems are routinely reviewed to remove unused services and applications to reduce attack surface. | G42: No Vulnerability | H42: 3 | I42: =IFERROR(VLOOKUP(tblRiskRegister32[[#This Row],[Asset Class]],tblVCDBIndex[],4,FALSE),"") -> 1 | J42: =IFERROR(VLOOKUP(10*tblRiskRegister32[[#This Row],[Safeguard Maturity Score]]+tblRiskRegister32[[#This Row],[VCDB Index]],tblHITIndexWeightTable[],4,FALSE),"") -> 1 | K42: =VLOOKUP(tblRiskRegister32[[#This Row],[Asset Class]],tblInherentImpacts30[],2,FALSE) -> 3 | L42: =VLOOKUP(tblRiskRegister32[[#This Row],[Asset Class]],tblInherentImpacts30[],3,FALSE) -> 3 | M42: =VLOOKUP(tblRiskRegister32[[#This Row],[Asset Class]],tblInherentImpacts30[],4,FALSE) -> 1 | N42: =VLOOKUP(tblRiskRegister32[[#This Row],[Asset Class]],tblInherentImpacts30[],5,FALSE) -> 3 | O42: =IFERROR(MAX(tblRiskRegister32[[#This Row],[Impact to Mission]:[Impact to Obligations]])*tblRiskRegister32[[#This Row],[Expectancy Score]],"") -> 3 | P42: =tblRiskRegister32[[#This Row],[Risk Score]] -> 3 | Q42: Accept | R42: 4.8 | S42: Uninstall or Disable Unnecessary Services on Enterprise Assets and Software | T42: Uninstall or disable unnecessary services on enterprise assets and software, such as an unused file sharing service, web application module, or service function. | W42: =IFERROR(VLOOKUP(10*tblRiskRegister32[[#This Row],[Risk Treatment Safeguard Maturity Score]]+tblRiskRegister32[[#This Row],[VCDB Index]],tblHITIndexWeightTable[],4,FALSE),"") | X42: =VLOOKUP(tblRiskRegister32[[#This Row],[Asset Class]],tblInherentImpacts30[],2,FALSE) -> 3 | Y42: =VLOOKUP(tblRiskRegister32[[#This Row],[Asset Class]],tblInherentImpacts30[],3,FALSE) -> 3 | Z42: =VLOOKUP(tblRiskRegister32[[#This Row],[Asset Class]],tblInherentImpacts30[],3,FALSE) -> 3 | AA42: =VLOOKUP(tblRiskRegister32[[#This Row],[Asset Class]],tblInherentImpacts30[],4,FALSE) -> 1 | AB42: =IFERROR(MAX(tblRiskRegister32[[#This Row],[Risk Treatment Safeguard Impact to Mission]:[Risk Treatment Safeguard Impact to Obligations]])*tblRiskRegister32[[#This Row],[Risk Treatment Safeguard Expectancy Score]],"") | AC42: =IF(tblRiskRegister32[[#This Row],[Risk Score]]>AcceptableRisk,IF(tblRiskRegister32[[#This Row],[Risk Treatment Safeguard Risk Score]]<AcceptableRisk, IF(tblRiskRegister32[[#This Row],[Risk Treatment Safeguard Risk Score]]<=tblRiskRegister32[[#This Row],[Risk Score]],"Yes","No"),"No"),"Yes") -> Yes
B43: Devices | D43: 4.9 | E43: Configure Trusted DNS Servers on Enterprise Assets | I43: =IFERROR(VLOOKUP(tblRiskRegister32[[#This Row],[Asset Class]],tblVCDBIndex[],4,FALSE),"") -> 1 | J43: =IFERROR(VLOOKUP(10*tblRiskRegister32[[#This Row],[Safeguard Maturity Score]]+tblRiskRegister32[[#This Row],[VCDB Index]],tblHITIndexWeightTable[],4,FALSE),"") | K43: =VLOOKUP(tblRiskRegister32[[#This Row],[Asset Class]],tblInherentImpacts30[],2,FALSE) -> 3 | L43: =VLOOKUP(tblRiskRegister32[[#This Row],[Asset Class]],tblInherentImpacts30[],3,FALSE) -> 3 | M43: =VLOOKUP(tblRiskRegister32[[#This Row],[Asset Class]],tblInherentImpacts30[],4,FALSE) -> 1 | N43: =VLOOKUP(tblRiskRegister32[[#This Row],[Asset Class]],tblInherentImpacts30[],5,FALSE) -> 3 | O43: =IFERROR(MAX(tblRiskRegister32[[#This Row],[Impact to Mission]:[Impact to Obligations]])*tblRiskRegister32[[#This Row],[Expectancy Score]],"") | P43: =tblRiskRegister32[[#This Row],[Risk Score]] | R43: 4.9 | S43: Configure Trusted DNS Servers on Enterprise Assets | T43: Configure trusted DNS servers on enterprise assets. Example implementations include: configuring assets to use enterprise-controlled DNS servers and/or reputable externally accessible DNS servers. | W43: =IFERROR(VLOOKUP(10*tblRiskRegister32[[#This Row],[Risk Treatment Safeguard Maturity Score]]+tblRiskRegister32[[#This Row],[VCDB Index]],tblHITIndexWeightTable[],4,FALSE),"") | X43: =VLOOKUP(tblRiskRegister32[[#This Row],[Asset Class]],tblInherentImpacts30[],2,FALSE) -> 3 | Y43: =VLOOKUP(tblRiskRegister32[[#This Row],[Asset Class]],tblInherentImpacts30[],3,FALSE) -> 3 | Z43: =VLOOKUP(tblRiskRegister32[[#This Row],[Asset Class]],tblInherentImpacts30[],3,FALSE) -> 3 | AA43: =VLOOKUP(tblRiskRegister32[[#This Row],[Asset Class]],tblInherentImpacts30[],4,FALSE) -> 1 | AB43: =IFERROR(MAX(tblRiskRegister32[[#This Row],[Risk Treatment Safeguard Impact to Mission]:[Risk Treatment Safeguard Impact to Obligations]])*tblRiskRegister32[[#This Row],[Risk Treatment Safeguard Expectancy Score]],"") | AC43: =IF(tblRiskRegister32[[#This Row],[Risk Score]]>AcceptableRisk,IF(tblRiskRegister32[[#This Row],[Risk Treatment Safeguard Risk Score]]<AcceptableRisk, IF(tblRiskRegister32[[#This Row],[Risk Treatment Safeguard Risk Score]]<=tblRiskRegister32[[#This Row],[Risk Score]],"Yes","No"),"No"),"Yes") -> No
B44: Users | D44: 5.1 | E44: Establish and Maintain an Inventory of Accounts | I44: =IFERROR(VLOOKUP(tblRiskRegister32[[#This Row],[Asset Class]],tblVCDBIndex[],4,FALSE),"") -> 3 | J44: =IFERROR(VLOOKUP(10*tblRiskRegister32[[#This Row],[Safeguard Maturity Score]]+tblRiskRegister32[[#This Row],[VCDB Index]],tblHITIndexWeightTable[],4,FALSE),"") | K44: =VLOOKUP(tblRiskRegister32[[#This Row],[Asset Class]],tblInherentImpacts30[],2,FALSE) -> 5 | L44: =VLOOKUP(tblRiskRegister32[[#This Row],[Asset Class]],tblInherentImpacts30[],3,FALSE) -> 5 | M44: =VLOOKUP(tblRiskRegister32[[#This Row],[Asset Class]],tblInherentImpacts30[],4,FALSE) -> 1 | N44: =VLOOKUP(tblRiskRegister32[[#This Row],[Asset Class]],tblInherentImpacts30[],5,FALSE) -> 5 | O44: =IFERROR(MAX(tblRiskRegister32[[#This Row],[Impact to Mission]:[Impact to Obligations]])*tblRiskRegister32[[#This Row],[Expectancy Score]],"") | P44: =tblRiskRegister32[[#This Row],[Risk Score]] | R44: 5.1 | S44: Establish and Maintain an Inventory of Accounts | T44: Establish and maintain an inventory of all accounts managed in the enterprise. The inventory must include both user and administrator accounts. The inventory, at a minimum, should contain the person’s name, username, start/stop dates, and department. Validate that all active accounts are authorized, on a recurring schedule at a minimum quarterly, or more frequently. | W44: =IFERROR(VLOOKUP(10*tblRiskRegister32[[#This Row],[Risk Treatment Safeguard Maturity Score]]+tblRiskRegister32[[#This Row],[VCDB Index]],tblHITIndexWeightTable[],4,FALSE),"") | X44: =VLOOKUP(tblRiskRegister32[[#This Row],[Asset Class]],tblInherentImpacts30[],2,FALSE) -> 5 | Y44: =VLOOKUP(tblRiskRegister32[[#This Row],[Asset Class]],tblInherentImpacts30[],3,FALSE) -> 5 | Z44: =VLOOKUP(tblRiskRegister32[[#This Row],[Asset Class]],tblInherentImpacts30[],3,FALSE) -> 5 | AA44: =VLOOKUP(tblRiskRegister32[[#This Row],[Asset Class]],tblInherentImpacts30[],4,FALSE) -> 1 | AB44: =IFERROR(MAX(tblRiskRegister32[[#This Row],[Risk Treatment Safeguard Impact to Mission]:[Risk Treatment Safeguard Impact to Obligations]])*tblRiskRegister32[[#This Row],[Risk Treatment Safeguard Expectancy Score]],"") | AC44: =IF(tblRiskRegister32[[#This Row],[Risk Score]]>AcceptableRisk,IF(tblRiskRegister32[[#This Row],[Risk Treatment Safeguard Risk Score]]<AcceptableRisk, IF(tblRiskRegister32[[#This Row],[Risk Treatment Safeguard Risk Score]]<=tblRiskRegister32[[#This Row],[Risk Score]],"Yes","No"),"No"),"Yes") -> No
B45: Users | C45: MIS 595 Focus | D45: 5.2 | E45: Use Unique Passwords | F45: Employees must use unique passwords for each system, enforced through the Password Policy and monitored via technical controls. | G45: No Vulnerability | H45: 5 | I45: =IFERROR(VLOOKUP(tblRiskRegister32[[#This Row],[Asset Class]],tblVCDBIndex[],4,FALSE),"") -> 3 | J45: =IFERROR(VLOOKUP(10*tblRiskRegister32[[#This Row],[Safeguard Maturity Score]]+tblRiskRegister32[[#This Row],[VCDB Index]],tblHITIndexWeightTable[],4,FALSE),"") -> 1 | K45: =VLOOKUP(tblRiskRegister32[[#This Row],[Asset Class]],tblInherentImpacts30[],2,FALSE) -> 5 | L45: =VLOOKUP(tblRiskRegister32[[#This Row],[Asset Class]],tblInherentImpacts30[],3,FALSE) -> 5 | M45: =VLOOKUP(tblRiskRegister32[[#This Row],[Asset Class]],tblInherentImpacts30[],4,FALSE) -> 1 | N45: =VLOOKUP(tblRiskRegister32[[#This Row],[Asset Class]],tblInherentImpacts30[],5,FALSE) -> 5 | O45: =IFERROR(MAX(tblRiskRegister32[[#This Row],[Impact to Mission]:[Impact to Obligations]])*tblRiskRegister32[[#This Row],[Expectancy Score]],"") -> 5 | P45: =tblRiskRegister32[[#This Row],[Risk Score]] -> 5 | Q45: Accept | R45: 5.2 | S45: Use Unique Passwords | T45: Use unique passwords for all enterprise assets. Best practice implementation includes, at a minimum, an 8-character password for accounts using MFA and a 14-character password for accounts not using MFA. | W45: =IFERROR(VLOOKUP(10*tblRiskRegister32[[#This Row],[Risk Treatment Safeguard Maturity Score]]+tblRiskRegister32[[#This Row],[VCDB Index]],tblHITIndexWeightTable[],4,FALSE),"") | X45: =VLOOKUP(tblRiskRegister32[[#This Row],[Asset Class]],tblInherentImpacts30[],2,FALSE) -> 5 | Y45: =VLOOKUP(tblRiskRegister32[[#This Row],[Asset Class]],tblInherentImpacts30[],3,FALSE) -> 5 | Z45: =VLOOKUP(tblRiskRegister32[[#This Row],[Asset Class]],tblInherentImpacts30[],3,FALSE) -> 5 | AA45: =VLOOKUP(tblRiskRegister32[[#This Row],[Asset Class]],tblInherentImpacts30[],4,FALSE) -> 1 | AB45: =IFERROR(MAX(tblRiskRegister32[[#This Row],[Risk Treatment Safeguard Impact to Mission]:[Risk Treatment Safeguard Impact to Obligations]])*tblRiskRegister32[[#This Row],[Risk Treatment Safeguard Expectancy Score]],"") | AC45: =IF(tblRiskRegister32[[#This Row],[Risk Score]]>AcceptableRisk,IF(tblRiskRegister32[[#This Row],[Risk Treatment Safeguard Risk Score]]<AcceptableRisk, IF(tblRiskRegister32[[#This Row],[Risk Treatment Safeguard Risk Score]]<=tblRiskRegister32[[#This Row],[Risk Score]],"Yes","No"),"No"),"Yes") -> Yes
B46: Users | D46: 5.3 | E46: Disable Dormant Accounts | I46: =IFERROR(VLOOKUP(tblRiskRegister32[[#This Row],[Asset Class]],tblVCDBIndex[],4,FALSE),"") -> 3 | J46: =IFERROR(VLOOKUP(10*tblRiskRegister32[[#This Row],[Safeguard Maturity Score]]+tblRiskRegister32[[#This Row],[VCDB Index]],tblHITIndexWeightTable[],4,FALSE),"") | K46: =VLOOKUP(tblRiskRegister32[[#This Row],[Asset Class]],tblInherentImpacts30[],2,FALSE) -> 5 | L46: =VLOOKUP(tblRiskRegister32[[#This Row],[Asset Class]],tblInherentImpacts30[],3,FALSE) -> 5 | M46: =VLOOKUP(tblRiskRegister32[[#This Row],[Asset Class]],tblInherentImpacts30[],4,FALSE) -> 1 | N46: =VLOOKUP(tblRiskRegister32[[#This Row],[Asset Class]],tblInherentImpacts30[],5,FALSE) -> 5 | O46: =IFERROR(MAX(tblRiskRegister32[[#This Row],[Impact to Mission]:[Impact to Obligations]])*tblRiskRegister32[[#This Row],[Expectancy Score]],"") | P46: =tblRiskRegister32[[#This Row],[Risk Score]] | R46: 5.3 | S46: Disable Dormant Accounts | T46: Delete or disable any dormant accounts after a period of 45 days of inactivity, where supported. | W46: =IFERROR(VLOOKUP(10*tblRiskRegister32[[#This Row],[Risk Treatment Safeguard Maturity Score]]+tblRiskRegister32[[#This Row],[VCDB Index]],tblHITIndexWeightTable[],4,FALSE),"") | X46: =VLOOKUP(tblRiskRegister32[[#This Row],[Asset Class]],tblInherentImpacts30[],2,FALSE) -> 5 | Y46: =VLOOKUP(tblRiskRegister32[[#This Row],[Asset Class]],tblInherentImpacts30[],3,FALSE) -> 5 | Z46: =VLOOKUP(tblRiskRegister32[[#This Row],[Asset Class]],tblInherentImpacts30[],3,FALSE) -> 5 | AA46: =VLOOKUP(tblRiskRegister32[[#This Row],[Asset Class]],tblInherentImpacts30[],4,FALSE) -> 1 | AB46: =IFERROR(MAX(tblRiskRegister32[[#This Row],[Risk Treatment Safeguard Impact to Mission]:[Risk Treatment Safeguard Impact to Obligations]])*tblRiskRegister32[[#This Row],[Risk Treatment Safeguard Expectancy Score]],"") | AC46: =IF(tblRiskRegister32[[#This Row],[Risk Score]]>AcceptableRisk,IF(tblRiskRegister32[[#This Row],[Risk Treatment Safeguard Risk Score]]<AcceptableRisk, IF(tblRiskRegister32[[#This Row],[Risk Treatment Safeguard Risk Score]]<=tblRiskRegister32[[#This Row],[Risk Score]],"Yes","No"),"No"),"Yes") -> No
B47: Users | C47: MIS 595 Focus | D47: 5.4 | E47: Restrict Administrator Privileges to Dedicated Administrator Accounts | F47: Administrative privileges are assigned only to authorized IT staff, following least-privilege principles | G47: No Vulnerability | H47: 5 | I47: =IFERROR(VLOOKUP(tblRiskRegister32[[#This Row],[Asset Class]],tblVCDBIndex[],4,FALSE),"") -> 3 | J47: =IFERROR(VLOOKUP(10*tblRiskRegister32[[#This Row],[Safeguard Maturity Score]]+tblRiskRegister32[[#This Row],[VCDB Index]],tblHITIndexWeightTable[],4,FALSE),"") -> 1 | K47: =VLOOKUP(tblRiskRegister32[[#This Row],[Asset Class]],tblInherentImpacts30[],2,FALSE) -> 5 | L47: =VLOOKUP(tblRiskRegister32[[#This Row],[Asset Class]],tblInherentImpacts30[],3,FALSE) -> 5 | M47: =VLOOKUP(tblRiskRegister32[[#This Row],[Asset Class]],tblInherentImpacts30[],4,FALSE) -> 1 | N47: =VLOOKUP(tblRiskRegister32[[#This Row],[Asset Class]],tblInherentImpacts30[],5,FALSE) -> 5 | O47: =IFERROR(MAX(tblRiskRegister32[[#This Row],[Impact to Mission]:[Impact to Obligations]])*tblRiskRegister32[[#This Row],[Expectancy Score]],"") -> 5 | P47: =tblRiskRegister32[[#This Row],[Risk Score]] -> 5 | Q47: Accept | R47: 5.4 | S47: Restrict Administrator Privileges to Dedicated Administrator Accounts | T47: Restrict administrator privileges to dedicated administrator accounts on enterprise assets. Conduct general computing activities, such as internet browsing, email, and productivity suite use, from the user’s primary, non-privileged account. | W47: =IFERROR(VLOOKUP(10*tblRiskRegister32[[#This Row],[Risk Treatment Safeguard Maturity Score]]+tblRiskRegister32[[#This Row],[VCDB Index]],tblHITIndexWeightTable[],4,FALSE),"") | X47: =VLOOKUP(tblRiskRegister32[[#This Row],[Asset Class]],tblInherentImpacts30[],2,FALSE) -> 5 | Y47: =VLOOKUP(tblRiskRegister32[[#This Row],[Asset Class]],tblInherentImpacts30[],3,FALSE) -> 5 | Z47: =VLOOKUP(tblRiskRegister32[[#This Row],[Asset Class]],tblInherentImpacts30[],3,FALSE) -> 5 | AA47: =VLOOKUP(tblRiskRegister32[[#This Row],[Asset Class]],tblInherentImpacts30[],4,FALSE) -> 1 | AB47: =IFERROR(MAX(tblRiskRegister32[[#This Row],[Risk Treatment Safeguard Impact to Mission]:[Risk Treatment Safeguard Impact to Obligations]])*tblRiskRegister32[[#This Row],[Risk Treatment Safeguard Expectancy Score]],"") | AC47: =IF(tblRiskRegister32[[#This Row],[Risk Score]]>AcceptableRisk,IF(tblRiskRegister32[[#This Row],[Risk Treatment Safeguard Risk Score]]<AcceptableRisk, IF(tblRiskRegister32[[#This Row],[Risk Treatment Safeguard Risk Score]]<=tblRiskRegister32[[#This Row],[Risk Score]],"Yes","No"),"No"),"Yes") -> Yes
B48: Users | D48: 5.5 | E48: Establish and Maintain an Inventory of Service Accounts | I48: =IFERROR(VLOOKUP(tblRiskRegister32[[#This Row],[Asset Class]],tblVCDBIndex[],4,FALSE),"") -> 3 | J48: =IFERROR(VLOOKUP(10*tblRiskRegister32[[#This Row],[Safeguard Maturity Score]]+tblRiskRegister32[[#This Row],[VCDB Index]],tblHITIndexWeightTable[],4,FALSE),"") | K48: =VLOOKUP(tblRiskRegister32[[#This Row],[Asset Class]],tblInherentImpacts30[],2,FALSE) -> 5 | L48: =VLOOKUP(tblRiskRegister32[[#This Row],[Asset Class]],tblInherentImpacts30[],3,FALSE) -> 5 | M48: =VLOOKUP(tblRiskRegister32[[#This Row],[Asset Class]],tblInherentImpacts30[],4,FALSE) -> 1 | N48: =VLOOKUP(tblRiskRegister32[[#This Row],[Asset Class]],tblInherentImpacts30[],5,FALSE) -> 5 | O48: =IFERROR(MAX(tblRiskRegister32[[#This Row],[Impact to Mission]:[Impact to Obligations]])*tblRiskRegister32[[#This Row],[Expectancy Score]],"") | P48: =tblRiskRegister32[[#This Row],[Risk Score]] | R48: 5.5 | S48: Establish and Maintain an Inventory of Service Accounts | T48: Establish and maintain an inventory of service accounts. The inventory, at a minimum, must contain department owner, review date, and purpose. Perform service account reviews to validate that all active accounts are authorized, on a recurring schedule at a minimum quarterly, or more frequently. | W48: =IFERROR(VLOOKUP(10*tblRiskRegister32[[#This Row],[Risk Treatment Safeguard Maturity Score]]+tblRiskRegister32[[#This Row],[VCDB Index]],tblHITIndexWeightTable[],4,FALSE),"") | X48: =VLOOKUP(tblRiskRegister32[[#This Row],[Asset Class]],tblInherentImpacts30[],2,FALSE) -> 5 | Y48: =VLOOKUP(tblRiskRegister32[[#This Row],[Asset Class]],tblInherentImpacts30[],3,FALSE) -> 5 | Z48: =VLOOKUP(tblRiskRegister32[[#This Row],[Asset Class]],tblInherentImpacts30[],3,FALSE) -> 5 | AA48: =VLOOKUP(tblRiskRegister32[[#This Row],[Asset Class]],tblInherentImpacts30[],4,FALSE) -> 1 | AB48: =IFERROR(MAX(tblRiskRegister32[[#This Row],[Risk Treatment Safeguard Impact to Mission]:[Risk Treatment Safeguard Impact to Obligations]])*tblRiskRegister32[[#This Row],[Risk Treatment Safeguard Expectancy Score]],"") | AC48: =IF(tblRiskRegister32[[#This Row],[Risk Score]]>AcceptableRisk,IF(tblRiskRegister32[[#This Row],[Risk Treatment Safeguard Risk Score]]<AcceptableRisk, IF(tblRiskRegister32[[#This Row],[Risk Treatment Safeguard Risk Score]]<=tblRiskRegister32[[#This Row],[Risk Score]],"Yes","No"),"No"),"Yes") -> No
B49: Users | C49: MIS 595 Focus | D49: 5.6 | E49: Centralize Account Management | F49: User accounts are managed centrally through Active Directory, ensuring consistent enforcement of authentication rules. | G49: No Vulnerability | H49: 5 | I49: =IFERROR(VLOOKUP(tblRiskRegister32[[#This Row],[Asset Class]],tblVCDBIndex[],4,FALSE),"") -> 3 | J49: =IFERROR(VLOOKUP(10*tblRiskRegister32[[#This Row],[Safeguard Maturity Score]]+tblRiskRegister32[[#This Row],[VCDB Index]],tblHITIndexWeightTable[],4,FALSE),"") -> 1 | K49: =VLOOKUP(tblRiskRegister32[[#This Row],[Asset Class]],tblInherentImpacts30[],2,FALSE) -> 5 | L49: =VLOOKUP(tblRiskRegister32[[#This Row],[Asset Class]],tblInherentImpacts30[],3,FALSE) -> 5 | M49: =VLOOKUP(tblRiskRegister32[[#This Row],[Asset Class]],tblInherentImpacts30[],4,FALSE) -> 1 | N49: =VLOOKUP(tblRiskRegister32[[#This Row],[Asset Class]],tblInherentImpacts30[],5,FALSE) -> 5 | O49: =IFERROR(MAX(tblRiskRegister32[[#This Row],[Impact to Mission]:[Impact to Obligations]])*tblRiskRegister32[[#This Row],[Expectancy Score]],"") -> 5 | P49: =tblRiskRegister32[[#This Row],[Risk Score]] -> 5 | Q49: Accept | R49: 5.6 | S49: Centralize Account Management | T49: Centralize account management through a directory or identity service. | W49: =IFERROR(VLOOKUP(10*tblRiskRegister32[[#This Row],[Risk Treatment Safeguard Maturity Score]]+tblRiskRegister32[[#This Row],[VCDB Index]],tblHITIndexWeightTable[],4,FALSE),"") | X49: =VLOOKUP(tblRiskRegister32[[#This Row],[Asset Class]],tblInherentImpacts30[],2,FALSE) -> 5 | Y49: =VLOOKUP(tblRiskRegister32[[#This Row],[Asset Class]],tblInherentImpacts30[],3,FALSE) -> 5 | Z49: =VLOOKUP(tblRiskRegister32[[#This Row],[Asset Class]],tblInherentImpacts30[],3,FALSE) -> 5 | AA49: =VLOOKUP(tblRiskRegister32[[#This Row],[Asset Class]],tblInherentImpacts30[],4,FALSE) -> 1 | AB49: =IFERROR(MAX(tblRiskRegister32[[#This Row],[Risk Treatment Safeguard Impact to Mission]:[Risk Treatment Safeguard Impact to Obligations]])*tblRiskRegister32[[#This Row],[Risk Treatment Safeguard Expectancy Score]],"") | AC49: =IF(tblRiskRegister32[[#This Row],[Risk Score]]>AcceptableRisk,IF(tblRiskRegister32[[#This Row],[Risk Treatment Safeguard Risk Score]]<AcceptableRisk, IF(tblRiskRegister32[[#This Row],[Risk Treatment Safeguard Risk Score]]<=tblRiskRegister32[[#This Row],[Risk Score]],"Yes","No"),"No"),"Yes") -> Yes
B50: Users | C50: MIS 595 Focus | D50: 6.1 | E50: Establish an Access Granting Process | F50: New user access is provisioned through a formal request and approval workflow aligned with our IAM procedures. | G50: No Vulnerability | H50: 5 | I50: =IFERROR(VLOOKUP(tblRiskRegister32[[#This Row],[Asset Class]],tblVCDBIndex[],4,FALSE),"") -> 3 | J50: =IFERROR(VLOOKUP(10*tblRiskRegister32[[#This Row],[Safeguard Maturity Score]]+tblRiskRegister32[[#This Row],[VCDB Index]],tblHITIndexWeightTable[],4,FALSE),"") -> 1 | K50: =VLOOKUP(tblRiskRegister32[[#This Row],[Asset Class]],tblInherentImpacts30[],2,FALSE) -> 5 | L50: =VLOOKUP(tblRiskRegister32[[#This Row],[Asset Class]],tblInherentImpacts30[],3,FALSE) -> 5 | M50: =VLOOKUP(tblRiskRegister32[[#This Row],[Asset Class]],tblInherentImpacts30[],4,FALSE) -> 1 | N50: =VLOOKUP(tblRiskRegister32[[#This Row],[Asset Class]],tblInherentImpacts30[],5,FALSE) -> 5 | O50: =IFERROR(MAX(tblRiskRegister32[[#This Row],[Impact to Mission]:[Impact to Obligations]])*tblRiskRegister32[[#This Row],[Expectancy Score]],"") -> 5 | P50: =tblRiskRegister32[[#This Row],[Risk Score]] -> 5 | Q50: Accept | R50: 6.1 | S50: Establish an Access Granting Process | T50: Establish and follow a process, preferably automated, for granting access to enterprise assets upon new hire, rights grant, or role change of a user. | W50: =IFERROR(VLOOKUP(10*tblRiskRegister32[[#This Row],[Risk Treatment Safeguard Maturity Score]]+tblRiskRegister32[[#This Row],[VCDB Index]],tblHITIndexWeightTable[],4,FALSE),"") | X50: =VLOOKUP(tblRiskRegister32[[#This Row],[Asset Class]],tblInherentImpacts30[],2,FALSE) -> 5 | Y50: =VLOOKUP(tblRiskRegister32[[#This Row],[Asset Class]],tblInherentImpacts30[],3,FALSE) -> 5 | Z50: =VLOOKUP(tblRiskRegister32[[#This Row],[Asset Class]],tblInherentImpacts30[],3,FALSE) -> 5 | AA50: =VLOOKUP(tblRiskRegister32[[#This Row],[Asset Class]],tblInherentImpacts30[],4,FALSE) -> 1 | AB50: =IFERROR(MAX(tblRiskRegister32[[#This Row],[Risk Treatment Safeguard Impact to Mission]:[Risk Treatment Safeguard Impact to Obligations]])*tblRiskRegister32[[#This Row],[Risk Treatment Safeguard Expectancy Score]],"") | AC50: =IF(tblRiskRegister32[[#This Row],[Risk Score]]>AcceptableRisk,IF(tblRiskRegister32[[#This Row],[Risk Treatment Safeguard Risk Score]]<AcceptableRisk, IF(tblRiskRegister32[[#This Row],[Risk Treatment Safeguard Risk Score]]<=tblRiskRegister32[[#This Row],[Risk Score]],"Yes","No"),"No"),"Yes") -> Yes
B51: Users | C51: MIS 595 Focus | D51: 6.2 | E51: Establish an Access Revoking Process | F51: User access is removed immediately upon termination or role change through HR-triggered deprovisioning. | G51: Access is not consistently revoked immediately when employees change roles or leave the organization. | H51: 2 | I51: =IFERROR(VLOOKUP(tblRiskRegister32[[#This Row],[Asset Class]],tblVCDBIndex[],4,FALSE),"") -> 3 | J51: =IFERROR(VLOOKUP(10*tblRiskRegister32[[#This Row],[Safeguard Maturity Score]]+tblRiskRegister32[[#This Row],[VCDB Index]],tblHITIndexWeightTable[],4,FALSE),"") -> 4 | K51: =VLOOKUP(tblRiskRegister32[[#This Row],[Asset Class]],tblInherentImpacts30[],2,FALSE) -> 5 | L51: =VLOOKUP(tblRiskRegister32[[#This Row],[Asset Class]],tblInherentImpacts30[],3,FALSE) -> 5 | M51: =VLOOKUP(tblRiskRegister32[[#This Row],[Asset Class]],tblInherentImpacts30[],4,FALSE) -> 1 | N51: =VLOOKUP(tblRiskRegister32[[#This Row],[Asset Class]],tblInherentImpacts30[],5,FALSE) -> 5 | O51: =IFERROR(MAX(tblRiskRegister32[[#This Row],[Impact to Mission]:[Impact to Obligations]])*tblRiskRegister32[[#This Row],[Expectancy Score]],"") -> 20 | P51: =tblRiskRegister32[[#This Row],[Risk Score]] -> 20 | Q51: Reduce | R51: 6.2 | S51: Establish an Access Revoking Process | T51: Establish and follow a process, preferably automated, for revoking access to enterprise assets, through disabling accounts immediately upon termination, rights revocation, or role change of a user. Disabling accounts, instead of deleting accounts, may be necessary to preserve audit trails. | W51: =IFERROR(VLOOKUP(10*tblRiskRegister32[[#This Row],[Risk Treatment Safeguard Maturity Score]]+tblRiskRegister32[[#This Row],[VCDB Index]],tblHITIndexWeightTable[],4,FALSE),"") | X51: =VLOOKUP(tblRiskRegister32[[#This Row],[Asset Class]],tblInherentImpacts30[],2,FALSE) -> 5 | Y51: =VLOOKUP(tblRiskRegister32[[#This Row],[Asset Class]],tblInherentImpacts30[],3,FALSE) -> 5 | Z51: =VLOOKUP(tblRiskRegister32[[#This Row],[Asset Class]],tblInherentImpacts30[],3,FALSE) -> 5 | AA51: =VLOOKUP(tblRiskRegister32[[#This Row],[Asset Class]],tblInherentImpacts30[],4,FALSE) -> 1 | AB51: =IFERROR(MAX(tblRiskRegister32[[#This Row],[Risk Treatment Safeguard Impact to Mission]:[Risk Treatment Safeguard Impact to Obligations]])*tblRiskRegister32[[#This Row],[Risk Treatment Safeguard Expectancy Score]],"") | AC51: =IF(tblRiskRegister32[[#This Row],[Risk Score]]>AcceptableRisk,IF(tblRiskRegister32[[#This Row],[Risk Treatment Safeguard Risk Score]]<AcceptableRisk, IF(tblRiskRegister32[[#This Row],[Risk Treatment Safeguard Risk Score]]<=tblRiskRegister32[[#This Row],[Risk Score]],"Yes","No"),"No"),"Yes") -> No
B52: Users | D52: 6.3 | E52: Require MFA for Externally-Exposed Applications | I52: =IFERROR(VLOOKUP(tblRiskRegister32[[#This Row],[Asset Class]],tblVCDBIndex[],4,FALSE),"") -> 3 | J52: =IFERROR(VLOOKUP(10*tblRiskRegister32[[#This Row],[Safeguard Maturity Score]]+tblRiskRegister32[[#This Row],[VCDB Index]],tblHITIndexWeightTable[],4,FALSE),"") | K52: =VLOOKUP(tblRiskRegister32[[#This Row],[Asset Class]],tblInherentImpacts30[],2,FALSE) -> 5 | L52: =VLOOKUP(tblRiskRegister32[[#This Row],[Asset Class]],tblInherentImpacts30[],3,FALSE) -> 5 | M52: =VLOOKUP(tblRiskRegister32[[#This Row],[Asset Class]],tblInherentImpacts30[],4,FALSE) -> 1 | N52: =VLOOKUP(tblRiskRegister32[[#This Row],[Asset Class]],tblInherentImpacts30[],5,FALSE) -> 5 | O52: =IFERROR(MAX(tblRiskRegister32[[#This Row],[Impact to Mission]:[Impact to Obligations]])*tblRiskRegister32[[#This Row],[Expectancy Score]],"") | P52: =tblRiskRegister32[[#This Row],[Risk Score]] | R52: 6.3 | S52: Require MFA for Externally-Exposed Applications | T52: Require all externally-exposed enterprise or third-party applications to enforce MFA, where supported. Enforcing MFA through a directory service or SSO provider is a satisfactory implementation of this Safeguard. | W52: =IFERROR(VLOOKUP(10*tblRiskRegister32[[#This Row],[Risk Treatment Safeguard Maturity Score]]+tblRiskRegister32[[#This Row],[VCDB Index]],tblHITIndexWeightTable[],4,FALSE),"") | X52: =VLOOKUP(tblRiskRegister32[[#This Row],[Asset Class]],tblInherentImpacts30[],2,FALSE) -> 5 | Y52: =VLOOKUP(tblRiskRegister32[[#This Row],[Asset Class]],tblInherentImpacts30[],3,FALSE) -> 5 | Z52: =VLOOKUP(tblRiskRegister32[[#This Row],[Asset Class]],tblInherentImpacts30[],3,FALSE) -> 5 | AA52: =VLOOKUP(tblRiskRegister32[[#This Row],[Asset Class]],tblInherentImpacts30[],4,FALSE) -> 1 | AB52: =IFERROR(MAX(tblRiskRegister32[[#This Row],[Risk Treatment Safeguard Impact to Mission]:[Risk Treatment Safeguard Impact to Obligations]])*tblRiskRegister32[[#This Row],[Risk Treatment Safeguard Expectancy Score]],"") | AC52: =IF(tblRiskRegister32[[#This Row],[Risk Score]]>AcceptableRisk,IF(tblRiskRegister32[[#This Row],[Risk Treatment Safeguard Risk Score]]<AcceptableRisk, IF(tblRiskRegister32[[#This Row],[Risk Treatment Safeguard Risk Score]]<=tblRiskRegister32[[#This Row],[Risk Score]],"Yes","No"),"No"),"Yes") -> No
B53: Users | C53: MIS 595 Focus | D53: 6.4 | E53: Require MFA for Remote Network Access | F53: Remote access requires multi-factor authentication, enforced through the enterprise VPN solution. | G53: No Vulnerability | H53: 5 | I53: =IFERROR(VLOOKUP(tblRiskRegister32[[#This Row],[Asset Class]],tblVCDBIndex[],4,FALSE),"") -> 3 | J53: =IFERROR(VLOOKUP(10*tblRiskRegister32[[#This Row],[Safeguard Maturity Score]]+tblRiskRegister32[[#This Row],[VCDB Index]],tblHITIndexWeightTable[],4,FALSE),"") -> 1 | K53: =VLOOKUP(tblRiskRegister32[[#This Row],[Asset Class]],tblInherentImpacts30[],2,FALSE) -> 5 | L53: =VLOOKUP(tblRiskRegister32[[#This Row],[Asset Class]],tblInherentImpacts30[],3,FALSE) -> 5 | M53: =VLOOKUP(tblRiskRegister32[[#This Row],[Asset Class]],tblInherentImpacts30[],4,FALSE) -> 1 | N53: =VLOOKUP(tblRiskRegister32[[#This Row],[Asset Class]],tblInherentImpacts30[],5,FALSE) -> 5 | O53: =IFERROR(MAX(tblRiskRegister32[[#This Row],[Impact to Mission]:[Impact to Obligations]])*tblRiskRegister32[[#This Row],[Expectancy Score]],"") -> 5 | P53: =tblRiskRegister32[[#This Row],[Risk Score]] -> 5 | Q53: Accept | R53: 6.4 | S53: Require MFA for Remote Network Access | T53: Require MFA for remote network access. | W53: =IFERROR(VLOOKUP(10*tblRiskRegister32[[#This Row],[Risk Treatment Safeguard Maturity Score]]+tblRiskRegister32[[#This Row],[VCDB Index]],tblHITIndexWeightTable[],4,FALSE),"") | X53: =VLOOKUP(tblRiskRegister32[[#This Row],[Asset Class]],tblInherentImpacts30[],2,FALSE) -> 5 | Y53: =VLOOKUP(tblRiskRegister32[[#This Row],[Asset Class]],tblInherentImpacts30[],3,FALSE) -> 5 | Z53: =VLOOKUP(tblRiskRegister32[[#This Row],[Asset Class]],tblInherentImpacts30[],3,FALSE) -> 5 | AA53: =VLOOKUP(tblRiskRegister32[[#This Row],[Asset Class]],tblInherentImpacts30[],4,FALSE) -> 1 | AB53: =IFERROR(MAX(tblRiskRegister32[[#This Row],[Risk Treatment Safeguard Impact to Mission]:[Risk Treatment Safeguard Impact to Obligations]])*tblRiskRegister32[[#This Row],[Risk Treatment Safeguard Expectancy Score]],"") | AC53: =IF(tblRiskRegister32[[#This Row],[Risk Score]]>AcceptableRisk,IF(tblRiskRegister32[[#This Row],[Risk Treatment Safeguard Risk Score]]<AcceptableRisk, IF(tblRiskRegister32[[#This Row],[Risk Treatment Safeguard Risk Score]]<=tblRiskRegister32[[#This Row],[Risk Score]],"Yes","No"),"No"),"Yes") -> Yes
B54: Users | C54: MIS 595 Focus | D54: 6.5 | E54: Require MFA for Administrative Access | F54: All privileged administrative accounts require MFA as an added layer of protection. | G54: No Vulnerability | H54: 5 | I54: =IFERROR(VLOOKUP(tblRiskRegister32[[#This Row],[Asset Class]],tblVCDBIndex[],4,FALSE),"") -> 3 | J54: =IFERROR(VLOOKUP(10*tblRiskRegister32[[#This Row],[Safeguard Maturity Score]]+tblRiskRegister32[[#This Row],[VCDB Index]],tblHITIndexWeightTable[],4,FALSE),"") -> 1 | K54: =VLOOKUP(tblRiskRegister32[[#This Row],[Asset Class]],tblInherentImpacts30[],2,FALSE) -> 5 | L54: =VLOOKUP(tblRiskRegister32[[#This Row],[Asset Class]],tblInherentImpacts30[],3,FALSE) -> 5 | M54: =VLOOKUP(tblRiskRegister32[[#This Row],[Asset Class]],tblInherentImpacts30[],4,FALSE) -> 1 | N54: =VLOOKUP(tblRiskRegister32[[#This Row],[Asset Class]],tblInherentImpacts30[],5,FALSE) -> 5 | O54: =IFERROR(MAX(tblRiskRegister32[[#This Row],[Impact to Mission]:[Impact to Obligations]])*tblRiskRegister32[[#This Row],[Expectancy Score]],"") -> 5 | P54: =tblRiskRegister32[[#This Row],[Risk Score]] -> 5 | Q54: Accept | R54: 6.5 | S54: Require MFA for Administrative Access | T54: Require MFA for all administrative access accounts, where supported, on all enterprise assets, whether managed on-site or through a third-party provider. | W54: =IFERROR(VLOOKUP(10*tblRiskRegister32[[#This Row],[Risk Treatment Safeguard Maturity Score]]+tblRiskRegister32[[#This Row],[VCDB Index]],tblHITIndexWeightTable[],4,FALSE),"") | X54: =VLOOKUP(tblRiskRegister32[[#This Row],[Asset Class]],tblInherentImpacts30[],2,FALSE) -> 5 | Y54: =VLOOKUP(tblRiskRegister32[[#This Row],[Asset Class]],tblInherentImpacts30[],3,FALSE) -> 5 | Z54: =VLOOKUP(tblRiskRegister32[[#This Row],[Asset Class]],tblInherentImpacts30[],3,FALSE) -> 5 | AA54: =VLOOKUP(tblRiskRegister32[[#This Row],[Asset Class]],tblInherentImpacts30[],4,FALSE) -> 1 | AB54: =IFERROR(MAX(tblRiskRegister32[[#This Row],[Risk Treatment Safeguard Impact to Mission]:[Risk Treatment Safeguard Impact to Obligations]])*tblRiskRegister32[[#This Row],[Risk Treatment Safeguard Expectancy Score]],"") | AC54: =IF(tblRiskRegister32[[#This Row],[Risk Score]]>AcceptableRisk,IF(tblRiskRegister32[[#This Row],[Risk Treatment Safeguard Risk Score]]<AcceptableRisk, IF(tblRiskRegister32[[#This Row],[Risk Treatment Safeguard Risk Score]]<=tblRiskRegister32[[#This Row],[Risk Score]],"Yes","No"),"No"),"Yes") -> Yes
B55: Users | D55: 6.6 | E55: Establish and Maintain an Inventory of Authentication and Authorization Systems | I55: =IFERROR(VLOOKUP(tblRiskRegister32[[#This Row],[Asset Class]],tblVCDBIndex[],4,FALSE),"") -> 3 | J55: =IFERROR(VLOOKUP(10*tblRiskRegister32[[#This Row],[Safeguard Maturity Score]]+tblRiskRegister32[[#This Row],[VCDB Index]],tblHITIndexWeightTable[],4,FALSE),"") | K55: =VLOOKUP(tblRiskRegister32[[#This Row],[Asset Class]],tblInherentImpacts30[],2,FALSE) -> 5 | L55: =VLOOKUP(tblRiskRegister32[[#This Row],[Asset Class]],tblInherentImpacts30[],3,FALSE) -> 5 | M55: =VLOOKUP(tblRiskRegister32[[#This Row],[Asset Class]],tblInherentImpacts30[],4,FALSE) -> 1 | N55: =VLOOKUP(tblRiskRegister32[[#This Row],[Asset Class]],tblInherentImpacts30[],5,FALSE) -> 5 | O55: =IFERROR(MAX(tblRiskRegister32[[#This Row],[Impact to Mission]:[Impact to Obligations]])*tblRiskRegister32[[#This Row],[Expectancy Score]],"") | P55: =tblRiskRegister32[[#This Row],[Risk Score]] | R55: 6.6 | S55: Establish and Maintain an Inventory of Authentication and Authorization Systems | T55: Establish and maintain an inventory of the enterprise’s authentication and authorization systems, including those hosted on-site or at a remote service provider. Review and update the inventory, at a minimum, annually, or more frequently. | W55: =IFERROR(VLOOKUP(10*tblRiskRegister32[[#This Row],[Risk Treatment Safeguard Maturity Score]]+tblRiskRegister32[[#This Row],[VCDB Index]],tblHITIndexWeightTable[],4,FALSE),"") | X55: =VLOOKUP(tblRiskRegister32[[#This Row],[Asset Class]],tblInherentImpacts30[],2,FALSE) -> 5 | Y55: =VLOOKUP(tblRiskRegister32[[#This Row],[Asset Class]],tblInherentImpacts30[],3,FALSE) -> 5 | Z55: =VLOOKUP(tblRiskRegister32[[#This Row],[Asset Class]],tblInherentImpacts30[],3,FALSE) -> 5 | AA55: =VLOOKUP(tblRiskRegister32[[#This Row],[Asset Class]],tblInherentImpacts30[],4,FALSE) -> 1 | AB55: =IFERROR(MAX(tblRiskRegister32[[#This Row],[Risk Treatment Safeguard Impact to Mission]:[Risk Treatment Safeguard Impact to Obligations]])*tblRiskRegister32[[#This Row],[Risk Treatment Safeguard Expectancy Score]],"") | AC55: =IF(tblRiskRegister32[[#This Row],[Risk Score]]>AcceptableRisk,IF(tblRiskRegister32[[#This Row],[Risk Treatment Safeguard Risk Score]]<AcceptableRisk, IF(tblRiskRegister32[[#This Row],[Risk Treatment Safeguard Risk Score]]<=tblRiskRegister32[[#This Row],[Risk Score]],"Yes","No"),"No"),"Yes") -> No
B56: Users | C56: MIS 595 Focus | D56: 6.7 | E56: Centralize Access Control | F56: Access permissions are centrally managed in Active Directory to ensure consistent permissions across systems. | G56: No Vulnerability | H56: 5 | I56: =IFERROR(VLOOKUP(tblRiskRegister32[[#This Row],[Asset Class]],tblVCDBIndex[],4,FALSE),"") -> 3 | J56: =IFERROR(VLOOKUP(10*tblRiskRegister32[[#This Row],[Safeguard Maturity Score]]+tblRiskRegister32[[#This Row],[VCDB Index]],tblHITIndexWeightTable[],4,FALSE),"") -> 1 | K56: =VLOOKUP(tblRiskRegister32[[#This Row],[Asset Class]],tblInherentImpacts30[],2,FALSE) -> 5 | L56: =VLOOKUP(tblRiskRegister32[[#This Row],[Asset Class]],tblInherentImpacts30[],3,FALSE) -> 5 | M56: =VLOOKUP(tblRiskRegister32[[#This Row],[Asset Class]],tblInherentImpacts30[],4,FALSE) -> 1 | N56: =VLOOKUP(tblRiskRegister32[[#This Row],[Asset Class]],tblInherentImpacts30[],5,FALSE) -> 5 | O56: =IFERROR(MAX(tblRiskRegister32[[#This Row],[Impact to Mission]:[Impact to Obligations]])*tblRiskRegister32[[#This Row],[Expectancy Score]],"") -> 5 | P56: =tblRiskRegister32[[#This Row],[Risk Score]] -> 5 | Q56: Accept | R56: 6.7 | S56: Centralize Access Control | T56: Centralize access control for all enterprise assets through a directory service or SSO provider, where supported. | W56: =IFERROR(VLOOKUP(10*tblRiskRegister32[[#This Row],[Risk Treatment Safeguard Maturity Score]]+tblRiskRegister32[[#This Row],[VCDB Index]],tblHITIndexWeightTable[],4,FALSE),"") | X56: =VLOOKUP(tblRiskRegister32[[#This Row],[Asset Class]],tblInherentImpacts30[],2,FALSE) -> 5 | Y56: =VLOOKUP(tblRiskRegister32[[#This Row],[Asset Class]],tblInherentImpacts30[],3,FALSE) -> 5 | Z56: =VLOOKUP(tblRiskRegister32[[#This Row],[Asset Class]],tblInherentImpacts30[],3,FALSE) -> 5 | AA56: =VLOOKUP(tblRiskRegister32[[#This Row],[Asset Class]],tblInherentImpacts30[],4,FALSE) -> 1 | AB56: =IFERROR(MAX(tblRiskRegister32[[#This Row],[Risk Treatment Safeguard Impact to Mission]:[Risk Treatment Safeguard Impact to Obligations]])*tblRiskRegister32[[#This Row],[Risk Treatment Safeguard Expectancy Score]],"") | AC56: =IF(tblRiskRegister32[[#This Row],[Risk Score]]>AcceptableRisk,IF(tblRiskRegister32[[#This Row],[Risk Treatment Safeguard Risk Score]]<AcceptableRisk, IF(tblRiskRegister32[[#This Row],[Risk Treatment Safeguard Risk Score]]<=tblRiskRegister32[[#This Row],[Risk Score]],"Yes","No"),"No"),"Yes") -> Yes
B57: Applications | C57: MIS 595 Focus | D57: 7.1 | E57: Establish and Maintain a Vulnerability Management Process | F57: Fabella Bank performs routine scanning, patching, and reporting as part of its Vulnerability Management Program. | G57: No Vulnerability | H57: 5 | I57: =IFERROR(VLOOKUP(tblRiskRegister32[[#This Row],[Asset Class]],tblVCDBIndex[],4,FALSE),"") -> 2 | J57: =IFERROR(VLOOKUP(10*tblRiskRegister32[[#This Row],[Safeguard Maturity Score]]+tblRiskRegister32[[#This Row],[VCDB Index]],tblHITIndexWeightTable[],4,FALSE),"") -> 1 | K57: =VLOOKUP(tblRiskRegister32[[#This Row],[Asset Class]],tblInherentImpacts30[],2,FALSE) -> 3 | L57: =VLOOKUP(tblRiskRegister32[[#This Row],[Asset Class]],tblInherentImpacts30[],3,FALSE) -> 4 | M57: =VLOOKUP(tblRiskRegister32[[#This Row],[Asset Class]],tblInherentImpacts30[],4,FALSE) -> 1 | N57: =VLOOKUP(tblRiskRegister32[[#This Row],[Asset Class]],tblInherentImpacts30[],5,FALSE) -> 4 | O57: =IFERROR(MAX(tblRiskRegister32[[#This Row],[Impact to Mission]:[Impact to Obligations]])*tblRiskRegister32[[#This Row],[Expectancy Score]],"") -> 4 | P57: =tblRiskRegister32[[#This Row],[Risk Score]] -> 4 | Q57: Accept | R57: 7.1 | S57: Establish and Maintain a Vulnerability Management Process | T57: Establish and maintain a documented vulnerability management process for enterprise assets. Review and update documentation annually, or when significant enterprise changes occur that could impact this Safeguard. | W57: =IFERROR(VLOOKUP(10*tblRiskRegister32[[#This Row],[Risk Treatment Safeguard Maturity Score]]+tblRiskRegister32[[#This Row],[VCDB Index]],tblHITIndexWeightTable[],4,FALSE),"") | X57: =VLOOKUP(tblRiskRegister32[[#This Row],[Asset Class]],tblInherentImpacts30[],2,FALSE) -> 3 | Y57: =VLOOKUP(tblRiskRegister32[[#This Row],[Asset Class]],tblInherentImpacts30[],3,FALSE) -> 4 | Z57: =VLOOKUP(tblRiskRegister32[[#This Row],[Asset Class]],tblInherentImpacts30[],3,FALSE) -> 4 | AA57: =VLOOKUP(tblRiskRegister32[[#This Row],[Asset Class]],tblInherentImpacts30[],4,FALSE) -> 1 | AB57: =IFERROR(MAX(tblRiskRegister32[[#This Row],[Risk Treatment Safeguard Impact to Mission]:[Risk Treatment Safeguard Impact to Obligations]])*tblRiskRegister32[[#This Row],[Risk Treatment Safeguard Expectancy Score]],"") | AC57: =IF(tblRiskRegister32[[#This Row],[Risk Score]]>AcceptableRisk,IF(tblRiskRegister32[[#This Row],[Risk Treatment Safeguard Risk Score]]<AcceptableRisk, IF(tblRiskRegister32[[#This Row],[Risk Treatment Safeguard Risk Score]]<=tblRiskRegister32[[#This Row],[Risk Score]],"Yes","No"),"No"),"Yes") -> Yes
B58: Applications | C58: MIS 595 Focus | D58: 7.2 | E58: Establish and Maintain a Remediation Process | F58: Identified vulnerabilities are assigned, tracked, and remediated based on severity and remediation timelines. | G58: No Vulnerability | H58: 4 | I58: =IFERROR(VLOOKUP(tblRiskRegister32[[#This Row],[Asset Class]],tblVCDBIndex[],4,FALSE),"") -> 2 | J58: =IFERROR(VLOOKUP(10*tblRiskRegister32[[#This Row],[Safeguard Maturity Score]]+tblRiskRegister32[[#This Row],[VCDB Index]],tblHITIndexWeightTable[],4,FALSE),"") -> 2 | K58: =VLOOKUP(tblRiskRegister32[[#This Row],[Asset Class]],tblInherentImpacts30[],2,FALSE) -> 3 | L58: =VLOOKUP(tblRiskRegister32[[#This Row],[Asset Class]],tblInherentImpacts30[],3,FALSE) -> 4 | M58: =VLOOKUP(tblRiskRegister32[[#This Row],[Asset Class]],tblInherentImpacts30[],4,FALSE) -> 1 | N58: =VLOOKUP(tblRiskRegister32[[#This Row],[Asset Class]],tblInherentImpacts30[],5,FALSE) -> 4 | O58: =IFERROR(MAX(tblRiskRegister32[[#This Row],[Impact to Mission]:[Impact to Obligations]])*tblRiskRegister32[[#This Row],[Expectancy Score]],"") -> 8 | P58: =tblRiskRegister32[[#This Row],[Risk Score]] -> 8 | Q58: Accept | R58: 7.2 | S58: Establish and Maintain a Remediation Process | T58: Establish and maintain a risk-based remediation strategy documented in a remediation process, with monthly, or more frequent, reviews. | W58: =IFERROR(VLOOKUP(10*tblRiskRegister32[[#This Row],[Risk Treatment Safeguard Maturity Score]]+tblRiskRegister32[[#This Row],[VCDB Index]],tblHITIndexWeightTable[],4,FALSE),"") | X58: =VLOOKUP(tblRiskRegister32[[#This Row],[Asset Class]],tblInherentImpacts30[],2,FALSE) -> 3 | Y58: =VLOOKUP(tblRiskRegister32[[#This Row],[Asset Class]],tblInherentImpacts30[],3,FALSE) -> 4 | Z58: =VLOOKUP(tblRiskRegister32[[#This Row],[Asset Class]],tblInherentImpacts30[],3,FALSE) -> 4 | AA58: =VLOOKUP(tblRiskRegister32[[#This Row],[Asset Class]],tblInherentImpacts30[],4,FALSE) -> 1 | AB58: =IFERROR(MAX(tblRiskRegister32[[#This Row],[Risk Treatment Safeguard Impact to Mission]:[Risk Treatment Safeguard Impact to Obligations]])*tblRiskRegister32[[#This Row],[Risk Treatment Safeguard Expectancy Score]],"") | AC58: =IF(tblRiskRegister32[[#This Row],[Risk Score]]>AcceptableRisk,IF(tblRiskRegister32[[#This Row],[Risk Treatment Safeguard Risk Score]]<AcceptableRisk, IF(tblRiskRegister32[[#This Row],[Risk Treatment Safeguard Risk Score]]<=tblRiskRegister32[[#This Row],[Risk Score]],"Yes","No"),"No"),"Yes") -> Yes
B59: Applications | C59: MIS 595 Focus | D59: 7.3 | E59: Perform Automated Operating System Patch Management | F59: Operating system updates are deployed automatically using enterprise patch-management tools. | G59: No Vulnerability | H59: 3 | I59: =IFERROR(VLOOKUP(tblRiskRegister32[[#This Row],[Asset Class]],tblVCDBIndex[],4,FALSE),"") -> 2 | J59: =IFERROR(VLOOKUP(10*tblRiskRegister32[[#This Row],[Safeguard Maturity Score]]+tblRiskRegister32[[#This Row],[VCDB Index]],tblHITIndexWeightTable[],4,FALSE),"") -> 2 | K59: =VLOOKUP(tblRiskRegister32[[#This Row],[Asset Class]],tblInherentImpacts30[],2,FALSE) -> 3 | L59: =VLOOKUP(tblRiskRegister32[[#This Row],[Asset Class]],tblInherentImpacts30[],3,FALSE) -> 4 | M59: =VLOOKUP(tblRiskRegister32[[#This Row],[Asset Class]],tblInherentImpacts30[],4,FALSE) -> 1 | N59: =VLOOKUP(tblRiskRegister32[[#This Row],[Asset Class]],tblInherentImpacts30[],5,FALSE) -> 4 | O59: =IFERROR(MAX(tblRiskRegister32[[#This Row],[Impact to Mission]:[Impact to Obligations]])*tblRiskRegister32[[#This Row],[Expectancy Score]],"") -> 8 | P59: =tblRiskRegister32[[#This Row],[Risk Score]] -> 8 | Q59: Accept | R59: 7.3 | S59: Perform Automated Operating System Patch Management | T59: Perform operating system updates on enterprise assets through automated patch management on a monthly, or more frequent, basis. | W59: =IFERROR(VLOOKUP(10*tblRiskRegister32[[#This Row],[Risk Treatment Safeguard Maturity Score]]+tblRiskRegister32[[#This Row],[VCDB Index]],tblHITIndexWeightTable[],4,FALSE),"") | X59: =VLOOKUP(tblRiskRegister32[[#This Row],[Asset Class]],tblInherentImpacts30[],2,FALSE) -> 3 | Y59: =VLOOKUP(tblRiskRegister32[[#This Row],[Asset Class]],tblInherentImpacts30[],3,FALSE) -> 4 | Z59: =VLOOKUP(tblRiskRegister32[[#This Row],[Asset Class]],tblInherentImpacts30[],3,FALSE) -> 4 | AA59: =VLOOKUP(tblRiskRegister32[[#This Row],[Asset Class]],tblInherentImpacts30[],4,FALSE) -> 1 | AB59: =IFERROR(MAX(tblRiskRegister32[[#This Row],[Risk Treatment Safeguard Impact to Mission]:[Risk Treatment Safeguard Impact to Obligations]])*tblRiskRegister32[[#This Row],[Risk Treatment Safeguard Expectancy Score]],"") | AC59: =IF(tblRiskRegister32[[#This Row],[Risk Score]]>AcceptableRisk,IF(tblRiskRegister32[[#This Row],[Risk Treatment Safeguard Risk Score]]<AcceptableRisk, IF(tblRiskRegister32[[#This Row],[Risk Treatment Safeguard Risk Score]]<=tblRiskRegister32[[#This Row],[Risk Score]],"Yes","No"),"No"),"Yes") -> Yes
B60: Applications | C60: MIS 595 Focus | D60: 7.4 | E60: Perform Automated Application Patch Management | F60: Applications receive automated patches through centralized endpoint management platforms. | G60: No Vulnerability | H60: 4 | I60: =IFERROR(VLOOKUP(tblRiskRegister32[[#This Row],[Asset Class]],tblVCDBIndex[],4,FALSE),"") -> 2 | J60: =IFERROR(VLOOKUP(10*tblRiskRegister32[[#This Row],[Safeguard Maturity Score]]+tblRiskRegister32[[#This Row],[VCDB Index]],tblHITIndexWeightTable[],4,FALSE),"") -> 2 | K60: =VLOOKUP(tblRiskRegister32[[#This Row],[Asset Class]],tblInherentImpacts30[],2,FALSE) -> 3 | L60: =VLOOKUP(tblRiskRegister32[[#This Row],[Asset Class]],tblInherentImpacts30[],3,FALSE) -> 4 | M60: =VLOOKUP(tblRiskRegister32[[#This Row],[Asset Class]],tblInherentImpacts30[],4,FALSE) -> 1 | N60: =VLOOKUP(tblRiskRegister32[[#This Row],[Asset Class]],tblInherentImpacts30[],5,FALSE) -> 4 | O60: =IFERROR(MAX(tblRiskRegister32[[#This Row],[Impact to Mission]:[Impact to Obligations]])*tblRiskRegister32[[#This Row],[Expectancy Score]],"") -> 8 | P60: =tblRiskRegister32[[#This Row],[Risk Score]] -> 8 | Q60: Accept | R60: 7.4 | S60: Perform Automated Application Patch Management | T60: Perform application updates on enterprise assets through automated patch management on a monthly, or more frequent, basis. | W60: =IFERROR(VLOOKUP(10*tblRiskRegister32[[#This Row],[Risk Treatment Safeguard Maturity Score]]+tblRiskRegister32[[#This Row],[VCDB Index]],tblHITIndexWeightTable[],4,FALSE),"") | X60: =VLOOKUP(tblRiskRegister32[[#This Row],[Asset Class]],tblInherentImpacts30[],2,FALSE) -> 3 | Y60: =VLOOKUP(tblRiskRegister32[[#This Row],[Asset Class]],tblInherentImpacts30[],3,FALSE) -> 4 | Z60: =VLOOKUP(tblRiskRegister32[[#This Row],[Asset Class]],tblInherentImpacts30[],3,FALSE) -> 4 | AA60: =VLOOKUP(tblRiskRegister32[[#This Row],[Asset Class]],tblInherentImpacts30[],4,FALSE) -> 1 | AB60: =IFERROR(MAX(tblRiskRegister32[[#This Row],[Risk Treatment Safeguard Impact to Mission]:[Risk Treatment Safeguard Impact to Obligations]])*tblRiskRegister32[[#This Row],[Risk Treatment Safeguard Expectancy Score]],"") | AC60: =IF(tblRiskRegister32[[#This Row],[Risk Score]]>AcceptableRisk,IF(tblRiskRegister32[[#This Row],[Risk Treatment Safeguard Risk Score]]<AcceptableRisk, IF(tblRiskRegister32[[#This Row],[Risk Treatment Safeguard Risk Score]]<=tblRiskRegister32[[#This Row],[Risk Score]],"Yes","No"),"No"),"Yes") -> Yes
B61: Applications | C61: MIS 595 Focus | D61: 7.5 | E61: Perform Automated Vulnerability Scans of Internal Enterprise Assets | F61: Internal systems undergo automated vulnerability scans on a scheduled basis with results tracked and reviewed. | G61: Internal vulnerability scans are performed, but results are not consistently reviewed or remediated on schedule. | H61: 2 | I61: =IFERROR(VLOOKUP(tblRiskRegister32[[#This Row],[Asset Class]],tblVCDBIndex[],4,FALSE),"") -> 2 | J61: =IFERROR(VLOOKUP(10*tblRiskRegister32[[#This Row],[Safeguard Maturity Score]]+tblRiskRegister32[[#This Row],[VCDB Index]],tblHITIndexWeightTable[],4,FALSE),"") -> 3 | K61: =VLOOKUP(tblRiskRegister32[[#This Row],[Asset Class]],tblInherentImpacts30[],2,FALSE) -> 3 | L61: =VLOOKUP(tblRiskRegister32[[#This Row],[Asset Class]],tblInherentImpacts30[],3,FALSE) -> 4 | M61: =VLOOKUP(tblRiskRegister32[[#This Row],[Asset Class]],tblInherentImpacts30[],4,FALSE) -> 1 | N61: =VLOOKUP(tblRiskRegister32[[#This Row],[Asset Class]],tblInherentImpacts30[],5,FALSE) -> 4 | O61: =IFERROR(MAX(tblRiskRegister32[[#This Row],[Impact to Mission]:[Impact to Obligations]])*tblRiskRegister32[[#This Row],[Expectancy Score]],"") -> 12 | P61: =tblRiskRegister32[[#This Row],[Risk Score]] -> 12 | Q61: Reduce | R61: 7.5 | S61: Perform Automated Vulnerability Scans of Internal Enterprise Assets | T61: Perform automated vulnerability scans of internal enterprise assets on a quarterly, or more frequent, basis. Conduct both authenticated and unauthenticated scans, using a SCAP-compliant vulnerability scanning tool. | W61: =IFERROR(VLOOKUP(10*tblRiskRegister32[[#This Row],[Risk Treatment Safeguard Maturity Score]]+tblRiskRegister32[[#This Row],[VCDB Index]],tblHITIndexWeightTable[],4,FALSE),"") | X61: =VLOOKUP(tblRiskRegister32[[#This Row],[Asset Class]],tblInherentImpacts30[],2,FALSE) -> 3 | Y61: =VLOOKUP(tblRiskRegister32[[#This Row],[Asset Class]],tblInherentImpacts30[],3,FALSE) -> 4 | Z61: =VLOOKUP(tblRiskRegister32[[#This Row],[Asset Class]],tblInherentImpacts30[],3,FALSE) -> 4 | AA61: =VLOOKUP(tblRiskRegister32[[#This Row],[Asset Class]],tblInherentImpacts30[],4,FALSE) -> 1 | AB61: =IFERROR(MAX(tblRiskRegister32[[#This Row],[Risk Treatment Safeguard Impact to Mission]:[Risk Treatment Safeguard Impact to Obligations]])*tblRiskRegister32[[#This Row],[Risk Treatment Safeguard Expectancy Score]],"") | AC61: =IF(tblRiskRegister32[[#This Row],[Risk Score]]>AcceptableRisk,IF(tblRiskRegister32[[#This Row],[Risk Treatment Safeguard Risk Score]]<AcceptableRisk, IF(tblRiskRegister32[[#This Row],[Risk Treatment Safeguard Risk Score]]<=tblRiskRegister32[[#This Row],[Risk Score]],"Yes","No"),"No"),"Yes") -> No
B62: Applications | C62: MIS 595 Focus | D62: 7.6 | E62: Perform Automated Vulnerability Scans of Externally-Exposed Enterprise Assets | F62: No control in place | G62: Externally facing systems are not being scanned for vulnerabilities, resulting in unknown exposure to the internet. | H62: 1 | I62: =IFERROR(VLOOKUP(tblRiskRegister32[[#This Row],[Asset Class]],tblVCDBIndex[],4,FALSE),"") -> 2 | J62: =IFERROR(VLOOKUP(10*tblRiskRegister32[[#This Row],[Safeguard Maturity Score]]+tblRiskRegister32[[#This Row],[VCDB Index]],tblHITIndexWeightTable[],4,FALSE),"") -> 4 | K62: =VLOOKUP(tblRiskRegister32[[#This Row],[Asset Class]],tblInherentImpacts30[],2,FALSE) -> 3 | L62: =VLOOKUP(tblRiskRegister32[[#This Row],[Asset Class]],tblInherentImpacts30[],3,FALSE) -> 4 | M62: =VLOOKUP(tblRiskRegister32[[#This Row],[Asset Class]],tblInherentImpacts30[],4,FALSE) -> 1 | N62: =VLOOKUP(tblRiskRegister32[[#This Row],[Asset Class]],tblInherentImpacts30[],5,FALSE) -> 4 | O62: =IFERROR(MAX(tblRiskRegister32[[#This Row],[Impact to Mission]:[Impact to Obligations]])*tblRiskRegister32[[#This Row],[Expectancy Score]],"") -> 16 | P62: =tblRiskRegister32[[#This Row],[Risk Score]] -> 16 | Q62: Reduce | R62: 7.6 | S62: Perform Automated Vulnerability Scans of Externally-Exposed Enterprise Assets | T62: Perform automated vulnerability scans of externally-exposed enterprise assets using a SCAP-compliant vulnerability scanning tool. Perform scans on a monthly, or more frequent, basis. | W62: =IFERROR(VLOOKUP(10*tblRiskRegister32[[#This Row],[Risk Treatment Safeguard Maturity Score]]+tblRiskRegister32[[#This Row],[VCDB Index]],tblHITIndexWeightTable[],4,FALSE),"") | X62: =VLOOKUP(tblRiskRegister32[[#This Row],[Asset Class]],tblInherentImpacts30[],2,FALSE) -> 3 | Y62: =VLOOKUP(tblRiskRegister32[[#This Row],[Asset Class]],tblInherentImpacts30[],3,FALSE) -> 4 | Z62: =VLOOKUP(tblRiskRegister32[[#This Row],[Asset Class]],tblInherentImpacts30[],3,FALSE) -> 4 | AA62: =VLOOKUP(tblRiskRegister32[[#This Row],[Asset Class]],tblInherentImpacts30[],4,FALSE) -> 1 | AB62: =IFERROR(MAX(tblRiskRegister32[[#This Row],[Risk Treatment Safeguard Impact to Mission]:[Risk Treatment Safeguard Impact to Obligations]])*tblRiskRegister32[[#This Row],[Risk Treatment Safeguard Expectancy Score]],"") | AC62: =IF(tblRiskRegister32[[#This Row],[Risk Score]]>AcceptableRisk,IF(tblRiskRegister32[[#This Row],[Risk Treatment Safeguard Risk Score]]<AcceptableRisk, IF(tblRiskRegister32[[#This Row],[Risk Treatment Safeguard Risk Score]]<=tblRiskRegister32[[#This Row],[Risk Score]],"Yes","No"),"No"),"Yes") -> No
B63: Applications | C63: MIS 595 Focus | D63: 7.7 | E63: Remediate Detected Vulnerabilities | F63: High-risk vulnerabilities are prioritized and remediated in alignment with Fabella’s patching standards. | G63: No Vulnerability | H63: 4 | I63: =IFERROR(VLOOKUP(tblRiskRegister32[[#This Row],[Asset Class]],tblVCDBIndex[],4,FALSE),"") -> 2 | J63: =IFERROR(VLOOKUP(10*tblRiskRegister32[[#This Row],[Safeguard Maturity Score]]+tblRiskRegister32[[#This Row],[VCDB Index]],tblHITIndexWeightTable[],4,FALSE),"") -> 2 | K63: =VLOOKUP(tblRiskRegister32[[#This Row],[Asset Class]],tblInherentImpacts30[],2,FALSE) -> 3 | L63: =VLOOKUP(tblRiskRegister32[[#This Row],[Asset Class]],tblInherentImpacts30[],3,FALSE) -> 4 | M63: =VLOOKUP(tblRiskRegister32[[#This Row],[Asset Class]],tblInherentImpacts30[],4,FALSE) -> 1 | N63: =VLOOKUP(tblRiskRegister32[[#This Row],[Asset Class]],tblInherentImpacts30[],5,FALSE) -> 4 | O63: =IFERROR(MAX(tblRiskRegister32[[#This Row],[Impact to Mission]:[Impact to Obligations]])*tblRiskRegister32[[#This Row],[Expectancy Score]],"") -> 8 | P63: =tblRiskRegister32[[#This Row],[Risk Score]] -> 8 | Q63: Accept | R63: 7.7 | S63: Remediate Detected Vulnerabilities | T63: Remediate detected vulnerabilities in software through processes and tooling on a monthly, or more frequent, basis, based on the remediation process. | W63: =IFERROR(VLOOKUP(10*tblRiskRegister32[[#This Row],[Risk Treatment Safeguard Maturity Score]]+tblRiskRegister32[[#This Row],[VCDB Index]],tblHITIndexWeightTable[],4,FALSE),"") | X63: =VLOOKUP(tblRiskRegister32[[#This Row],[Asset Class]],tblInherentImpacts30[],2,FALSE) -> 3 | Y63: =VLOOKUP(tblRiskRegister32[[#This Row],[Asset Class]],tblInherentImpacts30[],3,FALSE) -> 4 | Z63: =VLOOKUP(tblRiskRegister32[[#This Row],[Asset Class]],tblInherentImpacts30[],3,FALSE) -> 4 | AA63: =VLOOKUP(tblRiskRegister32[[#This Row],[Asset Class]],tblInherentImpacts30[],4,FALSE) -> 1 | AB63: =IFERROR(MAX(tblRiskRegister32[[#This Row],[Risk Treatment Safeguard Impact to Mission]:[Risk Treatment Safeguard Impact to Obligations]])*tblRiskRegister32[[#This Row],[Risk Treatment Safeguard Expectancy Score]],"") | AC63: =IF(tblRiskRegister32[[#This Row],[Risk Score]]>AcceptableRisk,IF(tblRiskRegister32[[#This Row],[Risk Treatment Safeguard Risk Score]]<AcceptableRisk, IF(tblRiskRegister32[[#This Row],[Risk Treatment Safeguard Risk Score]]<=tblRiskRegister32[[#This Row],[Risk Score]],"Yes","No"),"No"),"Yes") -> Yes
B64: Network | D64: 8.1 | E64: Establish and Maintain an Audit Log Management Process | I64: =IFERROR(VLOOKUP(tblRiskRegister32[[#This Row],[Asset Class]],tblVCDBIndex[],4,FALSE),"") -> 1 | J64: =IFERROR(VLOOKUP(10*tblRiskRegister32[[#This Row],[Safeguard Maturity Score]]+tblRiskRegister32[[#This Row],[VCDB Index]],tblHITIndexWeightTable[],4,FALSE),"") | K64: =VLOOKUP(tblRiskRegister32[[#This Row],[Asset Class]],tblInherentImpacts30[],2,FALSE) -> 4 | L64: =VLOOKUP(tblRiskRegister32[[#This Row],[Asset Class]],tblInherentImpacts30[],3,FALSE) -> 5 | M64: =VLOOKUP(tblRiskRegister32[[#This Row],[Asset Class]],tblInherentImpacts30[],4,FALSE) -> 1 | N64: =VLOOKUP(tblRiskRegister32[[#This Row],[Asset Class]],tblInherentImpacts30[],5,FALSE) -> 5 | O64: =IFERROR(MAX(tblRiskRegister32[[#This Row],[Impact to Mission]:[Impact to Obligations]])*tblRiskRegister32[[#This Row],[Expectancy Score]],"") | P64: =tblRiskRegister32[[#This Row],[Risk Score]] | R64: 8.1 | S64: Establish and Maintain an Audit Log Management Process | T64: Establish and maintain an audit log management process that defines the enterprise’s logging requirements. At a minimum, address the collection, review, and retention of audit logs for enterprise assets. Review and update documentation annually, or when significant enterprise changes occur that could impact this Safeguard. | W64: =IFERROR(VLOOKUP(10*tblRiskRegister32[[#This Row],[Risk Treatment Safeguard Maturity Score]]+tblRiskRegister32[[#This Row],[VCDB Index]],tblHITIndexWeightTable[],4,FALSE),"") | X64: =VLOOKUP(tblRiskRegister32[[#This Row],[Asset Class]],tblInherentImpacts30[],2,FALSE) -> 4 | Y64: =VLOOKUP(tblRiskRegister32[[#This Row],[Asset Class]],tblInherentImpacts30[],3,FALSE) -> 5 | Z64: =VLOOKUP(tblRiskRegister32[[#This Row],[Asset Class]],tblInherentImpacts30[],3,FALSE) -> 5 | AA64: =VLOOKUP(tblRiskRegister32[[#This Row],[Asset Class]],tblInherentImpacts30[],4,FALSE) -> 1 | AB64: =IFERROR(MAX(tblRiskRegister32[[#This Row],[Risk Treatment Safeguard Impact to Mission]:[Risk Treatment Safeguard Impact to Obligations]])*tblRiskRegister32[[#This Row],[Risk Treatment Safeguard Expectancy Score]],"") | AC64: =IF(tblRiskRegister32[[#This Row],[Risk Score]]>AcceptableRisk,IF(tblRiskRegister32[[#This Row],[Risk Treatment Safeguard Risk Score]]<AcceptableRisk, IF(tblRiskRegister32[[#This Row],[Risk Treatment Safeguard Risk Score]]<=tblRiskRegister32[[#This Row],[Risk Score]],"Yes","No"),"No"),"Yes") -> No
B65: Network | D65: 8.1 | E65: Retain Audit Logs | I65: =IFERROR(VLOOKUP(tblRiskRegister32[[#This Row],[Asset Class]],tblVCDBIndex[],4,FALSE),"") -> 1 | J65: =IFERROR(VLOOKUP(10*tblRiskRegister32[[#This Row],[Safeguard Maturity Score]]+tblRiskRegister32[[#This Row],[VCDB Index]],tblHITIndexWeightTable[],4,FALSE),"") | K65: =VLOOKUP(tblRiskRegister32[[#This Row],[Asset Class]],tblInherentImpacts30[],2,FALSE) -> 4 | L65: =VLOOKUP(tblRiskRegister32[[#This Row],[Asset Class]],tblInherentImpacts30[],3,FALSE) -> 5 | M65: =VLOOKUP(tblRiskRegister32[[#This Row],[Asset Class]],tblInherentImpacts30[],4,FALSE) -> 1 | N65: =VLOOKUP(tblRiskRegister32[[#This Row],[Asset Class]],tblInherentImpacts30[],5,FALSE) -> 5 | O65: =IFERROR(MAX(tblRiskRegister32[[#This Row],[Impact to Mission]:[Impact to Obligations]])*tblRiskRegister32[[#This Row],[Expectancy Score]],"") | P65: =tblRiskRegister32[[#This Row],[Risk Score]] | R65: 8.1 | S65: Retain Audit Logs | T65: Retain audit logs across enterprise assets for a minimum of 90 days. | W65: =IFERROR(VLOOKUP(10*tblRiskRegister32[[#This Row],[Risk Treatment Safeguard Maturity Score]]+tblRiskRegister32[[#This Row],[VCDB Index]],tblHITIndexWeightTable[],4,FALSE),"") | X65: =VLOOKUP(tblRiskRegister32[[#This Row],[Asset Class]],tblInherentImpacts30[],2,FALSE) -> 4 | Y65: =VLOOKUP(tblRiskRegister32[[#This Row],[Asset Class]],tblInherentImpacts30[],3,FALSE) -> 5 | Z65: =VLOOKUP(tblRiskRegister32[[#This Row],[Asset Class]],tblInherentImpacts30[],3,FALSE) -> 5 | AA65: =VLOOKUP(tblRiskRegister32[[#This Row],[Asset Class]],tblInherentImpacts30[],4,FALSE) -> 1 | AB65: =IFERROR(MAX(tblRiskRegister32[[#This Row],[Risk Treatment Safeguard Impact to Mission]:[Risk Treatment Safeguard Impact to Obligations]])*tblRiskRegister32[[#This Row],[Risk Treatment Safeguard Expectancy Score]],"") | AC65: =IF(tblRiskRegister32[[#This Row],[Risk Score]]>AcceptableRisk,IF(tblRiskRegister32[[#This Row],[Risk Treatment Safeguard Risk Score]]<AcceptableRisk, IF(tblRiskRegister32[[#This Row],[Risk Treatment Safeguard Risk Score]]<=tblRiskRegister32[[#This Row],[Risk Score]],"Yes","No"),"No"),"Yes") -> No
B66: Network | D66: 8.11 | E66: Conduct Audit Log Reviews | I66: =IFERROR(VLOOKUP(tblRiskRegister32[[#This Row],[Asset Class]],tblVCDBIndex[],4,FALSE),"") -> 1 | J66: =IFERROR(VLOOKUP(10*tblRiskRegister32[[#This Row],[Safeguard Maturity Score]]+tblRiskRegister32[[#This Row],[VCDB Index]],tblHITIndexWeightTable[],4,FALSE),"") | K66: =VLOOKUP(tblRiskRegister32[[#This Row],[Asset Class]],tblInherentImpacts30[],2,FALSE) -> 4 | L66: =VLOOKUP(tblRiskRegister32[[#This Row],[Asset Class]],tblInherentImpacts30[],3,FALSE) -> 5 | M66: =VLOOKUP(tblRiskRegister32[[#This Row],[Asset Class]],tblInherentImpacts30[],4,FALSE) -> 1 | N66: =VLOOKUP(tblRiskRegister32[[#This Row],[Asset Class]],tblInherentImpacts30[],5,FALSE) -> 5 | O66: =IFERROR(MAX(tblRiskRegister32[[#This Row],[Impact to Mission]:[Impact to Obligations]])*tblRiskRegister32[[#This Row],[Expectancy Score]],"") | P66: =tblRiskRegister32[[#This Row],[Risk Score]] | R66: 8.11 | S66: Conduct Audit Log Reviews | T66: Conduct reviews of audit logs to detect anomalies or abnormal events that could indicate a potential threat. Conduct reviews on a weekly, or more frequent, basis. | W66: =IFERROR(VLOOKUP(10*tblRiskRegister32[[#This Row],[Risk Treatment Safeguard Maturity Score]]+tblRiskRegister32[[#This Row],[VCDB Index]],tblHITIndexWeightTable[],4,FALSE),"") | X66: =VLOOKUP(tblRiskRegister32[[#This Row],[Asset Class]],tblInherentImpacts30[],2,FALSE) -> 4 | Y66: =VLOOKUP(tblRiskRegister32[[#This Row],[Asset Class]],tblInherentImpacts30[],3,FALSE) -> 5 | Z66: =VLOOKUP(tblRiskRegister32[[#This Row],[Asset Class]],tblInherentImpacts30[],3,FALSE) -> 5 | AA66: =VLOOKUP(tblRiskRegister32[[#This Row],[Asset Class]],tblInherentImpacts30[],4,FALSE) -> 1 | AB66: =IFERROR(MAX(tblRiskRegister32[[#This Row],[Risk Treatment Safeguard Impact to Mission]:[Risk Treatment Safeguard Impact to Obligations]])*tblRiskRegister32[[#This Row],[Risk Treatment Safeguard Expectancy Score]],"") | AC66: =IF(tblRiskRegister32[[#This Row],[Risk Score]]>AcceptableRisk,IF(tblRiskRegister32[[#This Row],[Risk Treatment Safeguard Risk Score]]<AcceptableRisk, IF(tblRiskRegister32[[#This Row],[Risk Treatment Safeguard Risk Score]]<=tblRiskRegister32[[#This Row],[Risk Score]],"Yes","No"),"No"),"Yes") -> No
B67: Network | D67: 8.2 | E67: Collect Audit Logs | I67: =IFERROR(VLOOKUP(tblRiskRegister32[[#This Row],[Asset Class]],tblVCDBIndex[],4,FALSE),"") -> 1 | J67: =IFERROR(VLOOKUP(10*tblRiskRegister32[[#This Row],[Safeguard Maturity Score]]+tblRiskRegister32[[#This Row],[VCDB Index]],tblHITIndexWeightTable[],4,FALSE),"") | K67: =VLOOKUP(tblRiskRegister32[[#This Row],[Asset Class]],tblInherentImpacts30[],2,FALSE) -> 4 | L67: =VLOOKUP(tblRiskRegister32[[#This Row],[Asset Class]],tblInherentImpacts30[],3,FALSE) -> 5 | M67: =VLOOKUP(tblRiskRegister32[[#This Row],[Asset Class]],tblInherentImpacts30[],4,FALSE) -> 1 | N67: =VLOOKUP(tblRiskRegister32[[#This Row],[Asset Class]],tblInherentImpacts30[],5,FALSE) -> 5 | O67: =IFERROR(MAX(tblRiskRegister32[[#This Row],[Impact to Mission]:[Impact to Obligations]])*tblRiskRegister32[[#This Row],[Expectancy Score]],"") | P67: =tblRiskRegister32[[#This Row],[Risk Score]] | R67: 8.2 | S67: Collect Audit Logs | T67: Collect audit logs. Ensure that logging, per the enterprise’s audit log management process, has been enabled across enterprise assets. | W67: =IFERROR(VLOOKUP(10*tblRiskRegister32[[#This Row],[Risk Treatment Safeguard Maturity Score]]+tblRiskRegister32[[#This Row],[VCDB Index]],tblHITIndexWeightTable[],4,FALSE),"") | X67: =VLOOKUP(tblRiskRegister32[[#This Row],[Asset Class]],tblInherentImpacts30[],2,FALSE) -> 4 | Y67: =VLOOKUP(tblRiskRegister32[[#This Row],[Asset Class]],tblInherentImpacts30[],3,FALSE) -> 5 | Z67: =VLOOKUP(tblRiskRegister32[[#This Row],[Asset Class]],tblInherentImpacts30[],3,FALSE) -> 5 | AA67: =VLOOKUP(tblRiskRegister32[[#This Row],[Asset Class]],tblInherentImpacts30[],4,FALSE) -> 1 | AB67: =IFERROR(MAX(tblRiskRegister32[[#This Row],[Risk Treatment Safeguard Impact to Mission]:[Risk Treatment Safeguard Impact to Obligations]])*tblRiskRegister32[[#This Row],[Risk Treatment Safeguard Expectancy Score]],"") | AC67: =IF(tblRiskRegister32[[#This Row],[Risk Score]]>AcceptableRisk,IF(tblRiskRegister32[[#This Row],[Risk Treatment Safeguard Risk Score]]<AcceptableRisk, IF(tblRiskRegister32[[#This Row],[Risk Treatment Safeguard Risk Score]]<=tblRiskRegister32[[#This Row],[Risk Score]],"Yes","No"),"No"),"Yes") -> No
B68: Network | D68: 8.3 | E68: Ensure Adequate Audit Log Storage | I68: =IFERROR(VLOOKUP(tblRiskRegister32[[#This Row],[Asset Class]],tblVCDBIndex[],4,FALSE),"") -> 1 | J68: =IFERROR(VLOOKUP(10*tblRiskRegister32[[#This Row],[Safeguard Maturity Score]]+tblRiskRegister32[[#This Row],[VCDB Index]],tblHITIndexWeightTable[],4,FALSE),"") | K68: =VLOOKUP(tblRiskRegister32[[#This Row],[Asset Class]],tblInherentImpacts30[],2,FALSE) -> 4 | L68: =VLOOKUP(tblRiskRegister32[[#This Row],[Asset Class]],tblInherentImpacts30[],3,FALSE) -> 5 | M68: =VLOOKUP(tblRiskRegister32[[#This Row],[Asset Class]],tblInherentImpacts30[],4,FALSE) -> 1 | N68: =VLOOKUP(tblRiskRegister32[[#This Row],[Asset Class]],tblInherentImpacts30[],5,FALSE) -> 5 | O68: =IFERROR(MAX(tblRiskRegister32[[#This Row],[Impact to Mission]:[Impact to Obligations]])*tblRiskRegister32[[#This Row],[Expectancy Score]],"") | P68: =tblRiskRegister32[[#This Row],[Risk Score]] | R68: 8.3 | S68: Ensure Adequate Audit Log Storage | T68: Ensure that logging destinations maintain adequate storage to comply with the enterprise’s audit log management process. | W68: =IFERROR(VLOOKUP(10*tblRiskRegister32[[#This Row],[Risk Treatment Safeguard Maturity Score]]+tblRiskRegister32[[#This Row],[VCDB Index]],tblHITIndexWeightTable[],4,FALSE),"") | X68: =VLOOKUP(tblRiskRegister32[[#This Row],[Asset Class]],tblInherentImpacts30[],2,FALSE) -> 4 | Y68: =VLOOKUP(tblRiskRegister32[[#This Row],[Asset Class]],tblInherentImpacts30[],3,FALSE) -> 5 | Z68: =VLOOKUP(tblRiskRegister32[[#This Row],[Asset Class]],tblInherentImpacts30[],3,FALSE) -> 5 | AA68: =VLOOKUP(tblRiskRegister32[[#This Row],[Asset Class]],tblInherentImpacts30[],4,FALSE) -> 1 | AB68: =IFERROR(MAX(tblRiskRegister32[[#This Row],[Risk Treatment Safeguard Impact to Mission]:[Risk Treatment Safeguard Impact to Obligations]])*tblRiskRegister32[[#This Row],[Risk Treatment Safeguard Expectancy Score]],"") | AC68: =IF(tblRiskRegister32[[#This Row],[Risk Score]]>AcceptableRisk,IF(tblRiskRegister32[[#This Row],[Risk Treatment Safeguard Risk Score]]<AcceptableRisk, IF(tblRiskRegister32[[#This Row],[Risk Treatment Safeguard Risk Score]]<=tblRiskRegister32[[#This Row],[Risk Score]],"Yes","No"),"No"),"Yes") -> No
B69: Network | D69: 8.4 | E69: Standardize Time Synchronization | I69: =IFERROR(VLOOKUP(tblRiskRegister32[[#This Row],[Asset Class]],tblVCDBIndex[],4,FALSE),"") -> 1 | J69: =IFERROR(VLOOKUP(10*tblRiskRegister32[[#This Row],[Safeguard Maturity Score]]+tblRiskRegister32[[#This Row],[VCDB Index]],tblHITIndexWeightTable[],4,FALSE),"") | K69: =VLOOKUP(tblRiskRegister32[[#This Row],[Asset Class]],tblInherentImpacts30[],2,FALSE) -> 4 | L69: =VLOOKUP(tblRiskRegister32[[#This Row],[Asset Class]],tblInherentImpacts30[],3,FALSE) -> 5 | M69: =VLOOKUP(tblRiskRegister32[[#This Row],[Asset Class]],tblInherentImpacts30[],4,FALSE) -> 1 | N69: =VLOOKUP(tblRiskRegister32[[#This Row],[Asset Class]],tblInherentImpacts30[],5,FALSE) -> 5 | O69: =IFERROR(MAX(tblRiskRegister32[[#This Row],[Impact to Mission]:[Impact to Obligations]])*tblRiskRegister32[[#This Row],[Expectancy Score]],"") | P69: =tblRiskRegister32[[#This Row],[Risk Score]] | R69: 8.4 | S69: Standardize Time Synchronization | T69: Standardize time synchronization. Configure at least two synchronized time sources across enterprise assets, where supported. | W69: =IFERROR(VLOOKUP(10*tblRiskRegister32[[#This Row],[Risk Treatment Safeguard Maturity Score]]+tblRiskRegister32[[#This Row],[VCDB Index]],tblHITIndexWeightTable[],4,FALSE),"") | X69: =VLOOKUP(tblRiskRegister32[[#This Row],[Asset Class]],tblInherentImpacts30[],2,FALSE) -> 4 | Y69: =VLOOKUP(tblRiskRegister32[[#This Row],[Asset Class]],tblInherentImpacts30[],3,FALSE) -> 5 | Z69: =VLOOKUP(tblRiskRegister32[[#This Row],[Asset Class]],tblInherentImpacts30[],3,FALSE) -> 5 | AA69: =VLOOKUP(tblRiskRegister32[[#This Row],[Asset Class]],tblInherentImpacts30[],4,FALSE) -> 1 | AB69: =IFERROR(MAX(tblRiskRegister32[[#This Row],[Risk Treatment Safeguard Impact to Mission]:[Risk Treatment Safeguard Impact to Obligations]])*tblRiskRegister32[[#This Row],[Risk Treatment Safeguard Expectancy Score]],"") | AC69: =IF(tblRiskRegister32[[#This Row],[Risk Score]]>AcceptableRisk,IF(tblRiskRegister32[[#This Row],[Risk Treatment Safeguard Risk Score]]<AcceptableRisk, IF(tblRiskRegister32[[#This Row],[Risk Treatment Safeguard Risk Score]]<=tblRiskRegister32[[#This Row],[Risk Score]],"Yes","No"),"No"),"Yes") -> No
B70: Network | D70: 8.5 | E70: Collect Detailed Audit Logs | I70: =IFERROR(VLOOKUP(tblRiskRegister32[[#This Row],[Asset Class]],tblVCDBIndex[],4,FALSE),"") -> 1 | J70: =IFERROR(VLOOKUP(10*tblRiskRegister32[[#This Row],[Safeguard Maturity Score]]+tblRiskRegister32[[#This Row],[VCDB Index]],tblHITIndexWeightTable[],4,FALSE),"") | K70: =VLOOKUP(tblRiskRegister32[[#This Row],[Asset Class]],tblInherentImpacts30[],2,FALSE) -> 4 | L70: =VLOOKUP(tblRiskRegister32[[#This Row],[Asset Class]],tblInherentImpacts30[],3,FALSE) -> 5 | M70: =VLOOKUP(tblRiskRegister32[[#This Row],[Asset Class]],tblInherentImpacts30[],4,FALSE) -> 1 | N70: =VLOOKUP(tblRiskRegister32[[#This Row],[Asset Class]],tblInherentImpacts30[],5,FALSE) -> 5 | O70: =IFERROR(MAX(tblRiskRegister32[[#This Row],[Impact to Mission]:[Impact to Obligations]])*tblRiskRegister32[[#This Row],[Expectancy Score]],"") | P70: =tblRiskRegister32[[#This Row],[Risk Score]] | R70: 8.5 | S70: Collect Detailed Audit Logs | T70: Configure detailed audit logging for enterprise assets containing sensitive data. Include event source, date, username, timestamp, source addresses, destination addresses, and other useful elements that could assist in a forensic investigation. | W70: =IFERROR(VLOOKUP(10*tblRiskRegister32[[#This Row],[Risk Treatment Safeguard Maturity Score]]+tblRiskRegister32[[#This Row],[VCDB Index]],tblHITIndexWeightTable[],4,FALSE),"") | X70: =VLOOKUP(tblRiskRegister32[[#This Row],[Asset Class]],tblInherentImpacts30[],2,FALSE) -> 4 | Y70: =VLOOKUP(tblRiskRegister32[[#This Row],[Asset Class]],tblInherentImpacts30[],3,FALSE) -> 5 | Z70: =VLOOKUP(tblRiskRegister32[[#This Row],[Asset Class]],tblInherentImpacts30[],3,FALSE) -> 5 | AA70: =VLOOKUP(tblRiskRegister32[[#This Row],[Asset Class]],tblInherentImpacts30[],4,FALSE) -> 1 | AB70: =IFERROR(MAX(tblRiskRegister32[[#This Row],[Risk Treatment Safeguard Impact to Mission]:[Risk Treatment Safeguard Impact to Obligations]])*tblRiskRegister32[[#This Row],[Risk Treatment Safeguard Expectancy Score]],"") | AC70: =IF(tblRiskRegister32[[#This Row],[Risk Score]]>AcceptableRisk,IF(tblRiskRegister32[[#This Row],[Risk Treatment Safeguard Risk Score]]<AcceptableRisk, IF(tblRiskRegister32[[#This Row],[Risk Treatment Safeguard Risk Score]]<=tblRiskRegister32[[#This Row],[Risk Score]],"Yes","No"),"No"),"Yes") -> No
B71: Network | D71: 8.6 | E71: Collect DNS Query Audit Logs | I71: =IFERROR(VLOOKUP(tblRiskRegister32[[#This Row],[Asset Class]],tblVCDBIndex[],4,FALSE),"") -> 1 | J71: =IFERROR(VLOOKUP(10*tblRiskRegister32[[#This Row],[Safeguard Maturity Score]]+tblRiskRegister32[[#This Row],[VCDB Index]],tblHITIndexWeightTable[],4,FALSE),"") | K71: =VLOOKUP(tblRiskRegister32[[#This Row],[Asset Class]],tblInherentImpacts30[],2,FALSE) -> 4 | L71: =VLOOKUP(tblRiskRegister32[[#This Row],[Asset Class]],tblInherentImpacts30[],3,FALSE) -> 5 | M71: =VLOOKUP(tblRiskRegister32[[#This Row],[Asset Class]],tblInherentImpacts30[],4,FALSE) -> 1 | N71: =VLOOKUP(tblRiskRegister32[[#This Row],[Asset Class]],tblInherentImpacts30[],5,FALSE) -> 5 | O71: =IFERROR(MAX(tblRiskRegister32[[#This Row],[Impact to Mission]:[Impact to Obligations]])*tblRiskRegister32[[#This Row],[Expectancy Score]],"") | P71: =tblRiskRegister32[[#This Row],[Risk Score]] | R71: 8.6 | S71: Collect DNS Query Audit Logs | T71: Collect DNS query audit logs on enterprise assets, where appropriate and supported. | W71: =IFERROR(VLOOKUP(10*tblRiskRegister32[[#This Row],[Risk Treatment Safeguard Maturity Score]]+tblRiskRegister32[[#This Row],[VCDB Index]],tblHITIndexWeightTable[],4,FALSE),"") | X71: =VLOOKUP(tblRiskRegister32[[#This Row],[Asset Class]],tblInherentImpacts30[],2,FALSE) -> 4 | Y71: =VLOOKUP(tblRiskRegister32[[#This Row],[Asset Class]],tblInherentImpacts30[],3,FALSE) -> 5 | Z71: =VLOOKUP(tblRiskRegister32[[#This Row],[Asset Class]],tblInherentImpacts30[],3,FALSE) -> 5 | AA71: =VLOOKUP(tblRiskRegister32[[#This Row],[Asset Class]],tblInherentImpacts30[],4,FALSE) -> 1 | AB71: =IFERROR(MAX(tblRiskRegister32[[#This Row],[Risk Treatment Safeguard Impact to Mission]:[Risk Treatment Safeguard Impact to Obligations]])*tblRiskRegister32[[#This Row],[Risk Treatment Safeguard Expectancy Score]],"") | AC71: =IF(tblRiskRegister32[[#This Row],[Risk Score]]>AcceptableRisk,IF(tblRiskRegister32[[#This Row],[Risk Treatment Safeguard Risk Score]]<AcceptableRisk, IF(tblRiskRegister32[[#This Row],[Risk Treatment Safeguard Risk Score]]<=tblRiskRegister32[[#This Row],[Risk Score]],"Yes","No"),"No"),"Yes") -> No
B72: Network | D72: 8.7 | E72: Collect URL Request Audit Logs | I72: =IFERROR(VLOOKUP(tblRiskRegister32[[#This Row],[Asset Class]],tblVCDBIndex[],4,FALSE),"") -> 1 | J72: =IFERROR(VLOOKUP(10*tblRiskRegister32[[#This Row],[Safeguard Maturity Score]]+tblRiskRegister32[[#This Row],[VCDB Index]],tblHITIndexWeightTable[],4,FALSE),"") | K72: =VLOOKUP(tblRiskRegister32[[#This Row],[Asset Class]],tblInherentImpacts30[],2,FALSE) -> 4 | L72: =VLOOKUP(tblRiskRegister32[[#This Row],[Asset Class]],tblInherentImpacts30[],3,FALSE) -> 5 | M72: =VLOOKUP(tblRiskRegister32[[#This Row],[Asset Class]],tblInherentImpacts30[],4,FALSE) -> 1 | N72: =VLOOKUP(tblRiskRegister32[[#This Row],[Asset Class]],tblInherentImpacts30[],5,FALSE) -> 5 | O72: =IFERROR(MAX(tblRiskRegister32[[#This Row],[Impact to Mission]:[Impact to Obligations]])*tblRiskRegister32[[#This Row],[Expectancy Score]],"") | P72: =tblRiskRegister32[[#This Row],[Risk Score]] | R72: 8.7 | S72: Collect URL Request Audit Logs | T72: Collect URL request audit logs on enterprise assets, where appropriate and supported. | W72: =IFERROR(VLOOKUP(10*tblRiskRegister32[[#This Row],[Risk Treatment Safeguard Maturity Score]]+tblRiskRegister32[[#This Row],[VCDB Index]],tblHITIndexWeightTable[],4,FALSE),"") | X72: =VLOOKUP(tblRiskRegister32[[#This Row],[Asset Class]],tblInherentImpacts30[],2,FALSE) -> 4 | Y72: =VLOOKUP(tblRiskRegister32[[#This Row],[Asset Class]],tblInherentImpacts30[],3,FALSE) -> 5 | Z72: =VLOOKUP(tblRiskRegister32[[#This Row],[Asset Class]],tblInherentImpacts30[],3,FALSE) -> 5 | AA72: =VLOOKUP(tblRiskRegister32[[#This Row],[Asset Class]],tblInherentImpacts30[],4,FALSE) -> 1 | AB72: =IFERROR(MAX(tblRiskRegister32[[#This Row],[Risk Treatment Safeguard Impact to Mission]:[Risk Treatment Safeguard Impact to Obligations]])*tblRiskRegister32[[#This Row],[Risk Treatment Safeguard Expectancy Score]],"") | AC72: =IF(tblRiskRegister32[[#This Row],[Risk Score]]>AcceptableRisk,IF(tblRiskRegister32[[#This Row],[Risk Treatment Safeguard Risk Score]]<AcceptableRisk, IF(tblRiskRegister32[[#This Row],[Risk Treatment Safeguard Risk Score]]<=tblRiskRegister32[[#This Row],[Risk Score]],"Yes","No"),"No"),"Yes") -> No
B73: Devices | D73: 8.8 | E73: Collect Command-Line Audit Logs | I73: =IFERROR(VLOOKUP(tblRiskRegister32[[#This Row],[Asset Class]],tblVCDBIndex[],4,FALSE),"") -> 1 | J73: =IFERROR(VLOOKUP(10*tblRiskRegister32[[#This Row],[Safeguard Maturity Score]]+tblRiskRegister32[[#This Row],[VCDB Index]],tblHITIndexWeightTable[],4,FALSE),"") | K73: =VLOOKUP(tblRiskRegister32[[#This Row],[Asset Class]],tblInherentImpacts30[],2,FALSE) -> 3 | L73: =VLOOKUP(tblRiskRegister32[[#This Row],[Asset Class]],tblInherentImpacts30[],3,FALSE) -> 3 | M73: =VLOOKUP(tblRiskRegister32[[#This Row],[Asset Class]],tblInherentImpacts30[],4,FALSE) -> 1 | N73: =VLOOKUP(tblRiskRegister32[[#This Row],[Asset Class]],tblInherentImpacts30[],5,FALSE) -> 3 | O73: =IFERROR(MAX(tblRiskRegister32[[#This Row],[Impact to Mission]:[Impact to Obligations]])*tblRiskRegister32[[#This Row],[Expectancy Score]],"") | P73: =tblRiskRegister32[[#This Row],[Risk Score]] | R73: 8.8 | S73: Collect Command-Line Audit Logs | T73: Collect command-line audit logs. Example implementations include collecting audit logs from PowerShell®, BASH™, and remote administrative terminals. | W73: =IFERROR(VLOOKUP(10*tblRiskRegister32[[#This Row],[Risk Treatment Safeguard Maturity Score]]+tblRiskRegister32[[#This Row],[VCDB Index]],tblHITIndexWeightTable[],4,FALSE),"") | X73: =VLOOKUP(tblRiskRegister32[[#This Row],[Asset Class]],tblInherentImpacts30[],2,FALSE) -> 3 | Y73: =VLOOKUP(tblRiskRegister32[[#This Row],[Asset Class]],tblInherentImpacts30[],3,FALSE) -> 3 | Z73: =VLOOKUP(tblRiskRegister32[[#This Row],[Asset Class]],tblInherentImpacts30[],3,FALSE) -> 3 | AA73: =VLOOKUP(tblRiskRegister32[[#This Row],[Asset Class]],tblInherentImpacts30[],4,FALSE) -> 1 | AB73: =IFERROR(MAX(tblRiskRegister32[[#This Row],[Risk Treatment Safeguard Impact to Mission]:[Risk Treatment Safeguard Impact to Obligations]])*tblRiskRegister32[[#This Row],[Risk Treatment Safeguard Expectancy Score]],"") | AC73: =IF(tblRiskRegister32[[#This Row],[Risk Score]]>AcceptableRisk,IF(tblRiskRegister32[[#This Row],[Risk Treatment Safeguard Risk Score]]<AcceptableRisk, IF(tblRiskRegister32[[#This Row],[Risk Treatment Safeguard Risk Score]]<=tblRiskRegister32[[#This Row],[Risk Score]],"Yes","No"),"No"),"Yes") -> No
B74: Network | D74: 8.9 | E74: Centralize Audit Logs | I74: =IFERROR(VLOOKUP(tblRiskRegister32[[#This Row],[Asset Class]],tblVCDBIndex[],4,FALSE),"") -> 1 | J74: =IFERROR(VLOOKUP(10*tblRiskRegister32[[#This Row],[Safeguard Maturity Score]]+tblRiskRegister32[[#This Row],[VCDB Index]],tblHITIndexWeightTable[],4,FALSE),"") | K74: =VLOOKUP(tblRiskRegister32[[#This Row],[Asset Class]],tblInherentImpacts30[],2,FALSE) -> 4 | L74: =VLOOKUP(tblRiskRegister32[[#This Row],[Asset Class]],tblInherentImpacts30[],3,FALSE) -> 5 | M74: =VLOOKUP(tblRiskRegister32[[#This Row],[Asset Class]],tblInherentImpacts30[],4,FALSE) -> 1 | N74: =VLOOKUP(tblRiskRegister32[[#This Row],[Asset Class]],tblInherentImpacts30[],5,FALSE) -> 5 | O74: =IFERROR(MAX(tblRiskRegister32[[#This Row],[Impact to Mission]:[Impact to Obligations]])*tblRiskRegister32[[#This Row],[Expectancy Score]],"") | P74: =tblRiskRegister32[[#This Row],[Risk Score]] | R74: 8.9 | S74: Centralize Audit Logs | T74: Centralize, to the extent possible, audit log collection and retention across enterprise assets. | W74: =IFERROR(VLOOKUP(10*tblRiskRegister32[[#This Row],[Risk Treatment Safeguard Maturity Score]]+tblRiskRegister32[[#This Row],[VCDB Index]],tblHITIndexWeightTable[],4,FALSE),"") | X74: =VLOOKUP(tblRiskRegister32[[#This Row],[Asset Class]],tblInherentImpacts30[],2,FALSE) -> 4 | Y74: =VLOOKUP(tblRiskRegister32[[#This Row],[Asset Class]],tblInherentImpacts30[],3,FALSE) -> 5 | Z74: =VLOOKUP(tblRiskRegister32[[#This Row],[Asset Class]],tblInherentImpacts30[],3,FALSE) -> 5 | AA74: =VLOOKUP(tblRiskRegister32[[#This Row],[Asset Class]],tblInherentImpacts30[],4,FALSE) -> 1 | AB74: =IFERROR(MAX(tblRiskRegister32[[#This Row],[Risk Treatment Safeguard Impact to Mission]:[Risk Treatment Safeguard Impact to Obligations]])*tblRiskRegister32[[#This Row],[Risk Treatment Safeguard Expectancy Score]],"") | AC74: =IF(tblRiskRegister32[[#This Row],[Risk Score]]>AcceptableRisk,IF(tblRiskRegister32[[#This Row],[Risk Treatment Safeguard Risk Score]]<AcceptableRisk, IF(tblRiskRegister32[[#This Row],[Risk Treatment Safeguard Risk Score]]<=tblRiskRegister32[[#This Row],[Risk Score]],"Yes","No"),"No"),"Yes") -> No
B75: Applications | D75: 9.1 | E75: Ensure Use of Only Fully Supported Browsers and Email Clients | I75: =IFERROR(VLOOKUP(tblRiskRegister32[[#This Row],[Asset Class]],tblVCDBIndex[],4,FALSE),"") -> 2 | J75: =IFERROR(VLOOKUP(10*tblRiskRegister32[[#This Row],[Safeguard Maturity Score]]+tblRiskRegister32[[#This Row],[VCDB Index]],tblHITIndexWeightTable[],4,FALSE),"") | K75: =VLOOKUP(tblRiskRegister32[[#This Row],[Asset Class]],tblInherentImpacts30[],2,FALSE) -> 3 | L75: =VLOOKUP(tblRiskRegister32[[#This Row],[Asset Class]],tblInherentImpacts30[],3,FALSE) -> 4 | M75: =VLOOKUP(tblRiskRegister32[[#This Row],[Asset Class]],tblInherentImpacts30[],4,FALSE) -> 1 | N75: =VLOOKUP(tblRiskRegister32[[#This Row],[Asset Class]],tblInherentImpacts30[],5,FALSE) -> 4 | O75: =IFERROR(MAX(tblRiskRegister32[[#This Row],[Impact to Mission]:[Impact to Obligations]])*tblRiskRegister32[[#This Row],[Expectancy Score]],"") | P75: =tblRiskRegister32[[#This Row],[Risk Score]] | R75: 9.1 | S75: Ensure Use of Only Fully Supported Browsers and Email Clients | T75: Ensure only fully supported browsers and email clients are allowed to execute in the enterprise, only using the latest version of browsers and email clients provided through the vendor. | W75: =IFERROR(VLOOKUP(10*tblRiskRegister32[[#This Row],[Risk Treatment Safeguard Maturity Score]]+tblRiskRegister32[[#This Row],[VCDB Index]],tblHITIndexWeightTable[],4,FALSE),"") | X75: =VLOOKUP(tblRiskRegister32[[#This Row],[Asset Class]],tblInherentImpacts30[],2,FALSE) -> 3 | Y75: =VLOOKUP(tblRiskRegister32[[#This Row],[Asset Class]],tblInherentImpacts30[],3,FALSE) -> 4 | Z75: =VLOOKUP(tblRiskRegister32[[#This Row],[Asset Class]],tblInherentImpacts30[],3,FALSE) -> 4 | AA75: =VLOOKUP(tblRiskRegister32[[#This Row],[Asset Class]],tblInherentImpacts30[],4,FALSE) -> 1 | AB75: =IFERROR(MAX(tblRiskRegister32[[#This Row],[Risk Treatment Safeguard Impact to Mission]:[Risk Treatment Safeguard Impact to Obligations]])*tblRiskRegister32[[#This Row],[Risk Treatment Safeguard Expectancy Score]],"") | AC75: =IF(tblRiskRegister32[[#This Row],[Risk Score]]>AcceptableRisk,IF(tblRiskRegister32[[#This Row],[Risk Treatment Safeguard Risk Score]]<AcceptableRisk, IF(tblRiskRegister32[[#This Row],[Risk Treatment Safeguard Risk Score]]<=tblRiskRegister32[[#This Row],[Risk Score]],"Yes","No"),"No"),"Yes") -> No
... B80: Network | D80: 9.6 | E80: Block Unnecessary File Types | I80: =IFERROR(VLOOKUP(tblRiskRegister32[[#This Row],[Asset Class]],tblVCDBIndex[],4,FALSE),"") -> 1 | J80: =IFERROR(VLOOKUP(10*tblRiskRegister32[[#This Row],[Safeguard Maturity Score]]+tblRiskRegister32[[#This Row],[VCDB Index]],tblHITIndexWeightTable[],4,FALSE),"") | K80: =VLOOKUP(tblRiskRegister32[[#This Row],[Asset Class]],tblInherentImpacts30[],2,FALSE) -> 4 | L80: =VLOOKUP(tblRiskRegister32[[#This Row],[Asset Class]],tblInherentImpacts30[],3,FALSE) -> 5 | M80: =VLOOKUP(tblRiskRegister32[[#This Row],[Asset Class]],tblInherentImpacts30[],4,FALSE) -> 1 | N80: =VLOOKUP(tblRiskRegister32[[#This Row],[Asset Class]],tblInherentImpacts30[],5,FALSE) -> 5 | O80: =IFERROR(MAX(tblRiskRegister32[[#This Row],[Impact to Mission]:[Impact to Obligations]])*tblRiskRegister32[[#This Row],[Expectancy Score]],"") | P80: =tblRiskRegister32[[#This Row],[Risk Score]] | R80: 9.6 | S80: Block Unnecessary File Types | T80: Block unnecessary file types attempting to enter the enterprise’s email gateway. | W80: =IFERROR(VLOOKUP(10*tblRiskRegister32[[#This Row],[Risk Treatment Safeguard Maturity Score]]+tblRiskRegister32[[#This Row],[VCDB Index]],tblHITIndexWeightTable[],4,FALSE),"") | X80: =VLOOKUP(tblRiskRegister32[[#This Row],[Asset Class]],tblInherentImpacts30[],2,FALSE) -> 4 | Y80: =VLOOKUP(tblRiskRegister32[[#This Row],[Asset Class]],tblInherentImpacts30[],3,FALSE) -> 5 | Z80: =VLOOKUP(tblRiskRegister32[[#This Row],[Asset Class]],tblInherentImpacts30[],3,FALSE) -> 5 | AA80: =VLOOKUP(tblRiskRegister32[[#This Row],[Asset Class]],tblInherentImpacts30[],4,FALSE) -> 1 | AB80: =IFERROR(MAX(tblRiskRegister32[[#This Row],[Risk Treatment Safeguard Impact to Mission]:[Risk Treatment Safeguard Impact to Obligations]])*tblRiskRegister32[[#This Row],[Risk Treatment Safeguard Expectancy Score]],"") | AC80: =IF(tblRiskRegister32[[#This Row],[Risk Score]]>AcceptableRisk,IF(tblRiskRegister32[[#This Row],[Risk Treatment Safeguard Risk Score]]<AcceptableRisk, IF(tblRiskRegister32[[#This Row],[Risk Treatment Safeguard Risk Score]]<=tblRiskRegister32[[#This Row],[Risk Score]],"Yes","No"),"No"),"Yes") -> No
B81: Devices | C81: MIS 595 Focus | D81: 10.1 | E81: Deploy and Maintain Anti-Malware Software | F81: Anti-malware tools are deployed on all devices and centrally monitored to ensure continuous protection. | G81: No Vulnerability | H81: 5 | I81: =IFERROR(VLOOKUP(tblRiskRegister32[[#This Row],[Asset Class]],tblVCDBIndex[],4,FALSE),"") -> 1 | J81: =IFERROR(VLOOKUP(10*tblRiskRegister32[[#This Row],[Safeguard Maturity Score]]+tblRiskRegister32[[#This Row],[VCDB Index]],tblHITIndexWeightTable[],4,FALSE),"") -> 1 | K81: =VLOOKUP(tblRiskRegister32[[#This Row],[Asset Class]],tblInherentImpacts30[],2,FALSE) -> 3 | L81: =VLOOKUP(tblRiskRegister32[[#This Row],[Asset Class]],tblInherentImpacts30[],3,FALSE) -> 3 | M81: =VLOOKUP(tblRiskRegister32[[#This Row],[Asset Class]],tblInherentImpacts30[],4,FALSE) -> 1 | N81: =VLOOKUP(tblRiskRegister32[[#This Row],[Asset Class]],tblInherentImpacts30[],5,FALSE) -> 3 | O81: =IFERROR(MAX(tblRiskRegister32[[#This Row],[Impact to Mission]:[Impact to Obligations]])*tblRiskRegister32[[#This Row],[Expectancy Score]],"") -> 3 | P81: =tblRiskRegister32[[#This Row],[Risk Score]] -> 3 | Q81: Accept | R81: 10.1 | S81: Deploy and Maintain Anti-Malware Software | T81: Deploy and maintain anti-malware software on all enterprise assets. | W81: =IFERROR(VLOOKUP(10*tblRiskRegister32[[#This Row],[Risk Treatment Safeguard Maturity Score]]+tblRiskRegister32[[#This Row],[VCDB Index]],tblHITIndexWeightTable[],4,FALSE),"") | X81: =VLOOKUP(tblRiskRegister32[[#This Row],[Asset Class]],tblInherentImpacts30[],2,FALSE) -> 3 | Y81: =VLOOKUP(tblRiskRegister32[[#This Row],[Asset Class]],tblInherentImpacts30[],3,FALSE) -> 3 | Z81: =VLOOKUP(tblRiskRegister32[[#This Row],[Asset Class]],tblInherentImpacts30[],3,FALSE) -> 3 | AA81: =VLOOKUP(tblRiskRegister32[[#This Row],[Asset Class]],tblInherentImpacts30[],4,FALSE) -> 1 | AB81: =IFERROR(MAX(tblRiskRegister32[[#This Row],[Risk Treatment Safeguard Impact to Mission]:[Risk Treatment Safeguard Impact to Obligations]])*tblRiskRegister32[[#This Row],[Risk Treatment Safeguard Expectancy Score]],"") | AC81: =IF(tblRiskRegister32[[#This Row],[Risk Score]]>AcceptableRisk,IF(tblRiskRegister32[[#This Row],[Risk Treatment Safeguard Risk Score]]<AcceptableRisk, IF(tblRiskRegister32[[#This Row],[Risk Treatment Safeguard Risk Score]]<=tblRiskRegister32[[#This Row],[Risk Score]],"Yes","No"),"No"),"Yes") -> Yes
B82: Devices | C82: MIS 595 Focus | D82: 10.2 | E82: Configure Automatic Anti-Malware Signature Updates | F82: No control in place | G82: Anti-malware tools do not automatically update signatures, allowing outdated threat definitions to persist. | H82: 1 | I82: =IFERROR(VLOOKUP(tblRiskRegister32[[#This Row],[Asset Class]],tblVCDBIndex[],4,FALSE),"") -> 1 | J82: =IFERROR(VLOOKUP(10*tblRiskRegister32[[#This Row],[Safeguard Maturity Score]]+tblRiskRegister32[[#This Row],[VCDB Index]],tblHITIndexWeightTable[],4,FALSE),"") -> 4 | K82: =VLOOKUP(tblRiskRegister32[[#This Row],[Asset Class]],tblInherentImpacts30[],2,FALSE) -> 3 | L82: =VLOOKUP(tblRiskRegister32[[#This Row],[Asset Class]],tblInherentImpacts30[],3,FALSE) -> 3 | M82: =VLOOKUP(tblRiskRegister32[[#This Row],[Asset Class]],tblInherentImpacts30[],4,FALSE) -> 1 | N82: =VLOOKUP(tblRiskRegister32[[#This Row],[Asset Class]],tblInherentImpacts30[],5,FALSE) -> 3 | O82: =IFERROR(MAX(tblRiskRegister32[[#This Row],[Impact to Mission]:[Impact to Obligations]])*tblRiskRegister32[[#This Row],[Expectancy Score]],"") -> 12 | P82: =tblRiskRegister32[[#This Row],[Risk Score]] -> 12 | Q82: Reduce | R82: 10.2 | S82: Configure Automatic Anti-Malware Signature Updates | T82: Configure automatic updates for anti-malware signature files on all enterprise assets. | W82: =IFERROR(VLOOKUP(10*tblRiskRegister32[[#This Row],[Risk Treatment Safeguard Maturity Score]]+tblRiskRegister32[[#This Row],[VCDB Index]],tblHITIndexWeightTable[],4,FALSE),"") | X82: =VLOOKUP(tblRiskRegister32[[#This Row],[Asset Class]],tblInherentImpacts30[],2,FALSE) -> 3 | Y82: =VLOOKUP(tblRiskRegister32[[#This Row],[Asset Class]],tblInherentImpacts30[],3,FALSE) -> 3 | Z82: =VLOOKUP(tblRiskRegister32[[#This Row],[Asset Class]],tblInherentImpacts30[],3,FALSE) -> 3 | AA82: =VLOOKUP(tblRiskRegister32[[#This Row],[Asset Class]],tblInherentImpacts30[],4,FALSE) -> 1 | AB82: =IFERROR(MAX(tblRiskRegister32[[#This Row],[Risk Treatment Safeguard Impact to Mission]:[Risk Treatment Safeguard Impact to Obligations]])*tblRiskRegister32[[#This Row],[Risk Treatment Safeguard Expectancy Score]],"") | AC82: =IF(tblRiskRegister32[[#This Row],[Risk Score]]>AcceptableRisk,IF(tblRiskRegister32[[#This Row],[Risk Treatment Safeguard Risk Score]]<AcceptableRisk, IF(tblRiskRegister32[[#This Row],[Risk Treatment Safeguard Risk Score]]<=tblRiskRegister32[[#This Row],[Risk Score]],"Yes","No"),"No"),"Yes") -> No
B83: Devices | D83: 10.3 | E83: Disable Autorun and Autoplay for Removable Media | I83: =IFERROR(VLOOKUP(tblRiskRegister32[[#This Row],[Asset Class]],tblVCDBIndex[],4,FALSE),"") -> 1 | J83: =IFERROR(VLOOKUP(10*tblRiskRegister32[[#This Row],[Safeguard Maturity Score]]+tblRiskRegister32[[#This Row],[VCDB Index]],tblHITIndexWeightTable[],4,FALSE),"") | K83: =VLOOKUP(tblRiskRegister32[[#This Row],[Asset Class]],tblInherentImpacts30[],2,FALSE) -> 3 | L83: =VLOOKUP(tblRiskRegister32[[#This Row],[Asset Class]],tblInherentImpacts30[],3,FALSE) -> 3 | M83: =VLOOKUP(tblRiskRegister32[[#This Row],[Asset Class]],tblInherentImpacts30[],4,FALSE) -> 1 | N83: =VLOOKUP(tblRiskRegister32[[#This Row],[Asset Class]],tblInherentImpacts30[],5,FALSE) -> 3 | O83: =IFERROR(MAX(tblRiskRegister32[[#This Row],[Impact to Mission]:[Impact to Obligations]])*tblRiskRegister32[[#This Row],[Expectancy Score]],"") | P83: =tblRiskRegister32[[#This Row],[Risk Score]] | R83: 10.3 | S83: Disable Autorun and Autoplay for Removable Media | T83: Disable autorun and autoplay auto-execute functionality for removable media. | W83: =IFERROR(VLOOKUP(10*tblRiskRegister32[[#This Row],[Risk Treatment Safeguard Maturity Score]]+tblRiskRegister32[[#This Row],[VCDB Index]],tblHITIndexWeightTable[],4,FALSE),"") | X83: =VLOOKUP(tblRiskRegister32[[#This Row],[Asset Class]],tblInherentImpacts30[],2,FALSE) -> 3 | Y83: =VLOOKUP(tblRiskRegister32[[#This Row],[Asset Class]],tblInherentImpacts30[],3,FALSE) -> 3 | Z83: =VLOOKUP(tblRiskRegister32[[#This Row],[Asset Class]],tblInherentImpacts30[],3,FALSE) -> 3 | AA83: =VLOOKUP(tblRiskRegister32[[#This Row],[Asset Class]],tblInherentImpacts30[],4,FALSE) -> 1 | AB83: =IFERROR(MAX(tblRiskRegister32[[#This Row],[Risk Treatment Safeguard Impact to Mission]:[Risk Treatment Safeguard Impact to Obligations]])*tblRiskRegister32[[#This Row],[Risk Treatment Safeguard Expectancy Score]],"") | AC83: =IF(tblRiskRegister32[[#This Row],[Risk Score]]>AcceptableRisk,IF(tblRiskRegister32[[#This Row],[Risk Treatment Safeguard Risk Score]]<AcceptableRisk, IF(tblRiskRegister32[[#This Row],[Risk Treatment Safeguard Risk Score]]<=tblRiskRegister32[[#This Row],[Risk Score]],"Yes","No"),"No"),"Yes") -> No
B84: Devices | D84: 10.4 | E84: Configure Automatic Anti-Malware Scanning of Removable Media | I84: =IFERROR(VLOOKUP(tblRiskRegister32[[#This Row],[Asset Class]],tblVCDBIndex[],4,FALSE),"") -> 1 | J84: =IFERROR(VLOOKUP(10*tblRiskRegister32[[#This Row],[Safeguard Maturity Score]]+tblRiskRegister32[[#This Row],[VCDB Index]],tblHITIndexWeightTable[],4,FALSE),"") | K84: =VLOOKUP(tblRiskRegister32[[#This Row],[Asset Class]],tblInherentImpacts30[],2,FALSE) -> 3 | L84: =VLOOKUP(tblRiskRegister32[[#This Row],[Asset Class]],tblInherentImpacts30[],3,FALSE) -> 3 | M84: =VLOOKUP(tblRiskRegister32[[#This Row],[Asset Class]],tblInherentImpacts30[],4,FALSE) -> 1 | N84: =VLOOKUP(tblRiskRegister32[[#This Row],[Asset Class]],tblInherentImpacts30[],5,FALSE) -> 3 | O84: =IFERROR(MAX(tblRiskRegister32[[#This Row],[Impact to Mission]:[Impact to Obligations]])*tblRiskRegister32[[#This Row],[Expectancy Score]],"") | P84: =tblRiskRegister32[[#This Row],[Risk Score]] | R84: 10.4 | S84: Configure Automatic Anti-Malware Scanning of Removable Media | T84: Configure anti-malware software to automatically scan removable media. | W84: =IFERROR(VLOOKUP(10*tblRiskRegister32[[#This Row],[Risk Treatment Safeguard Maturity Score]]+tblRiskRegister32[[#This Row],[VCDB Index]],tblHITIndexWeightTable[],4,FALSE),"") | X84: =VLOOKUP(tblRiskRegister32[[#This Row],[Asset Class]],tblInherentImpacts30[],2,FALSE) -> 3 | Y84: =VLOOKUP(tblRiskRegister32[[#This Row],[Asset Class]],tblInherentImpacts30[],3,FALSE) -> 3 | Z84: =VLOOKUP(tblRiskRegister32[[#This Row],[Asset Class]],tblInherentImpacts30[],3,FALSE) -> 3 | AA84: =VLOOKUP(tblRiskRegister32[[#This Row],[Asset Class]],tblInherentImpacts30[],4,FALSE) -> 1 | AB84: =IFERROR(MAX(tblRiskRegister32[[#This Row],[Risk Treatment Safeguard Impact to Mission]:[Risk Treatment Safeguard Impact to Obligations]])*tblRiskRegister32[[#This Row],[Risk Treatment Safeguard Expectancy Score]],"") | AC84: =IF(tblRiskRegister32[[#This Row],[Risk Score]]>AcceptableRisk,IF(tblRiskRegister32[[#This Row],[Risk Treatment Safeguard Risk Score]]<AcceptableRisk, IF(tblRiskRegister32[[#This Row],[Risk Treatment Safeguard Risk Score]]<=tblRiskRegister32[[#This Row],[Risk Score]],"Yes","No"),"No"),"Yes") -> No
B85: Devices | D85: 10.5 | E85: Enable Anti-Exploitation Features | I85: =IFERROR(VLOOKUP(tblRiskRegister32[[#This Row],[Asset Class]],tblVCDBIndex[],4,FALSE),"") -> 1 | J85: =IFERROR(VLOOKUP(10*tblRiskRegister32[[#This Row],[Safeguard Maturity Score]]+tblRiskRegister32[[#This Row],[VCDB Index]],tblHITIndexWeightTable[],4,FALSE),"") | K85: =VLOOKUP(tblRiskRegister32[[#This Row],[Asset Class]],tblInherentImpacts30[],2,FALSE) -> 3 | L85: =VLOOKUP(tblRiskRegister32[[#This Row],[Asset Class]],tblInherentImpacts30[],3,FALSE) -> 3 | M85: =VLOOKUP(tblRiskRegister32[[#This Row],[Asset Class]],tblInherentImpacts30[],4,FALSE) -> 1 | N85: =VLOOKUP(tblRiskRegister32[[#This Row],[Asset Class]],tblInherentImpacts30[],5,FALSE) -> 3 | O85: =IFERROR(MAX(tblRiskRegister32[[#This Row],[Impact to Mission]:[Impact to Obligations]])*tblRiskRegister32[[#This Row],[Expectancy Score]],"") | P85: =tblRiskRegister32[[#This Row],[Risk Score]] | R85: 10.5 | S85: Enable Anti-Exploitation Features | T85: Enable anti-exploitation features on enterprise assets and software, where possible, such as Microsoft® Data Execution Prevention (DEP), Windows® Defender Exploit Guard (WDEG), or Apple® System Integrity Protection (SIP) and Gatekeeper™. | W85: =IFERROR(VLOOKUP(10*tblRiskRegister32[[#This Row],[Risk Treatment Safeguard Maturity Score]]+tblRiskRegister32[[#This Row],[VCDB Index]],tblHITIndexWeightTable[],4,FALSE),"") | X85: =VLOOKUP(tblRiskRegister32[[#This Row],[Asset Class]],tblInherentImpacts30[],2,FALSE) -> 3 | Y85: =VLOOKUP(tblRiskRegister32[[#This Row],[Asset Class]],tblInherentImpacts30[],3,FALSE) -> 3 | Z85: =VLOOKUP(tblRiskRegister32[[#This Row],[Asset Class]],tblInherentImpacts30[],3,FALSE) -> 3 | AA85: =VLOOKUP(tblRiskRegister32[[#This Row],[Asset Class]],tblInherentImpacts30[],4,FALSE) -> 1 | AB85: =IFERROR(MAX(tblRiskRegister32[[#This Row],[Risk Treatment Safeguard Impact to Mission]:[Risk Treatment Safeguard Impact to Obligations]])*tblRiskRegister32[[#This Row],[Risk Treatment Safeguard Expectancy Score]],"") | AC85: =IF(tblRiskRegister32[[#This Row],[Risk Score]]>AcceptableRisk,IF(tblRiskRegister32[[#This Row],[Risk Treatment Safeguard Risk Score]]<AcceptableRisk, IF(tblRiskRegister32[[#This Row],[Risk Treatment Safeguard Risk Score]]<=tblRiskRegister32[[#This Row],[Risk Score]],"Yes","No"),"No"),"Yes") -> No
B86: Devices | D86: 10.6 | E86: Centrally Manage Anti-Malware Software | I86: =IFERROR(VLOOKUP(tblRiskRegister32[[#This Row],[Asset Class]],tblVCDBIndex[],4,FALSE),"") -> 1 | J86: =IFERROR(VLOOKUP(10*tblRiskRegister32[[#This Row],[Safeguard Maturity Score]]+tblRiskRegister32[[#This Row],[VCDB Index]],tblHITIndexWeightTable[],4,FALSE),"") | K86: =VLOOKUP(tblRiskRegister32[[#This Row],[Asset Class]],tblInherentImpacts30[],2,FALSE) -> 3 | L86: =VLOOKUP(tblRiskRegister32[[#This Row],[Asset Class]],tblInherentImpacts30[],3,FALSE) -> 3 | M86: =VLOOKUP(tblRiskRegister32[[#This Row],[Asset Class]],tblInherentImpacts30[],4,FALSE) -> 1 | N86: =VLOOKUP(tblRiskRegister32[[#This Row],[Asset Class]],tblInherentImpacts30[],5,FALSE) -> 3 | O86: =IFERROR(MAX(tblRiskRegister32[[#This Row],[Impact to Mission]:[Impact to Obligations]])*tblRiskRegister32[[#This Row],[Expectancy Score]],"") | P86: =tblRiskRegister32[[#This Row],[Risk Score]] | R86: 10.6 | S86: Centrally Manage Anti-Malware Software | T86: Centrally manage anti-malware software. | W86: =IFERROR(VLOOKUP(10*tblRiskRegister32[[#This Row],[Risk Treatment Safeguard Maturity Score]]+tblRiskRegister32[[#This Row],[VCDB Index]],tblHITIndexWeightTable[],4,FALSE),"") | X86: =VLOOKUP(tblRiskRegister32[[#This Row],[Asset Class]],tblInherentImpacts30[],2,FALSE) -> 3 | Y86: =VLOOKUP(tblRiskRegister32[[#This Row],[Asset Class]],tblInherentImpacts30[],3,FALSE) -> 3 | Z86: =VLOOKUP(tblRiskRegister32[[#This Row],[Asset Class]],tblInherentImpacts30[],3,FALSE) -> 3 | AA86: =VLOOKUP(tblRiskRegister32[[#This Row],[Asset Class]],tblInherentImpacts30[],4,FALSE) -> 1 | AB86: =IFERROR(MAX(tblRiskRegister32[[#This Row],[Risk Treatment Safeguard Impact to Mission]:[Risk Treatment Safeguard Impact to Obligations]])*tblRiskRegister32[[#This Row],[Risk Treatment Safeguard Expectancy Score]],"") | AC86: =IF(tblRiskRegister32[[#This Row],[Risk Score]]>AcceptableRisk,IF(tblRiskRegister32[[#This Row],[Risk Treatment Safeguard Risk Score]]<AcceptableRisk, IF(tblRiskRegister32[[#This Row],[Risk Treatment Safeguard Risk Score]]<=tblRiskRegister32[[#This Row],[Risk Score]],"Yes","No"),"No"),"Yes") -> No
B87: Devices | D87: 10.7 | E87: Use Behavior-Based Anti-Malware Software | I87: =IFERROR(VLOOKUP(tblRiskRegister32[[#This Row],[Asset Class]],tblVCDBIndex[],4,FALSE),"") -> 1 | J87: =IFERROR(VLOOKUP(10*tblRiskRegister32[[#This Row],[Safeguard Maturity Score]]+tblRiskRegister32[[#This Row],[VCDB Index]],tblHITIndexWeightTable[],4,FALSE),"") | K87: =VLOOKUP(tblRiskRegister32[[#This Row],[Asset Class]],tblInherentImpacts30[],2,FALSE) -> 3 | L87: =VLOOKUP(tblRiskRegister32[[#This Row],[Asset Class]],tblInherentImpacts30[],3,FALSE) -> 3 | M87: =VLOOKUP(tblRiskRegister32[[#This Row],[Asset Class]],tblInherentImpacts30[],4,FALSE) -> 1 | N87: =VLOOKUP(tblRiskRegister32[[#This Row],[Asset Class]],tblInherentImpacts30[],5,FALSE) -> 3 | O87: =IFERROR(MAX(tblRiskRegister32[[#This Row],[Impact to Mission]:[Impact to Obligations]])*tblRiskRegister32[[#This Row],[Expectancy Score]],"") | P87: =tblRiskRegister32[[#This Row],[Risk Score]] | R87: 10.7 | S87: Use Behavior-Based Anti-Malware Software | T87: Use behavior-based anti-malware software. | W87: =IFERROR(VLOOKUP(10*tblRiskRegister32[[#This Row],[Risk Treatment Safeguard Maturity Score]]+tblRiskRegister32[[#This Row],[VCDB Index]],tblHITIndexWeightTable[],4,FALSE),"") | X87: =VLOOKUP(tblRiskRegister32[[#This Row],[Asset Class]],tblInherentImpacts30[],2,FALSE) -> 3 | Y87: =VLOOKUP(tblRiskRegister32[[#This Row],[Asset Class]],tblInherentImpacts30[],3,FALSE) -> 3 | Z87: =VLOOKUP(tblRiskRegister32[[#This Row],[Asset Class]],tblInherentImpacts30[],3,FALSE) -> 3 | AA87: =VLOOKUP(tblRiskRegister32[[#This Row],[Asset Class]],tblInherentImpacts30[],4,FALSE) -> 1 | AB87: =IFERROR(MAX(tblRiskRegister32[[#This Row],[Risk Treatment Safeguard Impact to Mission]:[Risk Treatment Safeguard Impact to Obligations]])*tblRiskRegister32[[#This Row],[Risk Treatment Safeguard Expectancy Score]],"") | AC87: =IF(tblRiskRegister32[[#This Row],[Risk Score]]>AcceptableRisk,IF(tblRiskRegister32[[#This Row],[Risk Treatment Safeguard Risk Score]]<AcceptableRisk, IF(tblRiskRegister32[[#This Row],[Risk Treatment Safeguard Risk Score]]<=tblRiskRegister32[[#This Row],[Risk Score]],"Yes","No"),"No"),"Yes") -> No
B88: Data | D88: 11.1 | E88: Establish and Maintain a Data Recovery Process | I88: =IFERROR(VLOOKUP(tblRiskRegister32[[#This Row],[Asset Class]],tblVCDBIndex[],4,FALSE),"") -> 3 | J88: =IFERROR(VLOOKUP(10*tblRiskRegister32[[#This Row],[Safeguard Maturity Score]]+tblRiskRegister32[[#This Row],[VCDB Index]],tblHITIndexWeightTable[],4,FALSE),"") | K88: =VLOOKUP(tblRiskRegister32[[#This Row],[Asset Class]],tblInherentImpacts30[],2,FALSE) -> 4 | L88: =VLOOKUP(tblRiskRegister32[[#This Row],[Asset Class]],tblInherentImpacts30[],3,FALSE) -> 4 | M88: =VLOOKUP(tblRiskRegister32[[#This Row],[Asset Class]],tblInherentImpacts30[],4,FALSE) -> 1 | N88: =VLOOKUP(tblRiskRegister32[[#This Row],[Asset Class]],tblInherentImpacts30[],5,FALSE) -> 4 | O88: =IFERROR(MAX(tblRiskRegister32[[#This Row],[Impact to Mission]:[Impact to Obligations]])*tblRiskRegister32[[#This Row],[Expectancy Score]],"") | P88: =tblRiskRegister32[[#This Row],[Risk Score]] | R88: 11.1 | S88: Establish and Maintain a Data Recovery Process | T88: Establish and maintain a data recovery process. In the process, address the scope of data recovery activities, recovery prioritization, and the security of backup data. Review and update documentation annually, or when significant enterprise changes occur that could impact this Safeguard. | W88: =IFERROR(VLOOKUP(10*tblRiskRegister32[[#This Row],[Risk Treatment Safeguard Maturity Score]]+tblRiskRegister32[[#This Row],[VCDB Index]],tblHITIndexWeightTable[],4,FALSE),"") | X88: =VLOOKUP(tblRiskRegister32[[#This Row],[Asset Class]],tblInherentImpacts30[],2,FALSE) -> 4 | Y88: =VLOOKUP(tblRiskRegister32[[#This Row],[Asset Class]],tblInherentImpacts30[],3,FALSE) -> 4 | Z88: =VLOOKUP(tblRiskRegister32[[#This Row],[Asset Class]],tblInherentImpacts30[],3,FALSE) -> 4 | AA88: =VLOOKUP(tblRiskRegister32[[#This Row],[Asset Class]],tblInherentImpacts30[],4,FALSE) -> 1 | AB88: =IFERROR(MAX(tblRiskRegister32[[#This Row],[Risk Treatment Safeguard Impact to Mission]:[Risk Treatment Safeguard Impact to Obligations]])*tblRiskRegister32[[#This Row],[Risk Treatment Safeguard Expectancy Score]],"") | AC88: =IF(tblRiskRegister32[[#This Row],[Risk Score]]>AcceptableRisk,IF(tblRiskRegister32[[#This Row],[Risk Treatment Safeguard Risk Score]]<AcceptableRisk, IF(tblRiskRegister32[[#This Row],[Risk Treatment Safeguard Risk Score]]<=tblRiskRegister32[[#This Row],[Risk Score]],"Yes","No"),"No"),"Yes") -> No
B89: Data | C89: MIS 595 Focus | D89: 11.2 | E89: Perform Automated Backups | F89: No control in place | G89: Backups are not automated, increasing the risk of incomplete or inconsistent backup sets. | H89: 1 | I89: =IFERROR(VLOOKUP(tblRiskRegister32[[#This Row],[Asset Class]],tblVCDBIndex[],4,FALSE),"") -> 3 | J89: =IFERROR(VLOOKUP(10*tblRiskRegister32[[#This Row],[Safeguard Maturity Score]]+tblRiskRegister32[[#This Row],[VCDB Index]],tblHITIndexWeightTable[],4,FALSE),"") -> 5 | K89: =VLOOKUP(tblRiskRegister32[[#This Row],[Asset Class]],tblInherentImpacts30[],2,FALSE) -> 4 | L89: =VLOOKUP(tblRiskRegister32[[#This Row],[Asset Class]],tblInherentImpacts30[],3,FALSE) -> 4 | M89: =VLOOKUP(tblRiskRegister32[[#This Row],[Asset Class]],tblInherentImpacts30[],4,FALSE) -> 1 | N89: =VLOOKUP(tblRiskRegister32[[#This Row],[Asset Class]],tblInherentImpacts30[],5,FALSE) -> 4 | O89: =IFERROR(MAX(tblRiskRegister32[[#This Row],[Impact to Mission]:[Impact to Obligations]])*tblRiskRegister32[[#This Row],[Expectancy Score]],"") -> 20 | P89: =tblRiskRegister32[[#This Row],[Risk Score]] -> 20 | Q89: Reduce | R89: 11.2 | S89: Perform Automated Backups | T89: Perform automated backups of in-scope enterprise assets. Run backups weekly, or more frequently, based on the sensitivity of the data. | W89: =IFERROR(VLOOKUP(10*tblRiskRegister32[[#This Row],[Risk Treatment Safeguard Maturity Score]]+tblRiskRegister32[[#This Row],[VCDB Index]],tblHITIndexWeightTable[],4,FALSE),"") | X89: =VLOOKUP(tblRiskRegister32[[#This Row],[Asset Class]],tblInherentImpacts30[],2,FALSE) -> 4 | Y89: =VLOOKUP(tblRiskRegister32[[#This Row],[Asset Class]],tblInherentImpacts30[],3,FALSE) -> 4 | Z89: =VLOOKUP(tblRiskRegister32[[#This Row],[Asset Class]],tblInherentImpacts30[],3,FALSE) -> 4 | AA89: =VLOOKUP(tblRiskRegister32[[#This Row],[Asset Class]],tblInherentImpacts30[],4,FALSE) -> 1 | AB89: =IFERROR(MAX(tblRiskRegister32[[#This Row],[Risk Treatment Safeguard Impact to Mission]:[Risk Treatment Safeguard Impact to Obligations]])*tblRiskRegister32[[#This Row],[Risk Treatment Safeguard Expectancy Score]],"") | AC89: =IF(tblRiskRegister32[[#This Row],[Risk Score]]>AcceptableRisk,IF(tblRiskRegister32[[#This Row],[Risk Treatment Safeguard Risk Score]]<AcceptableRisk, IF(tblRiskRegister32[[#This Row],[Risk Treatment Safeguard Risk Score]]<=tblRiskRegister32[[#This Row],[Risk Score]],"Yes","No"),"No"),"Yes") -> No
